Workbook
Name Periodo: #REF!
Name OwnerMeter: #REF!
Name owner: ECxDpto!$A$9
Name fecha: CuECxDpto!$G$3
Name department: EC!$E$9
Name Soles: #REF!
Name OwnerDpto: #REF!
Name owner: EC!$A$9
Name owner: CuECxDpto!$A$9
Name meter: ECxDpto!$G$9
Name Consumo: #REF!
Name meter: CuECxDpto!$G$9
Name meter: EC!$G$9
Name fecha: EC!$G$3
Name DPTOS: Deuda!$A$4:$A$64
Name fecha: ECxDpto!$G$3

Sheet Calculo Gas
F2: CALCULO DE GAS 2024 | T2: CALCULO DE GAS 2025 | BD2: 2026
E3: COSTO UNIT | G3: =Consumo!$E$7/'Calculo Gas'!$F$66 -> 22.335927 | I3: =Consumo!E10/'Calculo Gas'!H66 -> 17.86569 | K3: =Consumo!E13/J66 -> 12.160825 | M3: =Consumo!E17/'Calculo Gas'!L66 -> 15.610637 | O3: =Consumo!E21/'Calculo Gas'!N66 -> 15.196672 | Q3: =Consumo!E25/P66 -> 14.840947 | S3: =Consumo!E30/R66 -> 16.571528 | U3: =Consumo!E34/T66 -> 17.562064 | W3: =Consumo!E37/V66 -> 12.223474 | Y3: =Consumo!E40/X66 -> 12.134376 | AA3: =Consumo!E44/'Calculo Gas'!Z66 -> 14.086322 | AC3: =Consumo!E48/'Calculo Gas'!AB66 -> 12.847039 | AE3: =Consumo!E52/'Calculo Gas'!AD66 -> 12.578186 | AG3: =Consumo!E57/'Calculo Gas'!AF66 -> 14.247901 | AI3: =Consumo!E62/'Calculo Gas'!AH66 -> 13.913957 | AK3: =Consumo!E67/'Calculo Gas'!AJ66 -> 14.407739 | AM3: =Consumo!E71/'Calculo Gas'!AL66 -> 9.9288235 | AO3: =Consumo!E76/'Calculo Gas'!AN66 -> 16.262939 | AQ3: =Consumo!E80/'Calculo Gas'!AP66 -> 13.32323 | AS3: =Consumo!E84/'Calculo Gas'!AR66 -> 11.816926 | AU3: =Consumo!E88/'Calculo Gas'!AT66 -> 12.025193 | AW3: =Consumo!E93/'Calculo Gas'!AV66 -> 12.258453 | AY3: =Consumo!E97/'Calculo Gas'!AX66 -> 11.604064 | BA3: =Consumo!E102/'Calculo Gas'!AZ66 -> 13.804031 | BC3: =Consumo!E107/'Calculo Gas'!BB66 -> 14.985666 | BE3: =Consumo!E113/'Calculo Gas'!BD66 -> 21.615018 | BG3: =Consumo!U80/'Calculo Gas'!BF66 -> #DIV/0! | BI3: =Consumo!W80/'Calculo Gas'!BH66 -> #DIV/0! | BK3: =Consumo!Y80/'Calculo Gas'!BJ66 -> #DIV/0! | BM3: =Consumo!AA80/'Calculo Gas'!BL66 -> #DIV/0! | BO3: =Consumo!AC80/'Calculo Gas'!BN66 -> #DIV/0!
A4: Pago total x mes | B4: Consumo del mes | C4: Departam. | D4: Nombre | E4: Número de Medidor | F4: Consumo Junio | G4: Consumo Junio | H4: Consumo Julio | I4: Consumo Julio | J4: Consumo Agosto | K4: Consumo Agosto | L4: Consumo Setiembre | M4: Consumo Setiembre | N4: Consumo Octubre | O4: Consumo Octubre | P4: Consumo Noviembre | Q4: Consumo Noviembre | R4: Consumo Diciembre | S4: Consumo Diciembre | T4: Consumo ENERO | U4: Consumo ENERO | V4: Consumo FEBRERO | W4: Consumo FEBRERO | X4: Consumo MARZO | Y4: Consumo MARZO | Z4: Consumo ABRIL | AA4: Consumo ABRIL | AB4: Consumo MAYO | AC4: Consumo MAYO | AD4: Consumo Junio | AE4: Consumo Junio | AF4: Consumo Julio | AG4: Consumo Julio | AH4: Consumo Agosto | AI4: Consumo Agosto | AJ4: Consumo Setiembre | AK4: Consumo Setiembre | AL4: Consumo Octubre | AM4: Consumo Octubre | AN4: Consumo Noviembre | AO4: Consumo Noviembre | AP4: Consumo Diciembre | AQ4: Consumo Diciembre | AR4: Consumo Enero | AS4: Consumo Enero | AT4: Consumo Febrero | AU4: Consumo Febrero | AV4: Consumo Marzo | AW4: Consumo Marzo | AX4: Consumo Abril | AY4: Consumo Abril | AZ4: Consumo Mayo | BA4: Consumo Mayo | BB4: Consumo Junio | BC4: Consumo Junio | BD4: Consumo Julio | BE4: Consumo Julio | BF4: Agosto | BG4: Agosto | BH4: Septiembre | BI4: Septiembre | BJ4: Octubre | BK4: Octubre | BL4: Noviembre | BM4: Noviembre | BN4: Diciembre | BO4: Diciembre
F5: m3 | G5: Soles | H5: m3 | I5: Soles | J5: m3 | K5: Soles | L5: m3 | M5: Soles | N5: m3 | O5: Soles | P5: m3 | Q5: Soles | R5: m3 | S5: Soles | T5: m3 | U5: Soles | V5: m3 | W5: Soles | X5: m3 | Y5: Soles | Z5: m3 | AA5: Soles | AB5: m3 | AC5: Soles | AD5: m3 | AE5: Soles | AF5: m3 | AG5: Soles | AH5: m3 | AI5: Soles | AJ5: m3 | AK5: Soles | AL5: m3 | AM5: Soles | AN5: m3 | AO5: Soles | AP5: m3 | AQ5: Soles | AR5: m3 | AS5: Soles | AT5: m3 | AU5: Soles | AV5: m3 | AW5: Soles | AX5: m3 | AY5: Soles | AZ5: m3 | BA5: Soles | BB5: m3 | BC5: Soles | BD5: m3 | BE5: Soles | BF5: m3 | BG5: Soles | BH5: m3 | BI5: Soles | BJ5: m3 | BK5: Soles | BL5: m3 | BM5: Soles | BN5: m3 | BO5: Soles
A6: =ROUND(AG6,1) -> 12.5 | B6: =AF6 -> 0.876 | C6: 201 | D6: HUGO LUCIO ADUVIRE PATACA | E6: 2034049 | F6: =Lecturas!D4-Lecturas!C4 -> 0.754 | G6: =F6*$G$3 -> 16.841289 | H6: =IF((Lecturas!E4-Lecturas!D4) < 0, "", Lecturas!E4-Lecturas!D4) -> 0.611 | I6: =IFERROR(H6*$I$3,"") -> 10.915936 | J6: =IF(OR((Lecturas!F4-Lecturas!E4) <= 0), "", Lecturas!F4-Lecturas!E4) -> 0.601 | K6: =IFERROR(J6*$K$3,"") -> 7.3086558 | L6: =IF(OR((Lecturas!G4-Lecturas!F4) <= 0), "", Lecturas!G4-Lecturas!F4) -> 0.867 | M6: =IFERROR(L6*$M$3,"") -> 13.534422 | N6: =IF(OR((Lecturas!H4-Lecturas!G4) <= 0), "", Lecturas!H4-Lecturas!G4) -> 0.583 | O6: =IFERROR(N6*$O$3,"") -> 8.8596599 | P6: =IF(OR((Lecturas!I4-Lecturas!H4) <= 0), "", Lecturas!I4-Lecturas!H4) -> 0.663 | Q6: =IFERROR(P6*$Q$3,"") -> 9.8395478 | R6: =IF(OR((Lecturas!J4-Lecturas!I4) <= 0), "", Lecturas!J4-Lecturas!I4) -> 0.502 | S6: =IFERROR(R6*$S$3,"") -> 8.3189069 | T6: =IF(OR((Lecturas!K4-Lecturas!J4) <= 0), "", Lecturas!K4-Lecturas!J4) -> 0.359 | U6: =IFERROR(T6*$U$3,"") -> 6.3047809 | V6: =IF(OR((Lecturas!L4-Lecturas!K4) <= 0), "", Lecturas!L4-Lecturas!K4) -> 0.394 | W6: =IFERROR(V6*$W$3,"") -> 4.8160489 | X6: =IF(OR((Lecturas!M4-Lecturas!L4) < 0), "", Lecturas!M4-Lecturas!L4) -> 0.181 | Y6: =IFERROR(X6*$Y$3,"") -> 2.1963221 | Z6: =IF(OR((Lecturas!N4-Lecturas!M4) <= 0), "", Lecturas!N4-Lecturas!M4) -> 0.496 | AA6: =IFERROR(Z6*$AA$3,"") -> 6.9868155 | AB6: =IF(OR((Lecturas!O4-Lecturas!N4) < 0), "", Lecturas!O4-Lecturas!N4) -> 0.901 | AC6: =IFERROR(AB6*$AC$3,"") -> 11.575182 | AD6: =IF(OR((Lecturas!P4-Lecturas!O4) < 0), "", Lecturas!P4-Lecturas!O4) -> 0.966 | AE6: =IFERROR(AD6*$AE$3,"") -> 12.150528 | AF6: =IF((Lecturas!Q4-Lecturas!P4)<= 0,"",Lecturas!Q4-Lecturas!P4) -> 0.876 | AG6: =IFERROR(AF6*$AG$3,"") -> 12.481161 | AH6: =IF((Lecturas!R4-Lecturas!Q4)<= 0,"",Lecturas!R4-Lecturas!Q4) -> 0.735 | AI6: =IFERROR(AH6*$AI$3,"") -> 10.226758 | AJ6: =IF((Lecturas!S4-Lecturas!R4)<= 0,"",Lecturas!S4-Lecturas!R4) -> 0.894 | AK6: =IFERROR(AJ6*$AK$3,"") -> 12.880519 | AL6: =IF((Lecturas!T4-Lecturas!S4)<= 0,"",Lecturas!T4-Lecturas!S4) -> 1.271 | AM6: =IFERROR(AL6*$AM$3,"") -> 12.619535 | AN6: =IF((Lecturas!U4-Lecturas!T4)<= 0,"",Lecturas!U4-Lecturas!T4) -> 0.102 | AO6: =IFERROR(AN6*$AO$3,"") -> 1.6588198 | AP6: =IF((Lecturas!V4-Lecturas!U4)<= 0,"",Lecturas!V4-Lecturas!U4) -> 0.043 | AQ6: =IFERROR(AP6*$AQ$3,"") -> 0.57289888 | AR6: =IF((Lecturas!W4-Lecturas!V4)<= 0,"",Lecturas!W4-Lecturas!V4) -> 0.215 | AS6: =IFERROR(AR6*$AS$3,"") -> 2.5406391 | AT6: =IF((Lecturas!X4-Lecturas!W4)<= 0,"",Lecturas!X4-Lecturas!W4) -> 0.128 | AU6: =IFERROR(AT6*$AU$3,"") -> 1.5392247 | AV6: =IF((Lecturas!Y4-Lecturas!X4)<= 0,"",Lecturas!Y4-Lecturas!X4) -> 0.087 | AW6: =IFERROR(AV6*$AW$3,"") -> 1.0664854 | AX6: =IF((Lecturas!Z4-Lecturas!Y4)<= 0,"0",Lecturas!Z4-Lecturas!Y4) -> 0.218 | AY6: =IFERROR(AX6*$AY$3,"0") -> 2.529686 | AZ6: =IF((Lecturas!AA4-Lecturas!Z4)<= 0,"0",Lecturas!AA4-Lecturas!Z4) -> 0.187 | BA6: =IFERROR(AZ6*$BA$3,"0") -> 2.5813538 | BB6: =IF((Lecturas!AB4-Lecturas!AA4)<= 0,"0",Lecturas!AB4-Lecturas!AA4) -> 0.094 | BC6: =IFERROR(BB6*$BC$3,"0") -> 1.4086526 | BD6: =IF((Lecturas!AC4-Lecturas!AB4)<= 0,"0",Lecturas!AC4-Lecturas!AB4) -> 0.254 | BE6: =IFERROR(BD6*$BE$3,"0") -> 5.4902145 | BF6: =IF((Lecturas!AD4-Lecturas!AC4)<= 0,"0",Lecturas!AD4-Lecturas!AC4) -> 0 | BG6: =IFERROR(BF6*$BG$3,"0") -> 0 | BH6: =IF((Lecturas!AE4-Lecturas!AD4)<= 0,"0",Lecturas!AE4-Lecturas!AD4) -> 0 | BI6: =IFERROR(BH6*$BI$3,"0") -> 0 | BJ6: =IF((Lecturas!AF4-Lecturas!AE4)<= 0,"0",Lecturas!AF4-Lecturas!AE4) -> 0 | BK6: =IFERROR(BJ6*$BK$3,"0") -> 0 | BL6: =IF((Lecturas!AG4-Lecturas!AF4)<= 0,"0",Lecturas!AG4-Lecturas!AF4) -> 0 | BM6: =IFERROR(BL6*$BM$3,"0") -> 0 | BN6: =IF((Lecturas!AH4-Lecturas!AG4)<= 0,"0",Lecturas!AH4-Lecturas!AG4) -> 0 | BO6: =IFERROR(BN6*$BO$3,"0") -> 0
A7: =ROUND(AG7,1) -> 22.3 | B7: =AF7 -> 1.564 | C7: 202 | D7: ELISABETH POTERICO HUAMAYALLI | E7: 2034056 | F7: =Lecturas!D5-Lecturas!C5 -> 0.847 | G7: =F7*$G$3 -> 18.91853 | H7: =IF((Lecturas!E5-Lecturas!D5) < 0, "", Lecturas!E5-Lecturas!D5) -> 0.608 | I7: =IFERROR(H7*$I$3,"") -> 10.862339 | J7: =IF(OR((Lecturas!F5-Lecturas!E5) <= 0), "", Lecturas!F5-Lecturas!E5) -> 0.915 | K7: =IFERROR(J7*$K$3,"") -> 11.127155 | L7: =IF(OR((Lecturas!G5-Lecturas!F5) <= 0), "", Lecturas!G5-Lecturas!F5) -> 0.576 | M7: =IFERROR(L7*$M$3,"") -> 8.9917267 | N7: =IF(OR((Lecturas!H5-Lecturas!G5) <= 0), "", Lecturas!H5-Lecturas!G5) -> 0.738 | O7: =IFERROR(N7*$O$3,"") -> 11.215144 | P7: =IF(OR((Lecturas!I5-Lecturas!H5) <= 0), "", Lecturas!I5-Lecturas!H5) -> 0.701 | Q7: =IFERROR(P7*$Q$3,"") -> 10.403504 | R7: =IF(OR((Lecturas!J5-Lecturas!I5) <= 0), "", Lecturas!J5-Lecturas!I5) -> 0.189 | S7: =IFERROR(R7*$S$3,"") -> 3.1320187 | T7: =IF(OR((Lecturas!K5-Lecturas!J5) <= 0), "", Lecturas!K5-Lecturas!J5) -> 0.562 | U7: =IFERROR(T7*$U$3,"") -> 9.8698799 | V7: =IF(OR((Lecturas!L5-Lecturas!K5) <= 0), "", Lecturas!L5-Lecturas!K5) -> 1.962 | W7: =IFERROR(V7*$W$3,"") -> 23.982457 | X7: =IF(OR((Lecturas!M5-Lecturas!L5) < 0), "", Lecturas!M5-Lecturas!L5) -> 1.805 | Y7: =IFERROR(X7*$Y$3,"") -> 21.902549 | Z7: =IF(OR((Lecturas!N5-Lecturas!M5) <= 0), "", Lecturas!N5-Lecturas!M5) -> 1.727 | AA7: =IFERROR(Z7*$AA$3,"") -> 24.327078 | AB7: =IF(OR((Lecturas!O5-Lecturas!N5) < 0), "", Lecturas!O5-Lecturas!N5) -> 1.681 | AC7: =IFERROR(AB7*$AC$3,"") -> 21.595873 | AD7: =IF(OR((Lecturas!P5-Lecturas!O5) < 0), "", Lecturas!P5-Lecturas!O5) -> 1.287 | AE7: =IFERROR(AD7*$AE$3,"") -> 16.188126 | AF7: =IF((Lecturas!Q5-Lecturas!P5)<= 0,"",Lecturas!Q5-Lecturas!P5) -> 1.564 | AG7: =IFERROR(AF7*$AG$3,"") -> 22.283717 | AH7: =IF((Lecturas!R5-Lecturas!Q5)<= 0,"",Lecturas!R5-Lecturas!Q5) -> 1.851 | AI7: =IFERROR(AH7*$AI$3,"") -> 25.754734 | AJ7: =IF((Lecturas!S5-Lecturas!R5)<= 0,"",Lecturas!S5-Lecturas!R5) -> 1.715 | AK7: =IFERROR(AJ7*$AK$3,"") -> 24.709272 | AL7: =IF((Lecturas!T5-Lecturas!S5)<= 0,"",Lecturas!T5-Lecturas!S5) -> 0.02 | AM7: =IFERROR(AL7*$AM$3,"") -> 0.19857647 | AN7: =IF((Lecturas!U5-Lecturas!T5)<= 0,"",Lecturas!U5-Lecturas!T5) -> 0.005 | AO7: =IFERROR(AN7*$AO$3,"") -> 0.081314696 | AP7: =IF((Lecturas!V5-Lecturas!U5)<= 0,"",Lecturas!V5-Lecturas!U5) -> 0.742 | AQ7: =IFERROR(AP7*$AQ$3,"") -> 9.8858366 | AR7: =IF((Lecturas!W5-Lecturas!V5)<= 0,"",Lecturas!W5-Lecturas!V5) -> 1.196 | AS7: =IFERROR(AR7*$AS$3,"") -> 14.133044 | AT7: =IF((Lecturas!X5-Lecturas!W5)<= 0,"",Lecturas!X5-Lecturas!W5) -> 1.543 | AU7: =IFERROR(AT7*$AU$3,"") -> 18.554872 | AV7: =IF((Lecturas!Y5-Lecturas!X5)<= 0,"",Lecturas!Y5-Lecturas!X5) -> 0.952 | AW7: =IFERROR(AV7*$AW$3,"") -> 11.670047 | AX7: =IF((Lecturas!Z5-Lecturas!Y5)<= 0,"0",Lecturas!Z5-Lecturas!Y5) -> 0.022 | AY7: =IFERROR(AX7*$AY$3,"0") -> 0.25528941 | AZ7: =IF((Lecturas!AA5-Lecturas!Z5)<= 0,"0",Lecturas!AA5-Lecturas!Z5) -> 0 | BA7: =IFERROR(AZ7*$BA$3,"0") -> 0 | BB7: =IF((Lecturas!AB5-Lecturas!AA5)<= 0,"0",Lecturas!AB5-Lecturas!AA5) -> 0.004 | BC7: =IFERROR(BB7*$BC$3,"0") -> 0.059942664 | BD7: =IF((Lecturas!AC5-Lecturas!AB5)<= 0,"0",Lecturas!AC5-Lecturas!AB5) -> 0.028 | BE7: =IFERROR(BD7*$BE$3,"0") -> 0.6052205 | BF7: =IF((Lecturas!AD5-Lecturas!AC5)<= 0,"0",Lecturas!AD5-Lecturas!AC5) -> 0 | BG7: =IFERROR(BF7*$BG$3,"0") -> 0 | BH7: =IF((Lecturas!AE5-Lecturas!AD5)<= 0,"0",Lecturas!AE5-Lecturas!AD5) -> 0 | BI7: =IFERROR(BH7*$BI$3,"0") -> 0 | BJ7: =IF((Lecturas!AF5-Lecturas!AE5)<= 0,"0",Lecturas!AF5-Lecturas!AE5) -> 0 | BK7: =IFERROR(BJ7*$BK$3,"0") -> 0 | BL7: =IF((Lecturas!AG5-Lecturas!AF5)<= 0,"0",Lecturas!AG5-Lecturas!AF5) -> 0 | BM7: =IFERROR(BL7*$BM$3,"0") -> 0 | BN7: =IF((Lecturas!AH5-Lecturas!AG5)<= 0,"0",Lecturas!AH5-Lecturas!AG5) -> 0 | BO7: =IFERROR(BN7*$BO$3,"0") -> 0
A8: =ROUND(AG8,1) -> 0 | B8: =AF8 -> 0 | C8: 203 | D8: SANTIAGO MORAN VASQUEZ | E8: 2034020 | F8: =Lecturas!D6-Lecturas!C6 -> 0.018 | G8: =F8*$G$3 -> 0.40204669 | H8: =IF((Lecturas!E6-Lecturas!D6) < 0, "", Lecturas!E6-Lecturas!D6) -> 0.674 | I8: =IFERROR(H8*$I$3,"") -> 12.041475 | J8: =IF(OR((Lecturas!F6-Lecturas!E6) <= 0), "", Lecturas!F6-Lecturas!E6) -> 0.911 | K8: =IFERROR(J8*$K$3,"") -> 11.078512 | L8: =IF(OR((Lecturas!G6-Lecturas!F6) < 0), "", Lecturas!G6-Lecturas!F6) -> 0 | M8: =IFERROR(L8*$M$3,"") -> 0 | N8: =IF(OR((Lecturas!H6-Lecturas!G6) < 0), "", Lecturas!H6-Lecturas!G6) -> 0 | O8: =IFERROR(N8*$O$3,"") -> 0 | P8: =IF(OR((Lecturas!I6-Lecturas!H6) <= 0), "", Lecturas!I6-Lecturas!H6) -> 0.318 | Q8: =IFERROR(P8*$Q$3,"") -> 4.7194211 | R8: =IF(OR((Lecturas!J6-Lecturas!I6) <= 0), "", Lecturas!J6-Lecturas!I6) -> 0.001 | S8: =IFERROR(R8*$S$3,"") -> 0.016571528 | T8: =IF(OR((Lecturas!K6-Lecturas!J6) < 0), "", Lecturas!K6-Lecturas!J6) -> 0 | U8: =IFERROR(T8*$U$3,"") -> 0 | V8: =IF(OR((Lecturas!L6-Lecturas!K6) <0), "", Lecturas!L6-Lecturas!K6) -> 0 | W8: =IFERROR(V8*$W$3,"") -> 0 | X8: =IF(OR((Lecturas!M6-Lecturas!L6) < 0), "", Lecturas!M6-Lecturas!L6) -> 0 | Y8: =IFERROR(X8*$Y$3,"") -> 0 | Z8: =IF(OR((Lecturas!N6-Lecturas!M6) <0), "", Lecturas!N6-Lecturas!M6) -> 0 | AA8: =IFERROR(Z8*$AA$3,"") -> 0 | AB8: =IF(OR((Lecturas!O6-Lecturas!N6) < 0), "", Lecturas!O6-Lecturas!N6) -> 0 | AC8: =IFERROR(AB8*$AC$3,"") -> 0 | AD8: =IF(OR((Lecturas!P6-Lecturas!O6) < 0), "", Lecturas!P6-Lecturas!O6) -> 0 | AE8: =IFERROR(AD8*$AE$3,"") -> 0 | AF8: =IF((Lecturas!Q6-Lecturas!P6)< 0,"",Lecturas!Q6-Lecturas!P6) -> 0 | AG8: =IFERROR(AF8*$AG$3,"") -> 0 | AH8: =IF((Lecturas!R6-Lecturas!Q6)<= 0,"",Lecturas!R6-Lecturas!Q6) -> 0.36 | AI8: =IFERROR(AH8*$AI$3,"") -> 5.0090244 | AJ8: =IF((Lecturas!S6-Lecturas!R6)<= 0,"",Lecturas!S6-Lecturas!R6) -> 0.008 | AK8: =IFERROR(AJ8*$AK$3,"") -> 0.11526191 | AL8: =IF((Lecturas!T6-Lecturas!S6)<= 0,"",Lecturas!T6-Lecturas!S6) -> 0.005 | AM8: =IFERROR(AL8*$AM$3,"") -> 0.049644117 | AN8: =IF((Lecturas!U6-Lecturas!T6)<= 0,"",Lecturas!U6-Lecturas!T6) -> 0.003 | AO8: =IFERROR(AN8*$AO$3,"") -> 0.048788818 | AP8: =IF((Lecturas!V6-Lecturas!U6)<= 0,"",Lecturas!V6-Lecturas!U6) -> 0.127 | AQ8: =IFERROR(AP8*$AQ$3,"") -> 1.6920502 | AR8: =IF((Lecturas!W6-Lecturas!V6)<= 0,"",Lecturas!W6-Lecturas!V6) -> 0.231 | AS8: =IFERROR(AR8*$AS$3,"") -> 2.72971 | AT8: =IF((Lecturas!X6-Lecturas!W6)<= 0,"",Lecturas!X6-Lecturas!W6) -> 0.114 | AU8: =IFERROR(AT8*$AU$3,"") -> 1.370872 | AV8: =IF((Lecturas!Y6-Lecturas!X6)<= 0,"",Lecturas!Y6-Lecturas!X6) -> 0.002 | AW8: =IFERROR(AV8*$AW$3,"") -> 0.024516906 | AX8: =IF((Lecturas!Z6-Lecturas!Y6)<= 0,"0",Lecturas!Z6-Lecturas!Y6) -> 0.003 | AY8: =IFERROR(AX8*$AY$3,"0") -> 0.034812192 | AZ8: =IF((Lecturas!AA6-Lecturas!Z6)<= 0,"0",Lecturas!AA6-Lecturas!Z6) -> 0 | BA8: =IFERROR(AZ8*$BA$3,"0") -> 0 | BB8: =IF((Lecturas!AB6-Lecturas!AA6)<= 0,"0",Lecturas!AB6-Lecturas!AA6) -> 0.004 | BC8: =IFERROR(BB8*$BC$3,"0") -> 0.059942664 | BD8: =IF((Lecturas!AC6-Lecturas!AB6)<= 0,"0",Lecturas!AC6-Lecturas!AB6) -> 0.04 | BE8: =IFERROR(BD8*$BE$3,"0") -> 0.86460071 | BF8: =IF((Lecturas!AD6-Lecturas!AC6)<= 0,"0",Lecturas!AD6-Lecturas!AC6) -> 0 | BG8: =IFERROR(BF8*$BG$3,"0") -> 0 | BH8: =IF((Lecturas!AE6-Lecturas!AD6)<= 0,"0",Lecturas!AE6-Lecturas!AD6) -> 0 | BI8: =IFERROR(BH8*$BI$3,"0") -> 0 | BJ8: =IF((Lecturas!AF6-Lecturas!AE6)<= 0,"0",Lecturas!AF6-Lecturas!AE6) -> 0 | BK8: =IFERROR(BJ8*$BK$3,"0") -> 0 | BL8: =IF((Lecturas!AG6-Lecturas!AF6)<= 0,"0",Lecturas!AG6-Lecturas!AF6) -> 0 | BM8: =IFERROR(BL8*$BM$3,"0") -> 0 | BN8: =IF((Lecturas!AH6-Lecturas!AG6)<= 0,"0",Lecturas!AH6-Lecturas!AG6) -> 0 | BO8: =IFERROR(BN8*$BO$3,"0") -> 0
A9: =ROUND(AG9,1) -> 12.3 | B9: =AF9 -> 0.86 | C9: 204 | D9: LILIA ISABEL GIL ARAUJO | E9: 2034040 | F9: =Lecturas!D7-Lecturas!C7 -> 0.185 | G9: =F9*$G$3 -> 4.1321465 | H9: =IF((Lecturas!E7-Lecturas!D7) < 0, "", Lecturas!E7-Lecturas!D7) -> 0.138 | I9: =IFERROR(H9*$I$3,"") -> 2.4654652 | J9: =IF(OR((Lecturas!F7-Lecturas!E7) < 0), "", Lecturas!F7-Lecturas!E7) -> 0 | K9: =IFERROR(J9*$K$3,"") -> 0 | L9: =IF(OR((Lecturas!G7-Lecturas!F7) <= 0), "", Lecturas!G7-Lecturas!F7) -> 0.296 | M9: =IFERROR(L9*$M$3,"") -> 4.6207484 | N9: =IF(OR((Lecturas!H7-Lecturas!G7) <= 0), "", Lecturas!H7-Lecturas!G7) -> 0.183 | O9: =IFERROR(N9*$O$3,"") -> 2.780991 | P9: =IF(OR((Lecturas!I7-Lecturas!H7) <= 0), "", Lecturas!I7-Lecturas!H7) -> 0.214 | Q9: =IFERROR(P9*$Q$3,"") -> 3.1759626 | R9: =IF(OR((Lecturas!J7-Lecturas!I7) <= 0), "", Lecturas!J7-Lecturas!I7) -> 0.324 | S9: =IFERROR(R9*$S$3,"") -> 5.369175 | T9: =IF(OR((Lecturas!K7-Lecturas!J7) <= 0), "", Lecturas!K7-Lecturas!J7) -> 0.513 | U9: =IFERROR(T9*$U$3,"") -> 9.0093388 | V9: =IF(OR((Lecturas!L7-Lecturas!K7) <= 0), "", Lecturas!L7-Lecturas!K7) -> 0.524 | W9: =IFERROR(V9*$W$3,"") -> 6.4051006 | X9: =IF(OR((Lecturas!M7-Lecturas!L7) < 0), "", Lecturas!M7-Lecturas!L7) -> 0.443 | Y9: =IFERROR(X9*$Y$3,"") -> 5.3755287 | Z9: =IF(OR((Lecturas!N7-Lecturas!M7) <= 0), "", Lecturas!N7-Lecturas!M7) -> 0.811 | AA9: =IFERROR(Z9*$AA$3,"") -> 11.424007 | AB9: =IF(OR((Lecturas!O7-Lecturas!N7) < 0), "", Lecturas!O7-Lecturas!N7) -> 0.749 | AC9: =IFERROR(AB9*$AC$3,"") -> 9.6224323 | AD9: =IF(OR((Lecturas!P7-Lecturas!O7) < 0), "", Lecturas!P7-Lecturas!O7) -> 0.811 | AE9: =IFERROR(AD9*$AE$3,"") -> 10.200909 | AF9: =IF((Lecturas!Q7-Lecturas!P7)<= 0,"",Lecturas!Q7-Lecturas!P7) -> 0.86 | AG9: =IFERROR(AF9*$AG$3,"") -> 12.253195 | AH9: =IF((Lecturas!R7-Lecturas!Q7)<= 0,"",Lecturas!R7-Lecturas!Q7) -> 0.706 | AI9: =IFERROR(AH9*$AI$3,"") -> 9.8232534 | AJ9: =IF((Lecturas!S7-Lecturas!R7)<= 0,"",Lecturas!S7-Lecturas!R7) -> 0.164 | AK9: =IFERROR(AJ9*$AK$3,"") -> 2.3628692 | AL9: =IF((Lecturas!T7-Lecturas!S7)<= 0,"",Lecturas!T7-Lecturas!S7) -> 1.253 | AM9: =IFERROR(AL9*$AM$3,"") -> 12.440816 | AN9: =IF((Lecturas!U7-Lecturas!T7)<= 0,"",Lecturas!U7-Lecturas!T7) -> 0.386 | AO9: =IFERROR(AN9*$AO$3,"") -> 6.2774945 | AP9: =IF((Lecturas!V7-Lecturas!U7)<= 0,"",Lecturas!V7-Lecturas!U7) -> 0.265 | AQ9: =IFERROR(AP9*$AQ$3,"") -> 3.5306559 | AR9: =IF((Lecturas!W7-Lecturas!V7)<= 0,"",Lecturas!W7-Lecturas!V7) -> 1.305 | AS9: =IFERROR(AR9*$AS$3,"") -> 15.421089 | AT9: =IF((Lecturas!X7-Lecturas!W7)<= 0,"",Lecturas!X7-Lecturas!W7) -> 0.324 | AU9: =IFERROR(AT9*$AU$3,"") -> 3.8961625 | AV9: =IF((Lecturas!Y7-Lecturas!X7)<= 0,"",Lecturas!Y7-Lecturas!X7) -> 0.041 | AW9: =IFERROR(AV9*$AW$3,"") -> 0.50259656 | AX9: =IF((Lecturas!Z7-Lecturas!Y7)<= 0,"0",Lecturas!Z7-Lecturas!Y7) -> 2.764 | AY9: =IFERROR(AX9*$AY$3,"0") -> 32.073633 | AZ9: =IF((Lecturas!AA7-Lecturas!Z7)<= 0,"0",Lecturas!AA7-Lecturas!Z7) -> 4.434 | BA9: =IFERROR(AZ9*$BA$3,"0") -> 61.207072 | BB9: =IF((Lecturas!AB7-Lecturas!AA7)<= 0,"0",Lecturas!AB7-Lecturas!AA7) -> 5.065 | BC9: =IFERROR(BB9*$BC$3,"0") -> 75.902398 | BD9: =IF((Lecturas!AC7-Lecturas!AB7)<= 0,"0",Lecturas!AC7-Lecturas!AB7) -> 5.037 | BE9: =IFERROR(BD9*$BE$3,"0") -> 108.87484 | BF9: =IF((Lecturas!AD7-Lecturas!AC7)<= 0,"0",Lecturas!AD7-Lecturas!AC7) -> 0 | BG9: =IFERROR(BF9*$BG$3,"0") -> 0 | BH9: =IF((Lecturas!AE7-Lecturas!AD7)<= 0,"0",Lecturas!AE7-Lecturas!AD7) -> 0 | BI9: =IFERROR(BH9*$BI$3,"0") -> 0 | BJ9: =IF((Lecturas!AF7-Lecturas!AE7)<= 0,"0",Lecturas!AF7-Lecturas!AE7) -> 0 | BK9: =IFERROR(BJ9*$BK$3,"0") -> 0 | BL9: =IF((Lecturas!AG7-Lecturas!AF7)<= 0,"0",Lecturas!AG7-Lecturas!AF7) -> 0 | BM9: =IFERROR(BL9*$BM$3,"0") -> 0 | BN9: =IF((Lecturas!AH7-Lecturas!AG7)<= 0,"0",Lecturas!AH7-Lecturas!AG7) -> 0 | BO9: =IFERROR(BN9*$BO$3,"0") -> 0
A10: =ROUND(AG10,1) -> 47.3 | B10: =AF10 -> 3.319 | C10: 205 | D10: HILDA LUZ VELEZ GHERSI | E10: 2034039 | F10: =Lecturas!D8-Lecturas!C8 -> 2.259 | G10: =F10*$G$3 -> 50.45686 | H10: =IF((Lecturas!E8-Lecturas!D8) < 0, "", Lecturas!E8-Lecturas!D8) -> 2.372 | I10: =IFERROR(H10*$I$3,"") -> 42.377416 | J10: =IF(OR((Lecturas!F8-Lecturas!E8) <= 0), "", Lecturas!F8-Lecturas!E8) -> 2.51 | K10: =IFERROR(J10*$K$3,"") -> 30.523671 | L10: =IF(OR((Lecturas!G8-Lecturas!F8) <= 0), "", Lecturas!G8-Lecturas!F8) -> 2.102 | M10: =IFERROR(L10*$M$3,"") -> 32.813558 | N10: =IF(OR((Lecturas!H8-Lecturas!G8) <= 0), "", Lecturas!H8-Lecturas!G8) -> 1.776 | O10: =IFERROR(N10*$O$3,"") -> 26.98929 | P10: =IF(OR((Lecturas!I8-Lecturas!H8) < 0), "", Lecturas!I8-Lecturas!H8) -> 0 | Q10: =IFERROR(P10*$Q$3,"") -> 0 | R10: =IF(OR((Lecturas!J8-Lecturas!I8) <= 0), "", Lecturas!J8-Lecturas!I8) -> 0.665 | S10: =IFERROR(R10*$S$3,"") -> 11.020066 | T10: =IF(OR((Lecturas!K8-Lecturas!J8) <= 0), "", Lecturas!K8-Lecturas!J8) -> 1.254 | U10: =IFERROR(T10*$U$3,"") -> 22.022828 | V10: =IF(OR((Lecturas!L8-Lecturas!K8) <= 0), "", Lecturas!L8-Lecturas!K8) -> 1.722 | W10: =IFERROR(V10*$W$3,"") -> 21.048823 | X10: =IF(OR((Lecturas!M8-Lecturas!L8) < 0), "", Lecturas!M8-Lecturas!L8) -> 1.933 | Y10: =IFERROR(X10*$Y$3,"") -> 23.45575 | Z10: =IF(OR((Lecturas!N8-Lecturas!M8) <= 0), "", Lecturas!N8-Lecturas!M8) -> 1.437 | AA10: =IFERROR(Z10*$AA$3,"") -> 20.242044 | AB10: =IF(OR((Lecturas!O8-Lecturas!N8) < 0), "", Lecturas!O8-Lecturas!N8) -> 1.347 | AC10: =IFERROR(AB10*$AC$3,"") -> 17.304962 | AD10: =IF(OR((Lecturas!P8-Lecturas!O8) < 0), "", Lecturas!P8-Lecturas!O8) -> 1.576 | AE10: =IFERROR(AD10*$AE$3,"") -> 19.823222 | AF10: =IF((Lecturas!Q8-Lecturas!P8)<= 0,"",Lecturas!Q8-Lecturas!P8) -> 3.319 | AG10: =IFERROR(AF10*$AG$3,"") -> 47.288783 | AH10: =IF((Lecturas!R8-Lecturas!Q8)<= 0,"",Lecturas!R8-Lecturas!Q8) -> 0.33 | AI10: =IFERROR(AH10*$AI$3,"") -> 4.5916057 | AJ10: =IF((Lecturas!S8-Lecturas!R8)<= 0,"",Lecturas!S8-Lecturas!R8) -> 0.471 | AK10: =IFERROR(AJ10*$AK$3,"") -> 6.7860451 | AL10: =IF((Lecturas!T8-Lecturas!S8)<= 0,"",Lecturas!T8-Lecturas!S8) -> 0.602 | AM10: =IFERROR(AL10*$AM$3,"") -> 5.9771517 | AN10: =IF((Lecturas!U8-Lecturas!T8)<= 0,"",Lecturas!U8-Lecturas!T8) -> 0.558 | AO10: =IFERROR(AN10*$AO$3,"") -> 9.0747201 | AP10: =IF((Lecturas!V8-Lecturas!U8)<= 0,"",Lecturas!V8-Lecturas!U8) -> 2.052 | AQ10: =IFERROR(AP10*$AQ$3,"") -> 27.339268 | AR10: =IF((Lecturas!W8-Lecturas!V8)<= 0,"",Lecturas!W8-Lecturas!V8) -> 3.381 | AS10: =IFERROR(AR10*$AS$3,"") -> 39.953028 | AT10: =IF((Lecturas!X8-Lecturas!W8)<= 0,"",Lecturas!X8-Lecturas!W8) -> 4.006 | AU10: =IFERROR(AT10*$AU$3,"") -> 48.172922 | AV10: =IF((Lecturas!Y8-Lecturas!X8)<= 0,"",Lecturas!Y8-Lecturas!X8) | AW10: =IFERROR(AV10*$AW$3,"") -> 0 | AX10: =IF((Lecturas!Z8-Lecturas!Y8)<= 0,"0",Lecturas!Z8-Lecturas!Y8) -> 16.597 | AY10: =IFERROR(AX10*$AY$3,"0") -> 192.59265 | AZ10: =IF((Lecturas!AA8-Lecturas!Z8)<= 0,"0",Lecturas!AA8-Lecturas!Z8) -> 0.138 | BA10: =IFERROR(AZ10*$BA$3,"0") -> 1.9049562 | BB10: =IF((Lecturas!AB8-Lecturas!AA8)<= 0,"0",Lecturas!AB8-Lecturas!AA8) -> 0 | BC10: =IFERROR(BB10*$BC$3,"0") -> 0 | BD10: =IF((Lecturas!AC8-Lecturas!AB8)<= 0,"0",Lecturas!AC8-Lecturas!AB8) -> 0 | BE10: =IFERROR(BD10*$BE$3,"0") -> 0 | BF10: =IF((Lecturas!AD8-Lecturas!AC8)<= 0,"0",Lecturas!AD8-Lecturas!AC8) -> 0 | BG10: =IFERROR(BF10*$BG$3,"0") -> 0 | BH10: =IF((Lecturas!AE8-Lecturas!AD8)<= 0,"0",Lecturas!AE8-Lecturas!AD8) -> 0 | BI10: =IFERROR(BH10*$BI$3,"0") -> 0 | BJ10: =IF((Lecturas!AF8-Lecturas!AE8)<= 0,"0",Lecturas!AF8-Lecturas!AE8) -> 0 | BK10: =IFERROR(BJ10*$BK$3,"0") -> 0 | BL10: =IF((Lecturas!AG8-Lecturas!AF8)<= 0,"0",Lecturas!AG8-Lecturas!AF8) -> 0 | BM10: =IFERROR(BL10*$BM$3,"0") -> 0 | BN10: =IF((Lecturas!AH8-Lecturas!AG8)<= 0,"0",Lecturas!AH8-Lecturas!AG8) -> 0 | BO10: =IFERROR(BN10*$BO$3,"0") -> 0
A11: =ROUND(AG11,1) -> 192.8 | B11: =AF11 -> 13.533 | C11: 206 | D11: GUSTAVO ENRIQUE LOPEZ CORDERO | E11: 2034052 | F11: =Lecturas!D9-Lecturas!C9 -> 7.134 | G11: =F11*$G$3 -> 159.3445 | H11: =IF((Lecturas!E9-Lecturas!D9) < 0, "", Lecturas!E9-Lecturas!D9) -> 8.759 | I11: =IFERROR(H11*$I$3,"") -> 156.48557 | J11: =IF(OR((Lecturas!F9-Lecturas!E9) <= 0), "", Lecturas!F9-Lecturas!E9) -> 9.6 | K11: =IFERROR(J11*$K$3,"") -> 116.74392 | L11: =IF(OR((Lecturas!G9-Lecturas!F9) <= 0), "", Lecturas!G9-Lecturas!F9) -> 11.064 | M11: =IFERROR(L11*$M$3,"") -> 172.71608 | N11: =IF(OR((Lecturas!H9-Lecturas!G9) <= 0), "", Lecturas!H9-Lecturas!G9) -> 9.658 | O11: =IFERROR(N11*$O$3,"") -> 146.76946 | P11: =IF(OR((Lecturas!I9-Lecturas!H9) <= 0), "", Lecturas!I9-Lecturas!H9) -> 10.605 | Q11: =IFERROR(P11*$Q$3,"") -> 157.38824 | R11: =IF(OR((Lecturas!J9-Lecturas!I9) <= 0), "", Lecturas!J9-Lecturas!I9) -> 10.696 | S11: =IFERROR(R11*$S$3,"") -> 177.24906 | T11: =IF(OR((Lecturas!K9-Lecturas!J9) <= 0), "", Lecturas!K9-Lecturas!J9) -> 8.891 | U11: =IFERROR(T11*$U$3,"") -> 156.14431 | V11: =IF(OR((Lecturas!L9-Lecturas!K9) <= 0), "", Lecturas!L9-Lecturas!K9) -> 11.337 | W11: =IFERROR(V11*$W$3,"") -> 138.57753 | X11: =IF(OR((Lecturas!M9-Lecturas!L9) < 0), "", Lecturas!M9-Lecturas!L9) -> 11.777 | Y11: =IFERROR(X11*$Y$3,"") -> 142.90655 | Z11: =IF(OR((Lecturas!N9-Lecturas!M9) <= 0), "", Lecturas!N9-Lecturas!M9) -> 11.311 | AA11: =IFERROR(Z11*$AA$3,"") -> 159.33038 | AB11: =IF(OR((Lecturas!O9-Lecturas!N9) < 0), "", Lecturas!O9-Lecturas!N9) -> 11.237 | AC11: =IFERROR(AB11*$AC$3,"") -> 144.36218 | AD11: =IF(OR((Lecturas!P9-Lecturas!O9) < 0), "", Lecturas!P9-Lecturas!O9) -> 11.397 | AE11: =IFERROR(AD11*$AE$3,"") -> 143.35359 | AF11: =IF((Lecturas!Q9-Lecturas!P9)<= 0,"",Lecturas!Q9-Lecturas!P9) -> 13.533 | AG11: =IFERROR(AF11*$AG$3,"") -> 192.81684 | AH11: =IF((Lecturas!R9-Lecturas!Q9)<= 0,"",Lecturas!R9-Lecturas!Q9) -> 13.812 | AI11: =IFERROR(AH11*$AI$3,"") -> 192.17957 | AJ11: =IF((Lecturas!S9-Lecturas!R9)<= 0,"",Lecturas!S9-Lecturas!R9) -> 13.811 | AK11: =IFERROR(AJ11*$AK$3,"") -> 198.98528 | AL11: =IF((Lecturas!T9-Lecturas!S9)<= 0,"",Lecturas!T9-Lecturas!S9) -> 17.564 | AM11: =IFERROR(AL11*$AM$3,"") -> 174.38986 | AN11: =IF((Lecturas!U9-Lecturas!T9)<= 0,"",Lecturas!U9-Lecturas!T9) -> 11.868 | AO11: =IFERROR(AN11*$AO$3,"") -> 193.00856 | AP11: =IF((Lecturas!V9-Lecturas!U9)<= 0,"",Lecturas!V9-Lecturas!U9) -> 9.677 | AQ11: =IFERROR(AP11*$AQ$3,"") -> 128.9289 | AR11: =IF((Lecturas!W9-Lecturas!V9)<= 0,"",Lecturas!W9-Lecturas!V9) -> 15.338 | AS11: =IFERROR(AR11*$AS$3,"") -> 181.24802 | AT11: =IF((Lecturas!X9-Lecturas!W9)<= 0,"",Lecturas!X9-Lecturas!W9) -> 12.231 | AU11: =IFERROR(AT11*$AU$3,"") -> 147.08013 | AV11: =IF((Lecturas!Y9-Lecturas!X9)<= 0,"",Lecturas!Y9-Lecturas!X9) -> 12.779 | AW11: =IFERROR(AV11*$AW$3,"") -> 156.65077 | AX11: =IF((Lecturas!Z9-Lecturas!Y9)<= 0,"0",Lecturas!Z9-Lecturas!Y9) -> 12.467 | AY11: =IFERROR(AX11*$AY$3,"0") -> 144.66787 | AZ11: =IF((Lecturas!AA9-Lecturas!Z9)<= 0,"0",Lecturas!AA9-Lecturas!Z9) -> 13.319 | BA11: =IFERROR(AZ11*$BA$3,"0") -> 183.85589 | BB11: =IF((Lecturas!AB9-Lecturas!AA9)<= 0,"0",Lecturas!AB9-Lecturas!AA9) -> 12.028 | BC11: =IFERROR(BB11*$BC$3,"0") -> 180.24759 | BD11: =IF((Lecturas!AC9-Lecturas!AB9)<= 0,"0",Lecturas!AC9-Lecturas!AB9) -> 10.236 | BE11: =IFERROR(BD11*$BE$3,"0") -> 221.25132 | BF11: =IF((Lecturas!AD9-Lecturas!AC9)<= 0,"0",Lecturas!AD9-Lecturas!AC9) -> 0 | BG11: =IFERROR(BF11*$BG$3,"0") -> 0 | BH11: =IF((Lecturas!AE9-Lecturas!AD9)<= 0,"0",Lecturas!AE9-Lecturas!AD9) -> 0 | BI11: =IFERROR(BH11*$BI$3,"0") -> 0 | BJ11: =IF((Lecturas!AF9-Lecturas!AE9)<= 0,"0",Lecturas!AF9-Lecturas!AE9) -> 0 | BK11: =IFERROR(BJ11*$BK$3,"0") -> 0 | BL11: =IF((Lecturas!AG9-Lecturas!AF9)<= 0,"0",Lecturas!AG9-Lecturas!AF9) -> 0 | BM11: =IFERROR(BL11*$BM$3,"0") -> 0 | BN11: =IF((Lecturas!AH9-Lecturas!AG9)<= 0,"0",Lecturas!AH9-Lecturas!AG9) -> 0 | BO11: =IFERROR(BN11*$BO$3,"0") -> 0
A12: =ROUND(AG12,1) -> 0 | B12: =AF12 -> 0 | C12: 301 | D12: TRADEX INTERNACIONALSAC | E12: 2033964 | F12: =Lecturas!D10-Lecturas!C10 -> 0 | G12: =F12*$G$3 -> 0 | H12: =IF((Lecturas!E10-Lecturas!D10) < 0, "", Lecturas!E10-Lecturas!D10) -> 0 | I12: =IFERROR(H12*$I$3,"") -> 0 | J12: =IF(OR((Lecturas!F10-Lecturas!E10) < 0), "", Lecturas!F10-Lecturas!E10) -> 0 | K12: =IFERROR(J12*$K$3,"") -> 0 | L12: =IF(OR((Lecturas!G10-Lecturas!F10) < 0), "", Lecturas!G10-Lecturas!F10) -> 0 | M12: =IFERROR(L12*$M$3,"") -> 0 | N12: =IF(OR((Lecturas!H10-Lecturas!G10) < 0), "", Lecturas!H10-Lecturas!G10) -> 0 | O12: =IFERROR(N12*$O$3,"") -> 0 | P12: =IF(OR((Lecturas!I10-Lecturas!H10) < 0), "", Lecturas!I10-Lecturas!H10) -> 0 | Q12: =IFERROR(P12*$Q$3,"") -> 0 | R12: =IF(OR((Lecturas!J10-Lecturas!I10) < 0), "", Lecturas!J10-Lecturas!I10) -> 0 | S12: =IFERROR(R12*$S$3,"") -> 0 | T12: =IF(OR((Lecturas!K10-Lecturas!J10) < 0), "", Lecturas!K10-Lecturas!J10) -> 0 | U12: =IFERROR(T12*$U$3,"") -> 0 | V12: =IF(OR((Lecturas!L10-Lecturas!K10) < 0), "", Lecturas!L10-Lecturas!K10) -> 0 | W12: =IFERROR(V12*$W$3,"") -> 0 | X12: =IF(OR((Lecturas!M10-Lecturas!L10) < 0), "", Lecturas!M10-Lecturas!L10) -> 0 | Y12: =IFERROR(X12*$Y$3,"") -> 0 | Z12: =IF(OR((Lecturas!N10-Lecturas!M10) < 0), "", Lecturas!N10-Lecturas!M10) -> 0 | AA12: =IFERROR(Z12*$AA$3,"") -> 0 | AB12: =IF(OR((Lecturas!O10-Lecturas!N10) < 0), "", Lecturas!O10-Lecturas!N10) -> 0 | AC12: =IFERROR(AB12*$AC$3,"") -> 0 | AD12: =IF(OR((Lecturas!P10-Lecturas!O10) < 0), "", Lecturas!P10-Lecturas!O10) -> 0 | AE12: =IFERROR(AD12*$AE$3,"") -> 0 | AF12: =IF((Lecturas!Q10-Lecturas!P10)< 0,"",Lecturas!Q10-Lecturas!P10) -> 0 | AG12: =IFERROR(AF12*$AG$3,"") -> 0 | AH12: 0 | AI12: =IFERROR(AH12*$AI$3,"") -> 0 | AJ12: =IF((Lecturas!S10-Lecturas!R10)<= 0,"",Lecturas!S10-Lecturas!R10) | AK12: =IFERROR(AJ12*$AK$3,"") -> 0 | AL12: =IF((Lecturas!T10-Lecturas!S10)<= 0,"",Lecturas!T10-Lecturas!S10) | AM12: =IFERROR(AL12*$AM$3,"") -> 0 | AN12: =IF((Lecturas!U10-Lecturas!T10)<= 0,"",Lecturas!U10-Lecturas!T10) | AO12: =IFERROR(AN12*$AO$3,"") -> 0 | AP12: =IF((Lecturas!V10-Lecturas!U10)<= 0,"",Lecturas!V10-Lecturas!U10) | AQ12: =IFERROR(AP12*$AQ$3,"") -> 0 | AR12: =IF((Lecturas!W10-Lecturas!V10)<= 0,"",Lecturas!W10-Lecturas!V10) | AS12: =IFERROR(AR12*$AS$3,"") -> 0 | AT12: =IF((Lecturas!X10-Lecturas!W10)<= 0,"",Lecturas!X10-Lecturas!W10) | AU12: =IFERROR(AT12*$AU$3,"") -> 0 | AV12: =IF((Lecturas!Y10-Lecturas!X10)<= 0,"",Lecturas!Y10-Lecturas!X10) | AW12: =IFERROR(AV12*$AW$3,"") -> 0 | AX12: =IF((Lecturas!Z10-Lecturas!Y10)<= 0,"0",Lecturas!Z10-Lecturas!Y10) -> 0 | AY12: =IFERROR(AX12*$AY$3,"0") -> 0 | AZ12: =IF((Lecturas!AA10-Lecturas!Z10)<= 0,"0",Lecturas!AA10-Lecturas!Z10) -> 0 | BA12: =IFERROR(AZ12*$BA$3,"0") -> 0 | BB12: =IF((Lecturas!AB10-Lecturas!AA10)<= 0,"0",Lecturas!AB10-Lecturas!AA10) -> 0 | BC12: =IFERROR(BB12*$BC$3,"0") -> 0 | BD12: =IF((Lecturas!AC10-Lecturas!AB10)<= 0,"0",Lecturas!AC10-Lecturas!AB10) -> 0 | BE12: =IFERROR(BD12*$BE$3,"0") -> 0 | BF12: =IF((Lecturas!AD10-Lecturas!AC10)<= 0,"0",Lecturas!AD10-Lecturas!AC10) -> 0 | BG12: =IFERROR(BF12*$BG$3,"0") -> 0 | BH12: =IF((Lecturas!AE10-Lecturas!AD10)<= 0,"0",Lecturas!AE10-Lecturas!AD10) -> 0 | BI12: =IFERROR(BH12*$BI$3,"0") -> 0 | BJ12: =IF((Lecturas!AF10-Lecturas!AE10)<= 0,"0",Lecturas!AF10-Lecturas!AE10) -> 0 | BK12: =IFERROR(BJ12*$BK$3,"0") -> 0 | BL12: =IF((Lecturas!AG10-Lecturas!AF10)<= 0,"0",Lecturas!AG10-Lecturas!AF10) -> 0 | BM12: =IFERROR(BL12*$BM$3,"0") -> 0 | BN12: =IF((Lecturas!AH10-Lecturas!AG10)<= 0,"0",Lecturas!AH10-Lecturas!AG10) -> 0 | BO12: =IFERROR(BN12*$BO$3,"0") -> 0
A13: =ROUND(AG13,1) -> 0 | B13: =AF13 -> 0 | C13: 301 | D13: ORELLANA HOLDAN OSCAR BRUNO | E13: GA170801166 | F13: =Lecturas!D11-Lecturas!C11 -> 0 | G13: =F13*$G$3 -> 0 | H13: =IF((Lecturas!E11-Lecturas!D11) < 0, "", Lecturas!E11-Lecturas!D11) -> 0 | I13: =IFERROR(H13*$I$3,"") -> 0 | J13: =IF(OR((Lecturas!F11-Lecturas!E11) < 0), "", Lecturas!F11-Lecturas!E11) -> 0 | K13: =IFERROR(J13*$K$3,"") -> 0 | L13: =IF(OR((Lecturas!G11-Lecturas!F11) < 0), "", Lecturas!G11-Lecturas!F11) -> 0 | M13: =IFERROR(L13*$M$3,"") -> 0 | N13: =IF(OR((Lecturas!H11-Lecturas!G11) < 0), "", Lecturas!H11-Lecturas!G11) -> 0 | O13: =IFERROR(N13*$O$3,"") -> 0 | P13: =IF(OR((Lecturas!I11-Lecturas!H11) < 0), "", Lecturas!I11-Lecturas!H11) -> 0 | Q13: =IFERROR(P13*$Q$3,"") -> 0 | R13: =IF(OR((Lecturas!J11-Lecturas!I11) < 0), "", Lecturas!J11-Lecturas!I11) -> 0 | S13: =IFERROR(R13*$S$3,"") -> 0 | T13: =IF(OR((Lecturas!K11-Lecturas!J11) < 0), "", Lecturas!K11-Lecturas!J11) -> 0 | U13: =IFERROR(T13*$U$3,"") -> 0 | V13: =IF(OR((Lecturas!L11-Lecturas!K11) < 0), "", Lecturas!L11-Lecturas!K11) -> 0 | W13: =IFERROR(V13*$W$3,"") -> 0 | X13: =IF(OR((Lecturas!M11-Lecturas!L11) < 0), "", Lecturas!M11-Lecturas!L11) -> 0 | Y13: =IFERROR(X13*$Y$3,"") -> 0 | Z13: =IF(OR((Lecturas!N11-Lecturas!M11) < 0), "", Lecturas!N11-Lecturas!M11) -> 0 | AA13: =IFERROR(Z13*$AA$3,"") -> 0 | AB13: =IF(OR((Lecturas!O11-Lecturas!N11) < 0), "", Lecturas!O11-Lecturas!N11) -> 0 | AC13: =IFERROR(AB13*$AC$3,"") -> 0 | AD13: =IF(OR((Lecturas!P11-Lecturas!O11) < 0), "", Lecturas!P11-Lecturas!O11) -> 0 | AE13: =IFERROR(AD13*$AE$3,"") -> 0 | AF13: =IF((Lecturas!Q11-Lecturas!P11)< 0,"",Lecturas!Q11-Lecturas!P11) -> 0 | AG13: =IFERROR(AF13*$AG$3,"") -> 0 | AH13: 0 | AI13: =IFERROR(AH13*$AI$3,"") -> 0 | AJ13: =IF((Lecturas!S11-Lecturas!R11)<= 0,"",Lecturas!S11-Lecturas!R11) | AK13: =IFERROR(AJ13*$AK$3,"") -> 0 | AL13: =IF((Lecturas!T11-Lecturas!S11)<= 0,"",Lecturas!T11-Lecturas!S11) | AM13: =IFERROR(AL13*$AM$3,"") -> 0 | AN13: =IF((Lecturas!U11-Lecturas!T11)<= 0,"",Lecturas!U11-Lecturas!T11) | AO13: =IFERROR(AN13*$AO$3,"") -> 0 | AP13: =IF((Lecturas!V11-Lecturas!U11)<= 0,"",Lecturas!V11-Lecturas!U11) | AQ13: =IFERROR(AP13*$AQ$3,"") -> 0 | AR13: =IF((Lecturas!W11-Lecturas!V11)<= 0,"",Lecturas!W11-Lecturas!V11) | AS13: =IFERROR(AR13*$AS$3,"") -> 0 | AT13: =IF((Lecturas!X11-Lecturas!W11)<= 0,"",Lecturas!X11-Lecturas!W11) | AU13: =IFERROR(AT13*$AU$3,"") -> 0 | AV13: =IF((Lecturas!Y11-Lecturas!X11)<= 0,"",Lecturas!Y11-Lecturas!X11) | AW13: =IFERROR(AV13*$AW$3,"") -> 0 | AX13: =IF((Lecturas!Z11-Lecturas!Y11)<= 0,"0",Lecturas!Z11-Lecturas!Y11) -> 0 | AY13: =IFERROR(AX13*$AY$3,"0") -> 0 | AZ13: =IF((Lecturas!AA11-Lecturas!Z11)<= 0,"0",Lecturas!AA11-Lecturas!Z11) -> 0 | BA13: =IFERROR(AZ13*$BA$3,"0") -> 0 | BB13: =IF((Lecturas!AB11-Lecturas!AA11)<= 0,"0",Lecturas!AB11-Lecturas!AA11) -> 0 | BC13: =IFERROR(BB13*$BC$3,"0") -> 0 | BD13: =IF((Lecturas!AC11-Lecturas!AB11)<= 0,"0",Lecturas!AC11-Lecturas!AB11) -> 0 | BE13: =IFERROR(BD13*$BE$3,"0") -> 0 | BF13: =IF((Lecturas!AD11-Lecturas!AC11)<= 0,"0",Lecturas!AD11-Lecturas!AC11) -> 0 | BG13: =IFERROR(BF13*$BG$3,"0") -> 0 | BH13: =IF((Lecturas!AE11-Lecturas!AD11)<= 0,"0",Lecturas!AE11-Lecturas!AD11) -> 0 | BI13: =IFERROR(BH13*$BI$3,"0") -> 0 | BJ13: =IF((Lecturas!AF11-Lecturas!AE11)<= 0,"0",Lecturas!AF11-Lecturas!AE11) -> 0 | BK13: =IFERROR(BJ13*$BK$3,"0") -> 0 | BL13: =IF((Lecturas!AG11-Lecturas!AF11)<= 0,"0",Lecturas!AG11-Lecturas!AF11) -> 0 | BM13: =IFERROR(BL13*$BM$3,"0") -> 0 | BN13: =IF((Lecturas!AH11-Lecturas!AG11)<= 0,"0",Lecturas!AH11-Lecturas!AG11) -> 0 | BO13: =IFERROR(BN13*$BO$3,"0") -> 0
A14: =ROUND(AG14,1) -> 11.6 | B14: =AF14 -> 0.817 | C14: 302 | D14: MARGOT MEDINA CARDENAS | E14: 2034062 | F14: =Lecturas!D12-Lecturas!C12 -> 4.871 | G14: =F14*$G$3 -> 108.7983 | H14: =IF((Lecturas!E12-Lecturas!D12) < 0, "", Lecturas!E12-Lecturas!D12) -> 1.266 | I14: =IFERROR(H14*$I$3,"") -> 22.617963 | J14: =IF(OR((Lecturas!F12-Lecturas!E12) <= 0), "", Lecturas!F12-Lecturas!E12) -> 0.499 | K14: =IFERROR(J14*$K$3,"") -> 6.0682517 | L14: =IF(OR((Lecturas!G12-Lecturas!F12) <= 0), "", Lecturas!G12-Lecturas!F12) -> 0.945 | M14: =IFERROR(L14*$M$3,"") -> 14.752052 | N14: =IF(OR((Lecturas!H12-Lecturas!G12) <= 0), "", Lecturas!H12-Lecturas!G12) -> 0.693 | O14: =IFERROR(N14*$O$3,"") -> 10.531294 | P14: =IF(OR((Lecturas!I12-Lecturas!H12) <= 0), "", Lecturas!I12-Lecturas!H12) -> 0.849 | Q14: =IFERROR(P14*$Q$3,"") -> 12.599964 | R14: =IF(OR((Lecturas!J12-Lecturas!I12) <= 0), "", Lecturas!J12-Lecturas!I12) -> 1.12 | S14: =IFERROR(R14*$S$3,"") -> 18.560111 | T14: =IF(OR((Lecturas!K12-Lecturas!J12) <= 0), "", Lecturas!K12-Lecturas!J12) -> 2.602 | U14: =IFERROR(T14*$U$3,"") -> 45.69649 | V14: =IF(OR((Lecturas!L12-Lecturas!K12) < 0), "", Lecturas!L12-Lecturas!K12) -> 3.413 | W14: =IFERROR(V14*$W$3,"") -> 41.718718 | X14: =IF(OR((Lecturas!M12-Lecturas!L12) < 0), "", Lecturas!M12-Lecturas!L12) -> 2.994 | Y14: =IFERROR(X14*$Y$3,"") -> 36.330323 | Z14: =IF(OR((Lecturas!N12-Lecturas!M12) <= 0), "", Lecturas!N12-Lecturas!M12) -> 0.795 | AA14: =IFERROR(Z14*$AA$3,"") -> 11.198626 | AB14: =IF(OR((Lecturas!O12-Lecturas!N12) < 0), "", Lecturas!O12-Lecturas!N12) -> 2.54 | AC14: =IFERROR(AB14*$AC$3,"") -> 32.631479 | AD14: =IF(OR((Lecturas!P12-Lecturas!O12) < 0), "", Lecturas!P12-Lecturas!O12) -> 2.333 | AE14: =IFERROR(AD14*$AE$3,"") -> 29.344909 | AF14: =IF((Lecturas!Q12-Lecturas!P12)<= 0,"",Lecturas!Q12-Lecturas!P12) -> 0.817 | AG14: =IFERROR(AF14*$AG$3,"") -> 11.640535 | AH14: =IF((Lecturas!R12-Lecturas!Q12)<= 0,"",Lecturas!R12-Lecturas!Q12) -> 3.466 | AI14: =IFERROR(AH14*$AI$3,"") -> 48.225774 | AJ14: =IF((Lecturas!S12-Lecturas!R12)<= 0,"",Lecturas!S12-Lecturas!R12) -> 4.252 | AK14: =IFERROR(AJ14*$AK$3,"") -> 61.261706 | AL14: =IF((Lecturas!T12-Lecturas!S12)<= 0,"",Lecturas!T12-Lecturas!S12) -> 4.214 | AM14: =IFERROR(AL14*$AM$3,"") -> 41.840062 | AN14: =IF((Lecturas!U12-Lecturas!T12)<= 0,"",Lecturas!U12-Lecturas!T12) -> 2.682 | AO14: =IFERROR(AN14*$AO$3,"") -> 43.617203 | AP14: =IF((Lecturas!V12-Lecturas!U12)<= 0,"",Lecturas!V12-Lecturas!U12) -> 3.858 | AQ14: =IFERROR(AP14*$AQ$3,"") -> 51.401021 | AR14: =IF((Lecturas!W12-Lecturas!V12)<= 0,"",Lecturas!W12-Lecturas!V12) -> 3.688 | AS14: =IFERROR(AR14*$AS$3,"") -> 43.580824 | AT14: =IF((Lecturas!X12-Lecturas!W12)<= 0,"",Lecturas!X12-Lecturas!W12) -> 2.838 | AU14: =IFERROR(AT14*$AU$3,"") -> 34.127497 | AV14: =IF((Lecturas!Y12-Lecturas!X12)<= 0,"",Lecturas!Y12-Lecturas!X12) -> 3.403 | AW14: =IFERROR(AV14*$AW$3,"") -> 41.715515 | AX14: =IF((Lecturas!Z12-Lecturas!Y12)<= 0,"0",Lecturas!Z12-Lecturas!Y12) -> 3.216 | AY14: =IFERROR(AX14*$AY$3,"0") -> 37.31867 | AZ14: =IF((Lecturas!AA12-Lecturas!Z12)<= 0,"0",Lecturas!AA12-Lecturas!Z12) -> 4.148 | BA14: =IFERROR(AZ14*$BA$3,"0") -> 57.25912 | BB14: =IF((Lecturas!AB12-Lecturas!AA12)<= 0,"0",Lecturas!AB12-Lecturas!AA12) -> 3.923 | BC14: =IFERROR(BB14*$BC$3,"0") -> 58.788767 | BD14: =IF((Lecturas!AC12-Lecturas!AB12)<= 0,"0",Lecturas!AC12-Lecturas!AB12) -> 4.07 | BE14: =IFERROR(BD14*$BE$3,"0") -> 87.973122 | BF14: =IF((Lecturas!AD12-Lecturas!AC12)<= 0,"0",Lecturas!AD12-Lecturas!AC12) -> 0 | BG14: =IFERROR(BF14*$BG$3,"0") -> 0 | BH14: =IF((Lecturas!AE12-Lecturas!AD12)<= 0,"0",Lecturas!AE12-Lecturas!AD12) -> 0 | BI14: =IFERROR(BH14*$BI$3,"0") -> 0 | BJ14: =IF((Lecturas!AF12-Lecturas!AE12)<= 0,"0",Lecturas!AF12-Lecturas!AE12) -> 0 | BK14: =IFERROR(BJ14*$BK$3,"0") -> 0 | BL14: =IF((Lecturas!AG12-Lecturas!AF12)<= 0,"0",Lecturas!AG12-Lecturas!AF12) -> 0 | BM14: =IFERROR(BL14*$BM$3,"0") -> 0 | BN14: =IF((Lecturas!AH12-Lecturas!AG12)<= 0,"0",Lecturas!AH12-Lecturas!AG12) -> 0 | BO14: =IFERROR(BN14*$BO$3,"0") -> 0
A15: =ROUND(AG15,1) -> 26.2 | B15: =AF15 -> 1.84 | C15: 303 | D15: OSCAR MARIMON PACHECO | E15: 2034065 | F15: =Lecturas!D13-Lecturas!C13 -> 1.486 | G15: =F15*$G$3 -> 33.191188 | H15: =IF((Lecturas!E13-Lecturas!D13) < 0, "", Lecturas!E13-Lecturas!D13) -> 1.629 | I15: =IFERROR(H15*$I$3,"") -> 29.103208 | J15: =IF(OR((Lecturas!F13-Lecturas!E13) <= 0), "", Lecturas!F13-Lecturas!E13) -> 2.991 | K15: =IFERROR(J15*$K$3,"") -> 36.373027 | L15: =IF(OR((Lecturas!G13-Lecturas!F13) <= 0), "", Lecturas!G13-Lecturas!F13) -> 1.42 | M15: =IFERROR(L15*$M$3,"") -> 22.167104 | N15: =IF(OR((Lecturas!H13-Lecturas!G13) <= 0), "", Lecturas!H13-Lecturas!G13) -> 2.517 | O15: =IFERROR(N15*$O$3,"") -> 38.250024 | P15: =IF(OR((Lecturas!I13-Lecturas!H13) <= 0), "", Lecturas!I13-Lecturas!H13) -> 1.461 | Q15: =IFERROR(P15*$Q$3,"") -> 21.682623 | R15: =IF(OR((Lecturas!J13-Lecturas!I13) <= 0), "", Lecturas!J13-Lecturas!I13) -> 4.412 | S15: =IFERROR(R15*$S$3,"") -> 73.11358 | T15: =IF(OR((Lecturas!K13-Lecturas!J13) <= 0), "", Lecturas!K13-Lecturas!J13) -> 1.043 | U15: =IFERROR(T15*$U$3,"") -> 18.317233 | V15: =IF(OR((Lecturas!L13-Lecturas!K13) < 0), "", Lecturas!L13-Lecturas!K13) -> 3.333 | W15: =IFERROR(V15*$W$3,"") -> 40.74084 | X15: =IF(OR((Lecturas!M13-Lecturas!L13) < 0), "", Lecturas!M13-Lecturas!L13) -> 6.026 | Y15: =IFERROR(X15*$Y$3,"") -> 73.121752 | Z15: =IF(OR((Lecturas!N13-Lecturas!M13) <= 0), "", Lecturas!N13-Lecturas!M13) -> 7.826 | AA15: =IFERROR(Z15*$AA$3,"") -> 110.23955 | AB15: =IF(OR((Lecturas!O13-Lecturas!N13) < 0), "", Lecturas!O13-Lecturas!N13) -> 5.635 | AC15: =IFERROR(AB15*$AC$3,"") -> 72.393065 | AD15: =IF(OR((Lecturas!P13-Lecturas!O13) < 0), "", Lecturas!P13-Lecturas!O13) -> 6.073 | AE15: =IFERROR(AD15*$AE$3,"") -> 76.387326 | AF15: =IF((Lecturas!Q13-Lecturas!P13)<= 0,"",Lecturas!Q13-Lecturas!P13) -> 1.84 | AG15: =IFERROR(AF15*$AG$3,"") -> 26.216137 | AH15: =IF((Lecturas!R13-Lecturas!Q13)<= 0,"",Lecturas!R13-Lecturas!Q13) -> 4.793 | AI15: =IFERROR(AH15*$AI$3,"") -> 66.689594 | AJ15: =IF((Lecturas!S13-Lecturas!R13)<= 0,"",Lecturas!S13-Lecturas!R13) -> 4.294 | AK15: =IFERROR(AJ15*$AK$3,"") -> 61.866831 | AL15: =IF((Lecturas!T13-Lecturas!S13)<= 0,"",Lecturas!T13-Lecturas!S13) -> 2.082 | AM15: =IFERROR(AL15*$AM$3,"") -> 20.671811 | AN15: =IF((Lecturas!U13-Lecturas!T13)<= 0,"",Lecturas!U13-Lecturas!T13) -> 1.297 | AO15: =IFERROR(AN15*$AO$3,"") -> 21.093032 | AP15: =IF((Lecturas!V13-Lecturas!U13)<= 0,"",Lecturas!V13-Lecturas!U13) -> 1.004 | AQ15: =IFERROR(AP15*$AQ$3,"") -> 13.376523 | AR15: =IF((Lecturas!W13-Lecturas!V13)<= 0,"",Lecturas!W13-Lecturas!V13) -> 3.375 | AS15: =IFERROR(AR15*$AS$3,"") -> 39.882126 | AT15: =IF((Lecturas!X13-Lecturas!W13)<= 0,"",Lecturas!X13-Lecturas!W13) -> 5.197 | AU15: =IFERROR(AT15*$AU$3,"") -> 62.494927 | AV15: =IF((Lecturas!Y13-Lecturas!X13)<= 0,"",Lecturas!Y13-Lecturas!X13) -> 0.987 | AW15: =IFERROR(AV15*$AW$3,"") -> 12.099093 | AX15: =IF((Lecturas!Z13-Lecturas!Y13)<= 0,"0",Lecturas!Z13-Lecturas!Y13) -> 2.951 | AY15: =IFERROR(AX15*$AY$3,"0") -> 34.243593 | AZ15: =IF((Lecturas!AA13-Lecturas!Z13)<= 0,"0",Lecturas!AA13-Lecturas!Z13) -> 1.35 | BA15: =IFERROR(AZ15*$BA$3,"0") -> 18.635442 | BB15: =IF((Lecturas!AB13-Lecturas!AA13)<= 0,"0",Lecturas!AB13-Lecturas!AA13) -> 4.076 | BC15: =IFERROR(BB15*$BC$3,"0") -> 61.081574 | BD15: =IF((Lecturas!AC13-Lecturas!AB13)<= 0,"0",Lecturas!AC13-Lecturas!AB13) -> 3.287 | BE15: =IFERROR(BD15*$BE$3,"0") -> 71.048563 | BF15: =IF((Lecturas!AD13-Lecturas!AC13)<= 0,"0",Lecturas!AD13-Lecturas!AC13) -> 0 | BG15: =IFERROR(BF15*$BG$3,"0") -> 0 | BH15: =IF((Lecturas!AE13-Lecturas!AD13)<= 0,"0",Lecturas!AE13-Lecturas!AD13) -> 0 | BI15: =IFERROR(BH15*$BI$3,"0") -> 0 | BJ15: =IF((Lecturas!AF13-Lecturas!AE13)<= 0,"0",Lecturas!AF13-Lecturas!AE13) -> 0 | BK15: =IFERROR(BJ15*$BK$3,"0") -> 0 | BL15: =IF((Lecturas!AG13-Lecturas!AF13)<= 0,"0",Lecturas!AG13-Lecturas!AF13) -> 0 | BM15: =IFERROR(BL15*$BM$3,"0") -> 0 | BN15: =IF((Lecturas!AH13-Lecturas!AG13)<= 0,"0",Lecturas!AH13-Lecturas!AG13) -> 0 | BO15: =IFERROR(BN15*$BO$3,"0") -> 0
A16: =ROUND(AG16,1) -> 29.8 | B16: =AF16 -> 2.09 | C16: 304 | D16: VICTORIA CARLOTA FEBRES ORE | E16: 2034043 | F16: =Lecturas!D14-Lecturas!C14 -> 0.616 | G16: =F16*$G$3 -> 13.758931 | H16: =IF((Lecturas!E14-Lecturas!D14) < 0, "", Lecturas!E14-Lecturas!D14) -> 0.611 | I16: =IFERROR(H16*$I$3,"") -> 10.915936 | J16: =IF(OR((Lecturas!F14-Lecturas!E14) < 0), "", Lecturas!F14-Lecturas!E14) -> 0 | K16: =IFERROR(J16*$K$3,"") -> 0 | L16: =IF(OR((Lecturas!G14-Lecturas!F14) <= 0), "", Lecturas!G14-Lecturas!F14) -> 4.376 | M16: =IFERROR(L16*$M$3,"") -> 68.312146 | N16: =IF(OR((Lecturas!H14-Lecturas!G14) <= 0), "", Lecturas!H14-Lecturas!G14) -> 3.587 | O16: =IFERROR(N16*$O$3,"") -> 54.510463 | P16: =IF(OR((Lecturas!I14-Lecturas!H14) <= 0), "", Lecturas!I14-Lecturas!H14) -> 2.449 | Q16: =IFERROR(P16*$Q$3,"") -> 36.345479 | R16: =IF(OR((Lecturas!J14-Lecturas!I14) <= 0), "", Lecturas!J14-Lecturas!I14) -> 1.184 | S16: =IFERROR(R16*$S$3,"") -> 19.620689 | T16: =IF(OR((Lecturas!K14-Lecturas!J14) <= 0), "", Lecturas!K14-Lecturas!J14) -> 0.002 | U16: =IFERROR(T16*$U$3,"") -> 0.035124128 | V16: =IF(OR((Lecturas!L14-Lecturas!K14) < 0), "", Lecturas!L14-Lecturas!K14) -> 0.062 | W16: =IFERROR(V16*$W$3,"") -> 0.75785541 | X16: =IF(OR((Lecturas!M14-Lecturas!L14) < 0), "", Lecturas!M14-Lecturas!L14) -> 0 | Y16: =IFERROR(X16*$Y$3,"") -> 0 | Z16: =IF(OR((Lecturas!N14-Lecturas!M14) <= 0), "", Lecturas!N14-Lecturas!M14) -> 5.724 | AA16: =IFERROR(Z16*$AA$3,"") -> 80.630105 | AB16: =IF(OR((Lecturas!O14-Lecturas!N14) < 0), "", Lecturas!O14-Lecturas!N14) -> 3.688 | AC16: =IFERROR(AB16*$AC$3,"") -> 47.37988 | AD16: =IF(OR((Lecturas!P14-Lecturas!O14) < 0), "", Lecturas!P14-Lecturas!O14) -> 4.763 | AE16: =IFERROR(AD16*$AE$3,"") -> 59.909902 | AF16: =IF((Lecturas!Q14-Lecturas!P14)<= 0,"",Lecturas!Q14-Lecturas!P14) -> 2.09 | AG16: =IFERROR(AF16*$AG$3,"") -> 29.778113 | AH16: =IF((Lecturas!R14-Lecturas!Q14)<= 0,"",Lecturas!R14-Lecturas!Q14) -> 0.006 | AI16: =IFERROR(AH16*$AI$3,"") -> 0.08348374 | AJ16: =IF((Lecturas!S14-Lecturas!R14)<= 0,"",Lecturas!S14-Lecturas!R14) -> 0.005 | AK16: =IFERROR(AJ16*$AK$3,"") -> 0.072038695 | AL16: =IF((Lecturas!T14-Lecturas!S14)<= 0,"",Lecturas!T14-Lecturas!S14) -> 0.002 | AM16: =IFERROR(AL16*$AM$3,"") -> 0.019857647 | AN16: =IF((Lecturas!U14-Lecturas!T14)<= 0,"",Lecturas!U14-Lecturas!T14) -> 2.289 | AO16: =IFERROR(AN16*$AO$3,"") -> 37.225868 | AP16: =IF((Lecturas!V14-Lecturas!U14)<= 0,"",Lecturas!V14-Lecturas!U14) -> 0.102 | AQ16: =IFERROR(AP16*$AQ$3,"") -> 1.3589694 | AR16: =IF((Lecturas!W14-Lecturas!V14)<= 0,"",Lecturas!W14-Lecturas!V14) -> 2.171 | AS16: =IFERROR(AR16*$AS$3,"") -> 25.654547 | AT16: =IF((Lecturas!X14-Lecturas!W14)<= 0,"",Lecturas!X14-Lecturas!W14) -> 0.001 | AU16: =IFERROR(AT16*$AU$3,"") -> 0.012025193 | AV16: =IF((Lecturas!Y14-Lecturas!X14)<= 0,"",Lecturas!Y14-Lecturas!X14) -> 2.248 | AW16: =IFERROR(AV16*$AW$3,"") -> 27.557002 | AX16: =IF((Lecturas!Z14-Lecturas!Y14)<= 0,"0",Lecturas!Z14-Lecturas!Y14) -> 4.133 | AY16: =IFERROR(AX16*$AY$3,"0") -> 47.959597 | AZ16: =IF((Lecturas!AA14-Lecturas!Z14)<= 0,"0",Lecturas!AA14-Lecturas!Z14) -> 4.615 | BA16: =IFERROR(AZ16*$BA$3,"0") -> 63.705602 | BB16: =IF((Lecturas!AB14-Lecturas!AA14)<= 0,"0",Lecturas!AB14-Lecturas!AA14) -> 3.989 | BC16: =IFERROR(BB16*$BC$3,"0") -> 59.777821 | BD16: =IF((Lecturas!AC14-Lecturas!AB14)<= 0,"0",Lecturas!AC14-Lecturas!AB14) -> 2.001 | BE16: =IFERROR(BD16*$BE$3,"0") -> 43.25165 | BF16: =IF((Lecturas!AD14-Lecturas!AC14)<= 0,"0",Lecturas!AD14-Lecturas!AC14) -> 0 | BG16: =IFERROR(BF16*$BG$3,"0") -> 0 | BH16: =IF((Lecturas!AE14-Lecturas!AD14)<= 0,"0",Lecturas!AE14-Lecturas!AD14) -> 0 | BI16: =IFERROR(BH16*$BI$3,"0") -> 0 | BJ16: =IF((Lecturas!AF14-Lecturas!AE14)<= 0,"0",Lecturas!AF14-Lecturas!AE14) -> 0 | BK16: =IFERROR(BJ16*$BK$3,"0") -> 0 | BL16: =IF((Lecturas!AG14-Lecturas!AF14)<= 0,"0",Lecturas!AG14-Lecturas!AF14) -> 0 | BM16: =IFERROR(BL16*$BM$3,"0") -> 0 | BN16: =IF((Lecturas!AH14-Lecturas!AG14)<= 0,"0",Lecturas!AH14-Lecturas!AG14) -> 0 | BO16: =IFERROR(BN16*$BO$3,"0") -> 0
A17: =ROUND(AG17,1) -> 0 | B17: =AF17 -> 0 | C17: 305 | D17: ROSA MARIA MONTENEGRO TORIBIO | E17: 2034044 | F17: =Lecturas!D15-Lecturas!C15 -> 1.522 | G17: =F17*$G$3 -> 33.995281 | H17: =IF((Lecturas!E15-Lecturas!D15) < 0, "", Lecturas!E15-Lecturas!D15) -> 1.541 | I17: =IFERROR(H17*$I$3,"") -> 27.531028 | J17: =IF(OR((Lecturas!F15-Lecturas!E15) <= 0), "", Lecturas!F15-Lecturas!E15) -> 1.523 | K17: =IFERROR(J17*$K$3,"") -> 18.520936 | L17: =IF(OR((Lecturas!G15-Lecturas!F15) <= 0), "", Lecturas!G15-Lecturas!F15) -> 1.312 | M17: =IFERROR(L17*$M$3,"") -> 20.481155 | N17: =IF(OR((Lecturas!H15-Lecturas!G15) <= 0), "", Lecturas!H15-Lecturas!G15) -> 1.465 | O17: =IFERROR(N17*$O$3,"") -> 22.263125 | P17: =IF(OR((Lecturas!I15-Lecturas!H15) <= 0), "", Lecturas!I15-Lecturas!H15) -> 1.355 | Q17: =IFERROR(P17*$Q$3,"") -> 20.109483 | R17: =IF(OR((Lecturas!J15-Lecturas!I15) <= 0), "", Lecturas!J15-Lecturas!I15) -> 1.184 | S17: =IFERROR(R17*$S$3,"") -> 19.620689 | T17: =IF(OR((Lecturas!K15-Lecturas!J15) <= 0), "", Lecturas!K15-Lecturas!J15) -> 0.251 | U17: =IFERROR(T17*$U$3,"") -> 4.408078 | V17: =IF(OR((Lecturas!L15-Lecturas!K15) < 0), "", Lecturas!L15-Lecturas!K15) -> 0.45 | W17: =IFERROR(V17*$W$3,"") -> 5.5005635 | X17: =IF(OR((Lecturas!M15-Lecturas!L15) < 0), "", Lecturas!M15-Lecturas!L15) -> 0 | Y17: =IFERROR(X17*$Y$3,"") -> 0 | Z17: =IF(OR((Lecturas!N15-Lecturas!M15) <= 0), "", Lecturas!N15-Lecturas!M15) -> 0.386 | AA17: =IFERROR(Z17*$AA$3,"") -> 5.4373202 | AB17: =IF(OR((Lecturas!O15-Lecturas!N15) < 0), "", Lecturas!O15-Lecturas!N15) -> 0 | AC17: =IFERROR(AB17*$AC$3,"") -> 0 | AD17: =IF(OR((Lecturas!P15-Lecturas!O15) < 0), "", Lecturas!P15-Lecturas!O15) -> 0 | AE17: =IFERROR(AD17*$AE$3,"") -> 0 | AF17: =IF((Lecturas!Q15-Lecturas!P15)< 0,"",Lecturas!Q15-Lecturas!P15) -> 0 | AG17: =IFERROR(AF17*$AG$3,"") -> 0 | AH17: 0 | AI17: =IFERROR(AH17*$AI$3,"") -> 0 | AJ17: =IF((Lecturas!S15-Lecturas!R15)<= 0,"",Lecturas!S15-Lecturas!R15) | AK17: =IFERROR(AJ17*$AK$3,"") -> 0 | AL17: =IF((Lecturas!T15-Lecturas!S15)<= 0,"",Lecturas!T15-Lecturas!S15) | AM17: =IFERROR(AL17*$AM$3,"") -> 0 | AN17: =IF((Lecturas!U15-Lecturas!T15)<= 0,"",Lecturas!U15-Lecturas!T15) | AO17: =IFERROR(AN17*$AO$3,"") -> 0 | AP17: =IF((Lecturas!V15-Lecturas!U15)<= 0,"",Lecturas!V15-Lecturas!U15) | AQ17: =IFERROR(AP17*$AQ$3,"") -> 0 | AR17: =IF((Lecturas!W15-Lecturas!V15)<= 0,"",Lecturas!W15-Lecturas!V15) | AS17: =IFERROR(AR17*$AS$3,"") -> 0 | AT17: =IF((Lecturas!X15-Lecturas!W15)<= 0,"",Lecturas!X15-Lecturas!W15) | AU17: =IFERROR(AT17*$AU$3,"") -> 0 | AV17: =IF((Lecturas!Y15-Lecturas!X15)<= 0,"",Lecturas!Y15-Lecturas!X15) | AW17: =IFERROR(AV17*$AW$3,"") -> 0 | AX17: =IF((Lecturas!Z15-Lecturas!Y15)<= 0,"0",Lecturas!Z15-Lecturas!Y15) -> 0 | AY17: =IFERROR(AX17*$AY$3,"0") -> 0 | AZ17: =IF((Lecturas!AA15-Lecturas!Z15)<= 0,"0",Lecturas!AA15-Lecturas!Z15) -> 0 | BA17: =IFERROR(AZ17*$BA$3,"0") -> 0 | BB17: =IF((Lecturas!AB15-Lecturas!AA15)<= 0,"0",Lecturas!AB15-Lecturas!AA15) -> 0.001 | BC17: =IFERROR(BB17*$BC$3,"0") -> 0.014985666 | BD17: =IF((Lecturas!AC15-Lecturas!AB15)<= 0,"0",Lecturas!AC15-Lecturas!AB15) -> 0 | BE17: =IFERROR(BD17*$BE$3,"0") -> 0 | BF17: =IF((Lecturas!AD15-Lecturas!AC15)<= 0,"0",Lecturas!AD15-Lecturas!AC15) -> 0 | BG17: =IFERROR(BF17*$BG$3,"0") -> 0 | BH17: =IF((Lecturas!AE15-Lecturas!AD15)<= 0,"0",Lecturas!AE15-Lecturas!AD15) -> 0 | BI17: =IFERROR(BH17*$BI$3,"0") -> 0 | BJ17: =IF((Lecturas!AF15-Lecturas!AE15)<= 0,"0",Lecturas!AF15-Lecturas!AE15) -> 0 | BK17: =IFERROR(BJ17*$BK$3,"0") -> 0 | BL17: =IF((Lecturas!AG15-Lecturas!AF15)<= 0,"0",Lecturas!AG15-Lecturas!AF15) -> 0 | BM17: =IFERROR(BL17*$BM$3,"0") -> 0 | BN17: =IF((Lecturas!AH15-Lecturas!AG15)<= 0,"0",Lecturas!AH15-Lecturas!AG15) -> 0 | BO17: =IFERROR(BN17*$BO$3,"0") -> 0
A18: =ROUND(AG18,1) -> 0 | B18: =AF18 -> 0 | C18: 306 | D18: JOSE LLERENA RODRIGUEZ | E18: 2034050 | F18: =Lecturas!D16-Lecturas!C16 -> 0 | G18: =F18*$G$3 -> 0 | H18: =IF((Lecturas!E16-Lecturas!D16) < 0, "", Lecturas!E16-Lecturas!D16) -> 0 | I18: =IFERROR(H18*$I$3,"") -> 0 | J18: =IF(OR((Lecturas!F16-Lecturas!E16) < 0), "", Lecturas!F16-Lecturas!E16) -> 0 | K18: =IFERROR(J18*$K$3,"") -> 0 | L18: =IF(OR((Lecturas!G16-Lecturas!F16) < 0), "", Lecturas!G16-Lecturas!F16) -> 0 | M18: =IFERROR(L18*$M$3,"") -> 0 | N18: =IF(OR((Lecturas!H16-Lecturas!G16) < 0), "", Lecturas!H16-Lecturas!G16) -> 0 | O18: =IFERROR(N18*$O$3,"") -> 0 | P18: =IF(OR((Lecturas!I16-Lecturas!H16) < 0), "", Lecturas!I16-Lecturas!H16) -> 0 | Q18: =IFERROR(P18*$Q$3,"") -> 0 | R18: =IF(OR((Lecturas!J16-Lecturas!I16) < 0), "", Lecturas!J16-Lecturas!I16) -> 0 | S18: =IFERROR(R18*$S$3,"") -> 0 | T18: =IF(OR((Lecturas!K16-Lecturas!J16) < 0), "", Lecturas!K16-Lecturas!J16) -> 0 | U18: =IFERROR(T18*$U$3,"") -> 0 | V18: =IF(OR((Lecturas!L16-Lecturas!K16) < 0), "", Lecturas!L16-Lecturas!K16) -> 0 | W18: =IFERROR(V18*$W$3,"") -> 0 | X18: =IF(OR((Lecturas!M16-Lecturas!L16) < 0), "", Lecturas!M16-Lecturas!L16) -> 0 | Y18: =IFERROR(X18*$Y$3,"") -> 0 | Z18: =IF(OR((Lecturas!N16-Lecturas!M16) < 0), "", Lecturas!N16-Lecturas!M16) -> 0 | AA18: =IFERROR(Z18*$AA$3,"") -> 0 | AB18: =IF(OR((Lecturas!O16-Lecturas!N16) < 0), "", Lecturas!O16-Lecturas!N16) -> 0 | AC18: =IFERROR(AB18*$AC$3,"") -> 0 | AD18: =IF(OR((Lecturas!P16-Lecturas!O16) < 0), "", Lecturas!P16-Lecturas!O16) -> 0 | AE18: =IFERROR(AD18*$AE$3,"") -> 0 | AF18: =IF((Lecturas!Q16-Lecturas!P16)< 0,"",Lecturas!Q16-Lecturas!P16) -> 0 | AG18: =IFERROR(AF18*$AG$3,"") -> 0 | AH18: 0 | AI18: =IFERROR(AH18*$AI$3,"") -> 0 | AJ18: =IF((Lecturas!S16-Lecturas!R16)<= 0,"",Lecturas!S16-Lecturas!R16) | AK18: =IFERROR(AJ18*$AK$3,"") -> 0 | AL18: =IF((Lecturas!T16-Lecturas!S16)<= 0,"",Lecturas!T16-Lecturas!S16) | AM18: =IFERROR(AL18*$AM$3,"") -> 0 | AN18: =IF((Lecturas!U16-Lecturas!T16)<= 0,"",Lecturas!U16-Lecturas!T16) | AO18: =IFERROR(AN18*$AO$3,"") -> 0 | AP18: =IF((Lecturas!V16-Lecturas!U16)<= 0,"",Lecturas!V16-Lecturas!U16) | AQ18: =IFERROR(AP18*$AQ$3,"") -> 0 | AR18: =IF((Lecturas!W16-Lecturas!V16)<= 0,"",Lecturas!W16-Lecturas!V16) | AS18: =IFERROR(AR18*$AS$3,"") -> 0 | AT18: =IF((Lecturas!X16-Lecturas!W16)<= 0,"",Lecturas!X16-Lecturas!W16) | AU18: =IFERROR(AT18*$AU$3,"") -> 0 | AV18: =IF((Lecturas!Y16-Lecturas!X16)<= 0,"",Lecturas!Y16-Lecturas!X16) | AW18: =IFERROR(AV18*$AW$3,"") -> 0 | AX18: =IF((Lecturas!Z16-Lecturas!Y16)<= 0,"0",Lecturas!Z16-Lecturas!Y16) -> 0 | AY18: =IFERROR(AX18*$AY$3,"0") -> 0 | AZ18: =IF((Lecturas!AA16-Lecturas!Z16)<= 0,"0",Lecturas!AA16-Lecturas!Z16) -> 0 | BA18: =IFERROR(AZ18*$BA$3,"0") -> 0 | BB18: =IF((Lecturas!AB16-Lecturas!AA16)<= 0,"0",Lecturas!AB16-Lecturas!AA16) -> 0 | BC18: =IFERROR(BB18*$BC$3,"0") -> 0 | BD18: =IF((Lecturas!AC16-Lecturas!AB16)<= 0,"0",Lecturas!AC16-Lecturas!AB16) -> 0 | BE18: =IFERROR(BD18*$BE$3,"0") -> 0 | BF18: =IF((Lecturas!AD16-Lecturas!AC16)<= 0,"0",Lecturas!AD16-Lecturas!AC16) -> 0 | BG18: =IFERROR(BF18*$BG$3,"0") -> 0 | BH18: =IF((Lecturas!AE16-Lecturas!AD16)<= 0,"0",Lecturas!AE16-Lecturas!AD16) -> 0 | BI18: =IFERROR(BH18*$BI$3,"0") -> 0 | BJ18: =IF((Lecturas!AF16-Lecturas!AE16)<= 0,"0",Lecturas!AF16-Lecturas!AE16) -> 0 | BK18: =IFERROR(BJ18*$BK$3,"0") -> 0 | BL18: =IF((Lecturas!AG16-Lecturas!AF16)<= 0,"0",Lecturas!AG16-Lecturas!AF16) -> 0 | BM18: =IFERROR(BL18*$BM$3,"0") -> 0 | BN18: =IF((Lecturas!AH16-Lecturas!AG16)<= 0,"0",Lecturas!AH16-Lecturas!AG16) -> 0 | BO18: =IFERROR(BN18*$BO$3,"0") -> 0
A19: =ROUND(AG19,1) -> 9.5 | B19: =AF19 -> 0.666 | C19: 402 | D19: GARREAUD INDACOCHEA MARIA ELENA | E19: 2034057 | F19: =Lecturas!D17-Lecturas!C17 -> 2.866 | G19: =F19*$G$3 -> 64.014767 | H19: =IF((Lecturas!E17-Lecturas!D17) < 0, "", Lecturas!E17-Lecturas!D17) -> 2.958 | I19: =IFERROR(H19*$I$3,"") -> 52.84671 | J19: =IF(OR((Lecturas!F17-Lecturas!E17) <= 0), "", Lecturas!F17-Lecturas!E17) -> 2.77 | K19: =IFERROR(J19*$K$3,"") -> 33.685485 | L19: =IF(OR((Lecturas!G17-Lecturas!F17) <= 0), "", Lecturas!G17-Lecturas!F17) -> 3.926 | M19: =IFERROR(L19*$M$3,"") -> 61.287359 | N19: =IF(OR((Lecturas!H17-Lecturas!G17) <= 0), "", Lecturas!H17-Lecturas!G17) -> 9.96 | O19: =IFERROR(N19*$O$3,"") -> 151.35886 | P19: =IF(OR((Lecturas!I17-Lecturas!H17) <= 0), "", Lecturas!I17-Lecturas!H17) -> 7.319 | Q19: =IFERROR(P19*$Q$3,"") -> 108.62089 | R19: =IF(OR((Lecturas!J17-Lecturas!I17) <= 0), "", Lecturas!J17-Lecturas!I17) -> 6.293 | S19: =IFERROR(R19*$S$3,"") -> 104.28462 | T19: =IF(OR((Lecturas!K17-Lecturas!J17) <= 0), "", Lecturas!K17-Lecturas!J17) -> 4.278 | U19: =IFERROR(T19*$U$3,"") -> 75.130509 | V19: =IF(OR((Lecturas!L17-Lecturas!K17) < 0), "", Lecturas!L17-Lecturas!K17) -> 4.653 | W19: =IFERROR(V19*$W$3,"") -> 56.875827 | X19: =IF(OR((Lecturas!M17-Lecturas!L17) < 0), "", Lecturas!M17-Lecturas!L17) -> 1.431 | Y19: =IFERROR(X19*$Y$3,"") -> 17.364293 | Z19: =IF(OR((Lecturas!N17-Lecturas!M17) <= 0), "", Lecturas!N17-Lecturas!M17) -> 4.414 | AA19: =IFERROR(Z19*$AA$3,"") -> 62.177024 | AB19: =IF(OR((Lecturas!O17-Lecturas!N17) < 0), "", Lecturas!O17-Lecturas!N17) -> 5.163 | AC19: =IFERROR(AB19*$AC$3,"") -> 66.329263 | AD19: =IF(OR((Lecturas!P17-Lecturas!O17) < 0), "", Lecturas!P17-Lecturas!O17) -> 4.288 | AE19: =IFERROR(AD19*$AE$3,"") -> 53.935263 | AF19: =IF((Lecturas!Q17-Lecturas!P17)<= 0,"",Lecturas!Q17-Lecturas!P17) -> 0.666 | AG19: =IFERROR(AF19*$AG$3,"") -> 9.4891019 | AH19: =IF((Lecturas!R17-Lecturas!Q17)<= 0,"",Lecturas!R17-Lecturas!Q17) -> 3.444 | AI19: =IFERROR(AH19*$AI$3,"") -> 47.919667 | AJ19: =IF((Lecturas!S17-Lecturas!R17)<= 0,"",Lecturas!S17-Lecturas!R17) -> 1.822 | AK19: =IFERROR(AJ19*$AK$3,"") -> 26.2509 | AL19: =IF((Lecturas!T17-Lecturas!S17)<= 0,"",Lecturas!T17-Lecturas!S17) -> 3.135 | AM19: =IFERROR(AL19*$AM$3,"") -> 31.126862 | AN19: =IF((Lecturas!U17-Lecturas!T17)<= 0,"",Lecturas!U17-Lecturas!T17) -> 1.449 | AO19: =IFERROR(AN19*$AO$3,"") -> 23.564999 | AP19: =IF((Lecturas!V17-Lecturas!U17)<= 0,"",Lecturas!V17-Lecturas!U17) -> 3.958 | AQ19: =IFERROR(AP19*$AQ$3,"") -> 52.733344 | AR19: =IF((Lecturas!W17-Lecturas!V17)<= 0,"",Lecturas!W17-Lecturas!V17) -> 3.174 | AS19: =IFERROR(AR19*$AS$3,"") -> 37.506924 | AT19: =IF((Lecturas!X17-Lecturas!W17)<= 0,"",Lecturas!X17-Lecturas!W17) -> 4.635 | AU19: =IFERROR(AT19*$AU$3,"") -> 55.736769 | AV19: =IF((Lecturas!Y17-Lecturas!X17)<= 0,"",Lecturas!Y17-Lecturas!X17) -> 4.841 | AW19: =IFERROR(AV19*$AW$3,"") -> 59.34317 | AX19: =IF((Lecturas!Z17-Lecturas!Y17)<= 0,"0",Lecturas!Z17-Lecturas!Y17) -> 0.664 | AY19: =IFERROR(AX19*$AY$3,"0") -> 7.7050985 | AZ19: =IF((Lecturas!AA17-Lecturas!Z17)<= 0,"0",Lecturas!AA17-Lecturas!Z17) -> 1.813 | BA19: =IFERROR(AZ19*$BA$3,"0") -> 25.026708 | BB19: =IF((Lecturas!AB17-Lecturas!AA17)<= 0,"0",Lecturas!AB17-Lecturas!AA17) -> 2.705 | BC19: =IFERROR(BB19*$BC$3,"0") -> 40.536226 | BD19: =IF((Lecturas!AC17-Lecturas!AB17)<= 0,"0",Lecturas!AC17-Lecturas!AB17) -> 2.887 | BE19: =IFERROR(BD19*$BE$3,"0") -> 62.402556 | BF19: =IF((Lecturas!AD17-Lecturas!AC17)<= 0,"0",Lecturas!AD17-Lecturas!AC17) -> 0 | BG19: =IFERROR(BF19*$BG$3,"0") -> 0 | BH19: =IF((Lecturas!AE17-Lecturas!AD17)<= 0,"0",Lecturas!AE17-Lecturas!AD17) -> 0 | BI19: =IFERROR(BH19*$BI$3,"0") -> 0 | BJ19: =IF((Lecturas!AF17-Lecturas!AE17)<= 0,"0",Lecturas!AF17-Lecturas!AE17) -> 0 | BK19: =IFERROR(BJ19*$BK$3,"0") -> 0 | BL19: =IF((Lecturas!AG17-Lecturas!AF17)<= 0,"0",Lecturas!AG17-Lecturas!AF17) -> 0 | BM19: =IFERROR(BL19*$BM$3,"0") -> 0 | BN19: =IF((Lecturas!AH17-Lecturas!AG17)<= 0,"0",Lecturas!AH17-Lecturas!AG17) -> 0 | BO19: =IFERROR(BN19*$BO$3,"0") -> 0
A20: =ROUND(AG20,1) -> 26.1 | B20: =AF20 -> 1.829 | C20: 403 | D20: CARMEN TERESA GANDARILLAS CARDENAS | E20: GA202101900335 | F20: =Lecturas!D18-Lecturas!C18 -> 1.995 | G20: =F20*$G$3 -> 44.560175 | H20: =IF((Lecturas!E18-Lecturas!D18) < 0, "", Lecturas!E18-Lecturas!D18) -> 1.343 | I20: =IFERROR(H20*$I$3,"") -> 23.993621 | J20: =IF(OR((Lecturas!F18-Lecturas!E18) <= 0), "", Lecturas!F18-Lecturas!E18) -> 1.888 | K20: =IFERROR(J20*$K$3,"") -> 22.959638 | L20: =IF(OR((Lecturas!G18-Lecturas!F18) <= 0), "", Lecturas!G18-Lecturas!F18) -> 1.44 | M20: =IFERROR(L20*$M$3,"") -> 22.479317 | N20: =IF(OR((Lecturas!H18-Lecturas!G18) <= 0), "", Lecturas!H18-Lecturas!G18) -> 1.51 | O20: =IFERROR(N20*$O$3,"") -> 22.946975 | P20: =IF(OR((Lecturas!I18-Lecturas!H18) <= 0), "", Lecturas!I18-Lecturas!H18) -> 1.048 | Q20: =IFERROR(P20*$Q$3,"") -> 15.553312 | R20: =IF(OR((Lecturas!J18-Lecturas!I18) <= 0), "", Lecturas!J18-Lecturas!I18) -> 0.946 | S20: =IFERROR(R20*$S$3,"") -> 15.676665 | T20: =IF(OR((Lecturas!K18-Lecturas!J18) <= 0), "", Lecturas!K18-Lecturas!J18) -> 0.978 | U20: =IFERROR(T20*$U$3,"") -> 17.175698 | V20: =IF(OR((Lecturas!L18-Lecturas!K18) < 0), "", Lecturas!L18-Lecturas!K18) -> 0.803 | W20: =IFERROR(V20*$W$3,"") -> 9.81545 | X20: =IF(OR((Lecturas!M18-Lecturas!L18) < 0), "", Lecturas!M18-Lecturas!L18) -> 1.325 | Y20: =IFERROR(X20*$Y$3,"") -> 16.078049 | Z20: =IF(OR((Lecturas!N18-Lecturas!M18) <= 0), "", Lecturas!N18-Lecturas!M18) -> 1.555 | AA20: =IFERROR(Z20*$AA$3,"") -> 21.90423 | AB20: =IF(OR((Lecturas!O18-Lecturas!N18) < 0), "", Lecturas!O18-Lecturas!N18) -> 1.753 | AC20: =IFERROR(AB20*$AC$3,"") -> 22.52086 | AD20: =IF(OR((Lecturas!P18-Lecturas!O18) < 0), "", Lecturas!P18-Lecturas!O18) -> 1.259 | AE20: =IFERROR(AD20*$AE$3,"") -> 15.835937 | AF20: =IF((Lecturas!Q18-Lecturas!P18)<= 0,"",Lecturas!Q18-Lecturas!P18) -> 1.829 | AG20: =IFERROR(AF20*$AG$3,"") -> 26.059411 | AH20: =IF((Lecturas!R18-Lecturas!Q18)<= 0,"",Lecturas!R18-Lecturas!Q18) -> 3.126 | AI20: =IFERROR(AH20*$AI$3,"") -> 43.495028 | AJ20: =IF((Lecturas!S18-Lecturas!R18)<= 0,"",Lecturas!S18-Lecturas!R18) -> 2.256 | AK20: =IFERROR(AJ20*$AK$3,"") -> 32.503859 | AL20: =IF((Lecturas!T18-Lecturas!S18)<= 0,"",Lecturas!T18-Lecturas!S18) -> 3.569 | AM20: =IFERROR(AL20*$AM$3,"") -> 35.435971 | AN20: =IF((Lecturas!U18-Lecturas!T18)<= 0,"",Lecturas!U18-Lecturas!T18) -> 1.112 | AO20: =IFERROR(AN20*$AO$3,"") -> 18.084388 | AP20: =IF((Lecturas!V18-Lecturas!U18)<= 0,"",Lecturas!V18-Lecturas!U18) -> 1.113 | AQ20: =IFERROR(AP20*$AQ$3,"") -> 14.828755 | AR20: =IF((Lecturas!W18-Lecturas!V18)<= 0,"",Lecturas!W18-Lecturas!V18) -> 1.777 | AS20: =IFERROR(AR20*$AS$3,"") -> 20.998678 | AT20: =IF((Lecturas!X18-Lecturas!W18)<= 0,"",Lecturas!X18-Lecturas!W18) -> 1.259 | AU20: =IFERROR(AT20*$AU$3,"") -> 15.139718 | AV20: =IF((Lecturas!Y18-Lecturas!X18)<= 0,"",Lecturas!Y18-Lecturas!X18) -> 0.293 | AW20: =IFERROR(AV20*$AW$3,"") -> 3.5917267 | AX20: =IF((Lecturas!Z18-Lecturas!Y18)<= 0,"0",Lecturas!Z18-Lecturas!Y18) -> 1.44 | AY20: =IFERROR(AX20*$AY$3,"0") -> 16.709852 | AZ20: =IF((Lecturas!AA18-Lecturas!Z18)<= 0,"0",Lecturas!AA18-Lecturas!Z18) -> 5.25 | BA20: =IFERROR(AZ20*$BA$3,"0") -> 72.471162 | BB20: =IF((Lecturas!AB18-Lecturas!AA18)<= 0,"0",Lecturas!AB18-Lecturas!AA18) -> 5.995 | BC20: =IFERROR(BB20*$BC$3,"0") -> 89.839067 | BD20: =IF((Lecturas!AC18-Lecturas!AB18)<= 0,"0",Lecturas!AC18-Lecturas!AB18) -> 4.739 | BE20: =IFERROR(BD20*$BE$3,"0") -> 102.43357 | BF20: =IF((Lecturas!AD18-Lecturas!AC18)<= 0,"0",Lecturas!AD18-Lecturas!AC18) -> 0 | BG20: =IFERROR(BF20*$BG$3,"0") -> 0 | BH20: =IF((Lecturas!AE18-Lecturas!AD18)<= 0,"0",Lecturas!AE18-Lecturas!AD18) -> 0 | BI20: =IFERROR(BH20*$BI$3,"0") -> 0 | BJ20: =IF((Lecturas!AF18-Lecturas!AE18)<= 0,"0",Lecturas!AF18-Lecturas!AE18) -> 0 | BK20: =IFERROR(BJ20*$BK$3,"0") -> 0 | BL20: =IF((Lecturas!AG18-Lecturas!AF18)<= 0,"0",Lecturas!AG18-Lecturas!AF18) -> 0 | BM20: =IFERROR(BL20*$BM$3,"0") -> 0 | BN20: =IF((Lecturas!AH18-Lecturas!AG18)<= 0,"0",Lecturas!AH18-Lecturas!AG18) -> 0 | BO20: =IFERROR(BN20*$BO$3,"0") -> 0
A21: =ROUND(AG21,1) -> 40 | B21: =AF21 -> 2.808 | C21: 404 | D21: MARIA VIVANCO FIGALLO | E21: 2034042 | F21: =Lecturas!D19-Lecturas!C19 -> 0 | G21: =F21*$G$3 -> 0 | H21: =IF((Lecturas!E19-Lecturas!D19) < 0, "", Lecturas!E19-Lecturas!D19) -> 0 | I21: =IFERROR(H21*$I$3,"") -> 0 | J21: =IF(OR((Lecturas!F19-Lecturas!E19) < 0), "", Lecturas!F19-Lecturas!E19) -> 0 | K21: =IFERROR(J21*$K$3,"") -> 0 | L21: =IF(OR((Lecturas!G19-Lecturas!F19) <0), "", Lecturas!G19-Lecturas!F19) -> 0 | M21: =IFERROR(L21*$M$3,"") -> 0 | N21: =IF(OR((Lecturas!H19-Lecturas!G19) < 0), "", Lecturas!H19-Lecturas!G19) -> 0 | O21: =IFERROR(N21*$O$3,"") -> 0 | P21: =IF(OR((Lecturas!I19-Lecturas!H19) < 0), "", Lecturas!I19-Lecturas!H19) -> 0 | Q21: =IFERROR(P21*$Q$3,"") -> 0 | R21: =IF(OR((Lecturas!J19-Lecturas!I19) < 0), "", Lecturas!J19-Lecturas!I19) -> 0 | S21: =IFERROR(R21*$S$3,"") -> 0 | T21: =IF(OR((Lecturas!K19-Lecturas!J19) < 0), "", Lecturas!K19-Lecturas!J19) -> 0 | U21: =IFERROR(T21*$U$3,"") -> 0 | V21: =IF(OR((Lecturas!L19-Lecturas!K19) < 0), "", Lecturas!L19-Lecturas!K19) -> 0.264 | W21: =IFERROR(V21*$W$3,"") -> 3.2269973 | X21: =IF(OR((Lecturas!M19-Lecturas!L19) < 0), "", Lecturas!M19-Lecturas!L19) -> 0 | Y21: =IFERROR(X21*$Y$3,"") -> 0 | Z21: =IF(OR((Lecturas!N19-Lecturas!M19) < 0), "", Lecturas!N19-Lecturas!M19) -> 0 | AA21: =IFERROR(Z21*$AA$3,"") -> 0 | AB21: =IF(OR((Lecturas!O19-Lecturas!N19) < 0), "", Lecturas!O19-Lecturas!N19) -> 0.13 | AC21: =IFERROR(AB21*$AC$3,"") -> 1.6701151 | AD21: =IF(OR((Lecturas!P19-Lecturas!O19) < 0), "", Lecturas!P19-Lecturas!O19) -> 2.073 | AE21: =IFERROR(AD21*$AE$3,"") -> 26.07458 | AF21: =IF((Lecturas!Q19-Lecturas!P19)<= 0,"",Lecturas!Q19-Lecturas!P19) -> 2.808 | AG21: =IFERROR(AF21*$AG$3,"") -> 40.008105 | AH21: =IF((Lecturas!R19-Lecturas!Q19)<= 0,"",Lecturas!R19-Lecturas!Q19) -> 0.472 | AI21: =IFERROR(AH21*$AI$3,"") -> 6.5673875 | AJ21: =IF((Lecturas!S19-Lecturas!R19)<= 0,"",Lecturas!S19-Lecturas!R19) | AK21: =IFERROR(AJ21*$AK$3,"") -> 0 | AL21: =IF((Lecturas!T19-Lecturas!S19)<= 0,"",Lecturas!T19-Lecturas!S19) | AM21: =IFERROR(AL21*$AM$3,"") -> 0 | AN21: =IF((Lecturas!U19-Lecturas!T19)<= 0,"",Lecturas!U19-Lecturas!T19) | AO21: =IFERROR(AN21*$AO$3,"") -> 0 | AP21: =IF((Lecturas!V19-Lecturas!U19)<= 0,"",Lecturas!V19-Lecturas!U19) | AQ21: =IFERROR(AP21*$AQ$3,"") -> 0 | AR21: =IF((Lecturas!W19-Lecturas!V19)<= 0,"",Lecturas!W19-Lecturas!V19) | AS21: =IFERROR(AR21*$AS$3,"") -> 0 | AT21: =IF((Lecturas!X19-Lecturas!W19)<= 0,"",Lecturas!X19-Lecturas!W19) -> 5.095 | AU21: =IFERROR(AT21*$AU$3,"") -> 61.268357 | AV21: =IF((Lecturas!Y19-Lecturas!X19)<= 0,"",Lecturas!Y19-Lecturas!X19) -> 4.638 | AW21: =IFERROR(AV21*$AW$3,"") -> 56.854704 | AX21: =IF((Lecturas!Z19-Lecturas!Y19)<= 0,"0",Lecturas!Z19-Lecturas!Y19) -> 2.889 | AY21: =IFERROR(AX21*$AY$3,"0") -> 33.524141 | AZ21: =IF((Lecturas!AA19-Lecturas!Z19)<= 0,"0",Lecturas!AA19-Lecturas!Z19) -> 5.067 | BA21: =IFERROR(AZ21*$BA$3,"0") -> 69.945024 | BB21: =IF((Lecturas!AB19-Lecturas!AA19)<= 0,"0",Lecturas!AB19-Lecturas!AA19) -> 0.206 | BC21: =IFERROR(BB21*$BC$3,"0") -> 3.0870472 | BD21: =IF((Lecturas!AC19-Lecturas!AB19)<= 0,"0",Lecturas!AC19-Lecturas!AB19) -> 0 | BE21: =IFERROR(BD21*$BE$3,"0") -> 0 | BF21: =IF((Lecturas!AD19-Lecturas!AC19)<= 0,"0",Lecturas!AD19-Lecturas!AC19) -> 0 | BG21: =IFERROR(BF21*$BG$3,"0") -> 0 | BH21: =IF((Lecturas!AE19-Lecturas!AD19)<= 0,"0",Lecturas!AE19-Lecturas!AD19) -> 0 | BI21: =IFERROR(BH21*$BI$3,"0") -> 0 | BJ21: =IF((Lecturas!AF19-Lecturas!AE19)<= 0,"0",Lecturas!AF19-Lecturas!AE19) -> 0 | BK21: =IFERROR(BJ21*$BK$3,"0") -> 0 | BL21: =IF((Lecturas!AG19-Lecturas!AF19)<= 0,"0",Lecturas!AG19-Lecturas!AF19) -> 0 | BM21: =IFERROR(BL21*$BM$3,"0") -> 0 | BN21: =IF((Lecturas!AH19-Lecturas!AG19)<= 0,"0",Lecturas!AH19-Lecturas!AG19) -> 0 | BO21: =IFERROR(BN21*$BO$3,"0") -> 0
A22: =ROUND(AG22,1) -> 0 | B22: =AF22 -> 0 | C22: 405 | D22: ARMANDO CUETO DUTHURBURU | E22: 2034046 | F22: =Lecturas!D20-Lecturas!C20 -> 0 | G22: =F22*$G$3 -> 0 | H22: =IF((Lecturas!E20-Lecturas!D20) < 0, "", Lecturas!E20-Lecturas!D20) -> 0 | I22: =IFERROR(H22*$I$3,"") -> 0 | J22: =IF(OR((Lecturas!F20-Lecturas!E20) < 0), "", Lecturas!F20-Lecturas!E20) -> 0 | K22: =IFERROR(J22*$K$3,"") -> 0 | L22: =IF(OR((Lecturas!G20-Lecturas!F20) <0), "", Lecturas!G20-Lecturas!F20) -> 0 | M22: =IFERROR(L22*$M$3,"") -> 0 | N22: =IF(OR((Lecturas!H20-Lecturas!G20) < 0), "", Lecturas!H20-Lecturas!G20) -> 0 | O22: =IFERROR(N22*$O$3,"") -> 0 | P22: =IF(OR((Lecturas!I20-Lecturas!H20) < 0), "", Lecturas!I20-Lecturas!H20) -> 0 | Q22: =IFERROR(P22*$Q$3,"") -> 0 | R22: =IF(OR((Lecturas!J20-Lecturas!I20) < 0), "", Lecturas!J20-Lecturas!I20) -> 0 | S22: =IFERROR(R22*$S$3,"") -> 0 | T22: =IF(OR((Lecturas!K20-Lecturas!J20) < 0), "", Lecturas!K20-Lecturas!J20) -> 0 | U22: =IFERROR(T22*$U$3,"") -> 0 | V22: =IF(OR((Lecturas!L20-Lecturas!K20) < 0), "", Lecturas!L20-Lecturas!K20) -> 0 | W22: =IFERROR(V22*$W$3,"") -> 0 | X22: =IF(OR((Lecturas!M20-Lecturas!L20) < 0), "", Lecturas!M20-Lecturas!L20) -> 0 | Y22: =IFERROR(X22*$Y$3,"") -> 0 | Z22: =IF(OR((Lecturas!N20-Lecturas!M20) < 0), "", Lecturas!N20-Lecturas!M20) -> 0 | AA22: =IFERROR(Z22*$AA$3,"") -> 0 | AB22: =IF(OR((Lecturas!O20-Lecturas!N20) < 0), "", Lecturas!O20-Lecturas!N20) -> 0 | AC22: =IFERROR(AB22*$AC$3,"") -> 0 | AD22: =IF(OR((Lecturas!P20-Lecturas!O20) < 0), "", Lecturas!P20-Lecturas!O20) -> 0 | AE22: =IFERROR(AD22*$AE$3,"") -> 0 | AF22: =IF((Lecturas!Q20-Lecturas!P20)< 0,"",Lecturas!Q20-Lecturas!P20) -> 0 | AG22: =IFERROR(AF22*$AG$3,"") -> 0 | AH22: =IF((Lecturas!R20-Lecturas!Q20)<= 0,"",Lecturas!R20-Lecturas!Q20) -> 0.006 | AI22: =IFERROR(AH22*$AI$3,"") -> 0.08348374 | AJ22: =IF((Lecturas!S20-Lecturas!R20)<= 0,"",Lecturas!S20-Lecturas!R20) | AK22: =IFERROR(AJ22*$AK$3,"") -> 0 | AL22: =IF((Lecturas!T20-Lecturas!S20)<= 0,"",Lecturas!T20-Lecturas!S20) | AM22: =IFERROR(AL22*$AM$3,"") -> 0 | AN22: =IF((Lecturas!U20-Lecturas!T20)<= 0,"",Lecturas!U20-Lecturas!T20) | AO22: =IFERROR(AN22*$AO$3,"") -> 0 | AP22: =IF((Lecturas!V20-Lecturas!U20)<= 0,"",Lecturas!V20-Lecturas!U20) | AQ22: =IFERROR(AP22*$AQ$3,"") -> 0 | AR22: =IF((Lecturas!W20-Lecturas!V20)<= 0,"",Lecturas!W20-Lecturas!V20) | AS22: =IFERROR(AR22*$AS$3,"") -> 0 | AT22: =IF((Lecturas!X20-Lecturas!W20)<= 0,"",Lecturas!X20-Lecturas!W20) | AU22: =IFERROR(AT22*$AU$3,"") -> 0 | AV22: =IF((Lecturas!Y20-Lecturas!X20)<= 0,"",Lecturas!Y20-Lecturas!X20) | AW22: =IFERROR(AV22*$AW$3,"") -> 0 | AX22: =IF((Lecturas!Z20-Lecturas!Y20)<= 0,"0",Lecturas!Z20-Lecturas!Y20) -> 0 | AY22: =IFERROR(AX22*$AY$3,"0") -> 0 | AZ22: =IF((Lecturas!AA20-Lecturas!Z20)<= 0,"0",Lecturas!AA20-Lecturas!Z20) -> 0 | BA22: =IFERROR(AZ22*$BA$3,"0") -> 0 | BB22: =IF((Lecturas!AB20-Lecturas!AA20)<= 0,"0",Lecturas!AB20-Lecturas!AA20) -> 0 | BC22: =IFERROR(BB22*$BC$3,"0") -> 0 | BD22: =IF((Lecturas!AC20-Lecturas!AB20)<= 0,"0",Lecturas!AC20-Lecturas!AB20) -> 0 | BE22: =IFERROR(BD22*$BE$3,"0") -> 0 | BF22: =IF((Lecturas!AD20-Lecturas!AC20)<= 0,"0",Lecturas!AD20-Lecturas!AC20) -> 0 | BG22: =IFERROR(BF22*$BG$3,"0") -> 0 | BH22: =IF((Lecturas!AE20-Lecturas!AD20)<= 0,"0",Lecturas!AE20-Lecturas!AD20) -> 0 | BI22: =IFERROR(BH22*$BI$3,"0") -> 0 | BJ22: =IF((Lecturas!AF20-Lecturas!AE20)<= 0,"0",Lecturas!AF20-Lecturas!AE20) -> 0 | BK22: =IFERROR(BJ22*$BK$3,"0") -> 0 | BL22: =IF((Lecturas!AG20-Lecturas!AF20)<= 0,"0",Lecturas!AG20-Lecturas!AF20) -> 0 | BM22: =IFERROR(BL22*$BM$3,"0") -> 0 | BN22: =IF((Lecturas!AH20-Lecturas!AG20)<= 0,"0",Lecturas!AH20-Lecturas!AG20) -> 0 | BO22: =IFERROR(BN22*$BO$3,"0") -> 0
A23: =ROUND(AG23,1) -> 0 | B23: =AF23 -> 0 | C23: 406 | D23: WALTER PEREZ RENGIFO | E23: 2034035 | F23: =Lecturas!D21-Lecturas!C21 -> 0 | G23: =F23*$G$3 -> 0 | H23: =IF((Lecturas!E21-Lecturas!D21) < 0, "", Lecturas!E21-Lecturas!D21) -> 0 | I23: =IFERROR(H23*$I$3,"") -> 0 | J23: =IF(OR((Lecturas!F21-Lecturas!E21) < 0), "", Lecturas!F21-Lecturas!E21) -> 0 | K23: =IFERROR(J23*$K$3,"") -> 0 | L23: =IF(OR((Lecturas!G21-Lecturas!F21) <0), "", Lecturas!G21-Lecturas!F21) -> 0 | M23: =IFERROR(L23*$M$3,"") -> 0 | N23: =IF(OR((Lecturas!H21-Lecturas!G21) < 0), "", Lecturas!H21-Lecturas!G21) -> 0 | O23: =IFERROR(N23*$O$3,"") -> 0 | P23: =IF(OR((Lecturas!I21-Lecturas!H21) < 0), "", Lecturas!I21-Lecturas!H21) -> 0 | Q23: =IFERROR(P23*$Q$3,"") -> 0 | R23: =IF(OR((Lecturas!J21-Lecturas!I21) < 0), "", Lecturas!J21-Lecturas!I21) -> 0 | S23: =IFERROR(R23*$S$3,"") -> 0 | T23: =IF(OR((Lecturas!K21-Lecturas!J21) < 0), "", Lecturas!K21-Lecturas!J21) -> 0 | U23: =IFERROR(T23*$U$3,"") -> 0 | V23: =IF(OR((Lecturas!L21-Lecturas!K21) < 0), "", Lecturas!L21-Lecturas!K21) -> 0 | W23: =IFERROR(V23*$W$3,"") -> 0 | X23: =IF(OR((Lecturas!M21-Lecturas!L21) < 0), "", Lecturas!M21-Lecturas!L21) -> 0 | Y23: =IFERROR(X23*$Y$3,"") -> 0 | Z23: =IF(OR((Lecturas!N21-Lecturas!M21) < 0), "", Lecturas!N21-Lecturas!M21) -> 0 | AA23: =IFERROR(Z23*$AA$3,"") -> 0 | AB23: =IF(OR((Lecturas!O21-Lecturas!N21) < 0), "", Lecturas!O21-Lecturas!N21) -> 0 | AC23: =IFERROR(AB23*$AC$3,"") -> 0 | AD23: =IF(OR((Lecturas!P21-Lecturas!O21) < 0), "", Lecturas!P21-Lecturas!O21) -> 0 | AE23: =IFERROR(AD23*$AE$3,"") -> 0 | AF23: =IF((Lecturas!Q21-Lecturas!P21)< 0,"",Lecturas!Q21-Lecturas!P21) -> 0 | AG23: =IFERROR(AF23*$AG$3,"") -> 0 | AH23: =IF((Lecturas!R21-Lecturas!Q21)<= 0,"",Lecturas!R21-Lecturas!Q21) -> 0.017 | AI23: =IFERROR(AH23*$AI$3,"") -> 0.23653726 | AJ23: =IF((Lecturas!S21-Lecturas!R21)<= 0,"",Lecturas!S21-Lecturas!R21) -> 0.002 | AK23: =IFERROR(AJ23*$AK$3,"") -> 0.028815478 | AL23: =IF((Lecturas!T21-Lecturas!S21)<= 0,"",Lecturas!T21-Lecturas!S21) -> 0.003 | AM23: =IFERROR(AL23*$AM$3,"") -> 0.02978647 | AN23: =IF((Lecturas!U21-Lecturas!T21)<= 0,"",Lecturas!U21-Lecturas!T21) -> 0.002 | AO23: =IFERROR(AN23*$AO$3,"") -> 0.032525878 | AP23: =IF((Lecturas!V21-Lecturas!U21)<= 0,"",Lecturas!V21-Lecturas!U21) -> 0.002 | AQ23: =IFERROR(AP23*$AQ$3,"") -> 0.02664646 | AR23: =IF((Lecturas!W21-Lecturas!V21)<= 0,"",Lecturas!W21-Lecturas!V21) -> 0.002 | AS23: =IFERROR(AR23*$AS$3,"") -> 0.023633853 | AT23: =IF((Lecturas!X21-Lecturas!W21)<= 0,"",Lecturas!X21-Lecturas!W21) -> 0.002 | AU23: =IFERROR(AT23*$AU$3,"") -> 0.024050386 | AV23: =IF((Lecturas!Y21-Lecturas!X21)<= 0,"",Lecturas!Y21-Lecturas!X21) -> 0.001 | AW23: =IFERROR(AV23*$AW$3,"") -> 0.012258453 | AX23: =IF((Lecturas!Z21-Lecturas!Y21)<= 0,"0",Lecturas!Z21-Lecturas!Y21) -> 0 | AY23: =IFERROR(AX23*$AY$3,"0") -> 0 | AZ23: =IF((Lecturas!AA21-Lecturas!Z21)<= 0,"0",Lecturas!AA21-Lecturas!Z21) -> 0 | BA23: =IFERROR(AZ23*$BA$3,"0") -> 0 | BB23: =IF((Lecturas!AB21-Lecturas!AA21)<= 0,"0",Lecturas!AB21-Lecturas!AA21) -> 0.005 | BC23: =IFERROR(BB23*$BC$3,"0") -> 0.074928329 | BD23: =IF((Lecturas!AC21-Lecturas!AB21)<= 0,"0",Lecturas!AC21-Lecturas!AB21) -> 0.002 | BE23: =IFERROR(BD23*$BE$3,"0") -> 0.043230035 | BF23: =IF((Lecturas!AD21-Lecturas!AC21)<= 0,"0",Lecturas!AD21-Lecturas!AC21) -> 0 | BG23: =IFERROR(BF23*$BG$3,"0") -> 0 | BH23: =IF((Lecturas!AE21-Lecturas!AD21)<= 0,"0",Lecturas!AE21-Lecturas!AD21) -> 0 | BI23: =IFERROR(BH23*$BI$3,"0") -> 0 | BJ23: =IF((Lecturas!AF21-Lecturas!AE21)<= 0,"0",Lecturas!AF21-Lecturas!AE21) -> 0 | BK23: =IFERROR(BJ23*$BK$3,"0") -> 0 | BL23: =IF((Lecturas!AG21-Lecturas!AF21)<= 0,"0",Lecturas!AG21-Lecturas!AF21) -> 0 | BM23: =IFERROR(BL23*$BM$3,"0") -> 0 | BN23: =IF((Lecturas!AH21-Lecturas!AG21)<= 0,"0",Lecturas!AH21-Lecturas!AG21) -> 0 | BO23: =IFERROR(BN23*$BO$3,"0") -> 0
A24: =ROUND(AG24,1) -> 0 | B24: =AF24 -> 0.001 | C24: 501 | D24: GEHNI DELGADO VDA. DE MARINI | E24: GA2003002006 | F24: =Lecturas!D22-Lecturas!C22 -> 5.517 | G24: =F24*$G$3 -> 123.22731 | H24: =IF((Lecturas!E22-Lecturas!D22) < 0, "", Lecturas!E22-Lecturas!D22) -> 10.774 | I24: =IFERROR(H24*$I$3,"") -> 192.48494 | J24: =IF(OR((Lecturas!F22-Lecturas!E22) < 0), "", Lecturas!F22-Lecturas!E22) -> 0.797 | K24: =IFERROR(J24*$K$3,"") -> 9.6921775 | L24: =IF(OR((Lecturas!G22-Lecturas!F22) < 0), "", Lecturas!G22-Lecturas!F22) -> 0 | M24: =IFERROR(L24*$M$3,"") -> 0 | N24: =IF(OR((Lecturas!H22-Lecturas!G22) < 0), "", Lecturas!H22-Lecturas!G22) -> 0 | O24: =IFERROR(N24*$O$3,"") -> 0 | P24: =IF(OR((Lecturas!I22-Lecturas!H22) < 0), "", Lecturas!I22-Lecturas!H22) -> 0 | Q24: =IFERROR(P24*$Q$3,"") -> 0 | R24: =IF(OR((Lecturas!J22-Lecturas!I22) < 0), "", Lecturas!J22-Lecturas!I22) -> 0 | S24: =IFERROR(R24*$S$3,"") -> 0 | T24: =IF(OR((Lecturas!K22-Lecturas!J22) < 0), "", Lecturas!K22-Lecturas!J22) -> 0 | U24: =IFERROR(T24*$U$3,"") -> 0 | V24: =IF(OR((Lecturas!L22-Lecturas!K22) < 0), "", Lecturas!L22-Lecturas!K22) -> 0 | W24: =IFERROR(V24*$W$3,"") -> 0 | X24: =IF(OR((Lecturas!M22-Lecturas!L22) < 0), "", Lecturas!M22-Lecturas!L22) -> 0 | Y24: =IFERROR(X24*$Y$3,"") -> 0 | Z24: =IF(OR((Lecturas!N22-Lecturas!M22) < 0), "", Lecturas!N22-Lecturas!M22) -> 0 | AA24: =IFERROR(Z24*$AA$3,"") -> 0 | AB24: =IF(OR((Lecturas!O22-Lecturas!N22) < 0), "", Lecturas!O22-Lecturas!N22) -> 0 | AC24: =IFERROR(AB24*$AC$3,"") -> 0 | AD24: =IF(OR((Lecturas!P22-Lecturas!O22) < 0), "", Lecturas!P22-Lecturas!O22) -> 0 | AE24: =IFERROR(AD24*$AE$3,"") -> 0 | AF24: =IF((Lecturas!Q22-Lecturas!P22)<= 0,"",Lecturas!Q22-Lecturas!P22) -> 0.001 | AG24: =IFERROR(AF24*$AG$3,"") -> 0.014247901 | AH24: 0 | AI24: =IFERROR(AH24*$AI$3,"") -> 0 | AJ24: =IF((Lecturas!S22-Lecturas!R22)<= 0,"",Lecturas!S22-Lecturas!R22) | AK24: =IFERROR(AJ24*$AK$3,"") -> 0 | AL24: =IF((Lecturas!T22-Lecturas!S22)<= 0,"",Lecturas!T22-Lecturas!S22) | AM24: =IFERROR(AL24*$AM$3,"") -> 0 | AN24: =IF((Lecturas!U22-Lecturas!T22)<= 0,"",Lecturas!U22-Lecturas!T22) | AO24: =IFERROR(AN24*$AO$3,"") -> 0 | AP24: =IF((Lecturas!V22-Lecturas!U22)<= 0,"",Lecturas!V22-Lecturas!U22) | AQ24: =IFERROR(AP24*$AQ$3,"") -> 0 | AR24: =IF((Lecturas!W22-Lecturas!V22)<= 0,"",Lecturas!W22-Lecturas!V22) | AS24: =IFERROR(AR24*$AS$3,"") -> 0 | AT24: =IF((Lecturas!X22-Lecturas!W22)<= 0,"",Lecturas!X22-Lecturas!W22) -> 0.001 | AU24: =IFERROR(AT24*$AU$3,"") -> 0.012025193 | AV24: =IF((Lecturas!Y22-Lecturas!X22)<= 0,"",Lecturas!Y22-Lecturas!X22) | AW24: =IFERROR(AV24*$AW$3,"") -> 0 | AX24: =IF((Lecturas!Z22-Lecturas!Y22)<= 0,"0",Lecturas!Z22-Lecturas!Y22) -> 0 | AY24: =IFERROR(AX24*$AY$3,"0") -> 0 | AZ24: =IF((Lecturas!AA22-Lecturas!Z22)<= 0,"0",Lecturas!AA22-Lecturas!Z22) -> 0 | BA24: =IFERROR(AZ24*$BA$3,"0") -> 0 | BB24: =IF((Lecturas!AB22-Lecturas!AA22)<= 0,"0",Lecturas!AB22-Lecturas!AA22) -> 0 | BC24: =IFERROR(BB24*$BC$3,"0") -> 0 | BD24: =IF((Lecturas!AC22-Lecturas!AB22)<= 0,"0",Lecturas!AC22-Lecturas!AB22) -> 0 | BE24: =IFERROR(BD24*$BE$3,"0") -> 0 | BF24: =IF((Lecturas!AD22-Lecturas!AC22)<= 0,"0",Lecturas!AD22-Lecturas!AC22) -> 0 | BG24: =IFERROR(BF24*$BG$3,"0") -> 0 | BH24: =IF((Lecturas!AE22-Lecturas!AD22)<= 0,"0",Lecturas!AE22-Lecturas!AD22) -> 0 | BI24: =IFERROR(BH24*$BI$3,"0") -> 0 | BJ24: =IF((Lecturas!AF22-Lecturas!AE22)<= 0,"0",Lecturas!AF22-Lecturas!AE22) -> 0 | BK24: =IFERROR(BJ24*$BK$3,"0") -> 0 | BL24: =IF((Lecturas!AG22-Lecturas!AF22)<= 0,"0",Lecturas!AG22-Lecturas!AF22) -> 0 | BM24: =IFERROR(BL24*$BM$3,"0") -> 0 | BN24: =IF((Lecturas!AH22-Lecturas!AG22)<= 0,"0",Lecturas!AH22-Lecturas!AG22) -> 0 | BO24: =IFERROR(BN24*$BO$3,"0") -> 0
A25: =ROUND(AG25,1) -> 26.7 | B25: =AF25 -> 1.876 | C25: 502 | D25: CAROLINA JONSSON | E25: 2034055 | F25: =Lecturas!D23-Lecturas!C23 -> 0 | G25: =F25*$G$3 -> 0 | H25: =IF((Lecturas!E23-Lecturas!D23) < 0, "", Lecturas!E23-Lecturas!D23) -> 1.044 | I25: =IFERROR(H25*$I$3,"") -> 18.65178 | J25: =IF(OR((Lecturas!F23-Lecturas!E23) <0), "", Lecturas!F23-Lecturas!E23) -> 0 | K25: =IFERROR(J25*$K$3,"") -> 0 | L25: =IF(OR((Lecturas!G23-Lecturas!F23) < 0), "", Lecturas!G23-Lecturas!F23) -> 0 | M25: =IFERROR(L25*$M$3,"") -> 0 | N25: =IF(OR((Lecturas!H23-Lecturas!G23) < 0), "", Lecturas!H23-Lecturas!G23) -> 0 | O25: =IFERROR(N25*$O$3,"") -> 0 | P25: =IF(OR((Lecturas!I23-Lecturas!H23) <= 0), "", Lecturas!I23-Lecturas!H23) -> 0.425 | Q25: =IFERROR(P25*$Q$3,"") -> 6.3074024 | R25: =IF(OR((Lecturas!J23-Lecturas!I23) <= 0), "", Lecturas!J23-Lecturas!I23) -> 0.652 | S25: =IFERROR(R25*$S$3,"") -> 10.804636 | T25: =IF(OR((Lecturas!K23-Lecturas!J23) <= 0), "", Lecturas!K23-Lecturas!J23) -> 3.493 | U25: =IFERROR(T25*$U$3,"") -> 61.344289 | V25: =IF(OR((Lecturas!L23-Lecturas!K23) < 0), "", Lecturas!L23-Lecturas!K23) -> 2.263 | W25: =IFERROR(V25*$W$3,"") -> 27.661723 | X25: =IF(OR((Lecturas!M23-Lecturas!L23) < 0), "", Lecturas!M23-Lecturas!L23) -> 0.581 | Y25: =IFERROR(X25*$Y$3,"") -> 7.0500727 | Z25: =IF(OR((Lecturas!N23-Lecturas!M23) <= 0), "", Lecturas!N23-Lecturas!M23) -> 2.092 | AA25: =IFERROR(Z25*$AA$3,"") -> 29.468585 | AB25: =IF(OR((Lecturas!O23-Lecturas!N23) < 0), "", Lecturas!O23-Lecturas!N23) -> 1.923 | AC25: =IFERROR(AB25*$AC$3,"") -> 24.704856 | AD25: =IF(OR((Lecturas!P23-Lecturas!O23) < 0), "", Lecturas!P23-Lecturas!O23) -> 3.242 | AE25: =IFERROR(AD25*$AE$3,"") -> 40.77848 | AF25: =IF((Lecturas!Q23-Lecturas!P23)<= 0,"",Lecturas!Q23-Lecturas!P23) -> 1.876 | AG25: =IFERROR(AF25*$AG$3,"") -> 26.729062 | AH25: =IF((Lecturas!R23-Lecturas!Q23)<= 0,"",Lecturas!R23-Lecturas!Q23) -> 0.635 | AI25: =IFERROR(AH25*$AI$3,"") -> 8.8353625 | AJ25: =IF((Lecturas!S23-Lecturas!R23)<= 0,"",Lecturas!S23-Lecturas!R23) -> 0.634 | AK25: =IFERROR(AJ25*$AK$3,"") -> 9.1345065 | AL25: =IF((Lecturas!T23-Lecturas!S23)<= 0,"",Lecturas!T23-Lecturas!S23) -> 0.011 | AM25: =IFERROR(AL25*$AM$3,"") -> 0.10921706 | AN25: =IF((Lecturas!U23-Lecturas!T23)<= 0,"",Lecturas!U23-Lecturas!T23) -> 0.151 | AO25: =IFERROR(AN25*$AO$3,"") -> 2.4557038 | AP25: =IF((Lecturas!V23-Lecturas!U23)<= 0,"",Lecturas!V23-Lecturas!U23) -> 0.738 | AQ25: =IFERROR(AP25*$AQ$3,"") -> 9.8325437 | AR25: =IF((Lecturas!W23-Lecturas!V23)<= 0,"",Lecturas!W23-Lecturas!V23) -> 0.392 | AS25: =IFERROR(AR25*$AS$3,"") -> 4.6322351 | AT25: =IF((Lecturas!X23-Lecturas!W23)<= 0,"",Lecturas!X23-Lecturas!W23) -> 0.197 | AU25: =IFERROR(AT25*$AU$3,"") -> 2.368963 | AV25: =IF((Lecturas!Y23-Lecturas!X23)<= 0,"",Lecturas!Y23-Lecturas!X23) -> 0.101 | AW25: =IFERROR(AV25*$AW$3,"") -> 1.2381037 | AX25: =IF((Lecturas!Z23-Lecturas!Y23)<= 0,"0",Lecturas!Z23-Lecturas!Y23) -> 0.424 | AY25: =IFERROR(AX25*$AY$3,"0") -> 4.9201232 | AZ25: =IF((Lecturas!AA23-Lecturas!Z23)<= 0,"0",Lecturas!AA23-Lecturas!Z23) -> 0.024 | BA25: =IFERROR(AZ25*$BA$3,"0") -> 0.33129674 | BB25: =IF((Lecturas!AB23-Lecturas!AA23)<= 0,"0",Lecturas!AB23-Lecturas!AA23) -> 0.053 | BC25: =IFERROR(BB25*$BC$3,"0") -> 0.79424029 | BD25: =IF((Lecturas!AC23-Lecturas!AB23)<= 0,"0",Lecturas!AC23-Lecturas!AB23) -> 0 | BE25: =IFERROR(BD25*$BE$3,"0") -> 0 | BF25: =IF((Lecturas!AD23-Lecturas!AC23)<= 0,"0",Lecturas!AD23-Lecturas!AC23) -> 0 | BG25: =IFERROR(BF25*$BG$3,"0") -> 0 | BH25: =IF((Lecturas!AE23-Lecturas!AD23)<= 0,"0",Lecturas!AE23-Lecturas!AD23) -> 0 | BI25: =IFERROR(BH25*$BI$3,"0") -> 0 | BJ25: =IF((Lecturas!AF23-Lecturas!AE23)<= 0,"0",Lecturas!AF23-Lecturas!AE23) -> 0 | BK25: =IFERROR(BJ25*$BK$3,"0") -> 0 | BL25: =IF((Lecturas!AG23-Lecturas!AF23)<= 0,"0",Lecturas!AG23-Lecturas!AF23) -> 0 | BM25: =IFERROR(BL25*$BM$3,"0") -> 0 | BN25: =IF((Lecturas!AH23-Lecturas!AG23)<= 0,"0",Lecturas!AH23-Lecturas!AG23) -> 0 | BO25: =IFERROR(BN25*$BO$3,"0") -> 0
A26: =ROUND(AG26,1) -> 45.1 | B26: =AF26 -> 3.164 | C26: 503 | D26: CARLOS AVILA BOCANEGRA | E26: 2034083 | F26: =Lecturas!D24-Lecturas!C24 -> 0.021 | G26: =F26*$G$3 -> 0.46905447 | H26: =IF((Lecturas!E24-Lecturas!D24) < 0, "", Lecturas!E24-Lecturas!D24) -> 0 | I26: =IFERROR(H26*$I$3,"") -> 0 | J26: =IF(OR((Lecturas!F24-Lecturas!E24) < 0), "", Lecturas!F24-Lecturas!E24) -> 0 | K26: =IFERROR(J26*$K$3,"") -> 0 | L26: =IF(OR((Lecturas!G24-Lecturas!F24) <= 0), "", Lecturas!G24-Lecturas!F24) -> 1.126 | M26: =IFERROR(L26*$M$3,"") -> 17.577577 | N26: =IF(OR((Lecturas!H24-Lecturas!G24) < 0), "", Lecturas!H24-Lecturas!G24) -> 0 | O26: =IFERROR(N26*$O$3,"") -> 0 | P26: =IF(OR((Lecturas!I24-Lecturas!H24) < 0), "", Lecturas!I24-Lecturas!H24) -> 0 | Q26: =IFERROR(P26*$Q$3,"") -> 0 | R26: =IF(OR((Lecturas!J24-Lecturas!I24) < 0), "", Lecturas!J24-Lecturas!I24) -> 0 | S26: =IFERROR(R26*$S$3,"") -> 0 | T26: =IF(OR((Lecturas!K24-Lecturas!J24) <= 0), "", Lecturas!K24-Lecturas!J24) -> 0.288 | U26: =IFERROR(T26*$U$3,"") -> 5.0578744 | V26: =IF(OR((Lecturas!L24-Lecturas!K24) < 0), "", Lecturas!L24-Lecturas!K24) -> 1.077 | W26: =IFERROR(V26*$W$3,"") -> 13.164682 | X26: =IF(OR((Lecturas!M24-Lecturas!L24) < 0), "", Lecturas!M24-Lecturas!L24) -> 0.853 | Y26: =IFERROR(X26*$Y$3,"") -> 10.350623 | Z26: =IF(OR((Lecturas!N24-Lecturas!M24) <= 0), "", Lecturas!N24-Lecturas!M24) -> 0.949 | AA26: =IFERROR(Z26*$AA$3,"") -> 13.367919 | AB26: =IF(OR((Lecturas!O24-Lecturas!N24) < 0), "", Lecturas!O24-Lecturas!N24) -> 2.027 | AC26: =IFERROR(AB26*$AC$3,"") -> 26.040948 | AD26: =IF(OR((Lecturas!P24-Lecturas!O24) < 0), "", Lecturas!P24-Lecturas!O24) -> 0.66 | AE26: =IFERROR(AD26*$AE$3,"") -> 8.301603 | AF26: =IF((Lecturas!Q24-Lecturas!P24)<= 0,"",Lecturas!Q24-Lecturas!P24) -> 3.164 | AG26: =IFERROR(AF26*$AG$3,"") -> 45.080358 | AH26: =IF((Lecturas!R24-Lecturas!Q24)<= 0,"",Lecturas!R24-Lecturas!Q24) -> 2.605 | AI26: =IFERROR(AH26*$AI$3,"") -> 36.245857 | AJ26: =IF((Lecturas!S24-Lecturas!R24)<= 0,"",Lecturas!S24-Lecturas!R24) -> 1.299 | AK26: =IFERROR(AJ26*$AK$3,"") -> 18.715653 | AL26: =IF((Lecturas!T24-Lecturas!S24)<= 0,"",Lecturas!T24-Lecturas!S24) -> 1 | AM26: =IFERROR(AL26*$AM$3,"") -> 9.9288235 | AN26: =IF((Lecturas!U24-Lecturas!T24)<= 0,"",Lecturas!U24-Lecturas!T24) -> 2.908 | AO26: =IFERROR(AN26*$AO$3,"") -> 47.292627 | AP26: =IF((Lecturas!V24-Lecturas!U24)<= 0,"",Lecturas!V24-Lecturas!U24) -> 1.003 | AQ26: =IFERROR(AP26*$AQ$3,"") -> 13.3632 | AR26: =IF((Lecturas!W24-Lecturas!V24)<= 0,"",Lecturas!W24-Lecturas!V24) -> 1.767 | AS26: =IFERROR(AR26*$AS$3,"") -> 20.880509 | AT26: =IF((Lecturas!X24-Lecturas!W24)<= 0,"",Lecturas!X24-Lecturas!W24) -> 2.061 | AU26: =IFERROR(AT26*$AU$3,"") -> 24.783922 | AV26: =IF((Lecturas!Y24-Lecturas!X24)<= 0,"",Lecturas!Y24-Lecturas!X24) -> 0.437 | AW26: =IFERROR(AV26*$AW$3,"") -> 5.3569439 | AX26: =IF((Lecturas!Z24-Lecturas!Y24)<= 0,"0",Lecturas!Z24-Lecturas!Y24) -> 0.757 | AY26: =IFERROR(AX26*$AY$3,"0") -> 8.7842765 | AZ26: =IF((Lecturas!AA24-Lecturas!Z24)<= 0,"0",Lecturas!AA24-Lecturas!Z24) -> 1.577 | BA26: =IFERROR(AZ26*$BA$3,"0") -> 21.768957 | BB26: =IF((Lecturas!AB24-Lecturas!AA24)<= 0,"0",Lecturas!AB24-Lecturas!AA24) -> 1.291 | BC26: =IFERROR(BB26*$BC$3,"0") -> 19.346495 | BD26: =IF((Lecturas!AC24-Lecturas!AB24)<= 0,"0",Lecturas!AC24-Lecturas!AB24) -> 2.346 | BE26: =IFERROR(BD26*$BE$3,"0") -> 50.708832 | BF26: =IF((Lecturas!AD24-Lecturas!AC24)<= 0,"0",Lecturas!AD24-Lecturas!AC24) -> 0 | BG26: =IFERROR(BF26*$BG$3,"0") -> 0 | BH26: =IF((Lecturas!AE24-Lecturas!AD24)<= 0,"0",Lecturas!AE24-Lecturas!AD24) -> 0 | BI26: =IFERROR(BH26*$BI$3,"0") -> 0 | BJ26: =IF((Lecturas!AF24-Lecturas!AE24)<= 0,"0",Lecturas!AF24-Lecturas!AE24) -> 0 | BK26: =IFERROR(BJ26*$BK$3,"0") -> 0 | BL26: =IF((Lecturas!AG24-Lecturas!AF24)<= 0,"0",Lecturas!AG24-Lecturas!AF24) -> 0 | BM26: =IFERROR(BL26*$BM$3,"0") -> 0 | BN26: =IF((Lecturas!AH24-Lecturas!AG24)<= 0,"0",Lecturas!AH24-Lecturas!AG24) -> 0 | BO26: =IFERROR(BN26*$BO$3,"0") -> 0
A27: =ROUND(AG27,1) -> 22.4 | B27: =AF27 -> 1.569 | C27: 504 | D27: VALEGA BAELLA ALICIA | E27: 2034037 | F27: =Lecturas!D25-Lecturas!C25 -> 2.5 | G27: =F27*$G$3 -> 55.839818 | H27: =IF((Lecturas!E25-Lecturas!D25) < 0, "", Lecturas!E25-Lecturas!D25) -> 4.239 | I27: =IFERROR(H27*$I$3,"") -> 75.732658 | J27: =IF(OR((Lecturas!F25-Lecturas!E25) <= 0), "", Lecturas!F25-Lecturas!E25) -> 3.094 | K27: =IFERROR(J27*$K$3,"") -> 37.625592 | L27: =IF(OR((Lecturas!G25-Lecturas!F25) <= 0), "", Lecturas!G25-Lecturas!F25) -> 2.026 | M27: =IFERROR(L27*$M$3,"") -> 31.62715 | N27: =IF(OR((Lecturas!H25-Lecturas!G25) <= 0), "", Lecturas!H25-Lecturas!G25) -> 2.307 | O27: =IFERROR(N27*$O$3,"") -> 35.058723 | P27: =IF(OR((Lecturas!I25-Lecturas!H25) <= 0), "", Lecturas!I25-Lecturas!H25) -> 2.44 | Q27: =IFERROR(P27*$Q$3,"") -> 36.21191 | R27: =IF(OR((Lecturas!J25-Lecturas!I25) <= 0), "", Lecturas!J25-Lecturas!I25) -> 2.617 | S27: =IFERROR(R27*$S$3,"") -> 43.367688 | T27: =IF(OR((Lecturas!K25-Lecturas!J25) <= 0), "", Lecturas!K25-Lecturas!J25) -> 2.076 | U27: =IFERROR(T27*$U$3,"") -> 36.458845 | V27: =IF(OR((Lecturas!L25-Lecturas!K25) < 0), "", Lecturas!L25-Lecturas!K25) -> 2.062 | W27: =IFERROR(V27*$W$3,"") -> 25.204804 | X27: =IF(OR((Lecturas!M25-Lecturas!L25) < 0), "", Lecturas!M25-Lecturas!L25) -> 0.959 | Y27: =IFERROR(X27*$Y$3,"") -> 11.636867 | Z27: =IF(OR((Lecturas!N25-Lecturas!M25) <= 0), "", Lecturas!N25-Lecturas!M25) -> 1.629 | AA27: =IFERROR(Z27*$AA$3,"") -> 22.946618 | AB27: =IF(OR((Lecturas!O25-Lecturas!N25) < 0), "", Lecturas!O25-Lecturas!N25) -> 2.341 | AC27: =IFERROR(AB27*$AC$3,"") -> 30.074919 | AD27: =IF(OR((Lecturas!P25-Lecturas!O25) < 0), "", Lecturas!P25-Lecturas!O25) -> 1.567 | AE27: =IFERROR(AD27*$AE$3,"") -> 19.710018 | AF27: =IF((Lecturas!Q25-Lecturas!P25)<= 0,"",Lecturas!Q25-Lecturas!P25) -> 1.569 | AG27: =IFERROR(AF27*$AG$3,"") -> 22.354956 | AH27: =IF((Lecturas!R25-Lecturas!Q25)<= 0,"",Lecturas!R25-Lecturas!Q25) -> 1.288 | AI27: =IFERROR(AH27*$AI$3,"") -> 17.921176 | AJ27: =IF((Lecturas!S25-Lecturas!R25)<= 0,"",Lecturas!S25-Lecturas!R25) -> 2.308 | AK27: =IFERROR(AJ27*$AK$3,"") -> 33.253062 | AL27: =IF((Lecturas!T25-Lecturas!S25)<= 0,"",Lecturas!T25-Lecturas!S25) -> 2.026 | AM27: =IFERROR(AL27*$AM$3,"") -> 20.115796 | AN27: =IF((Lecturas!U25-Lecturas!T25)<= 0,"",Lecturas!U25-Lecturas!T25) -> 1.259 | AO27: =IFERROR(AN27*$AO$3,"") -> 20.47504 | AP27: =IF((Lecturas!V25-Lecturas!U25)<= 0,"",Lecturas!V25-Lecturas!U25) -> 1.129 | AQ27: =IFERROR(AP27*$AQ$3,"") -> 15.041927 | AR27: =IF((Lecturas!W25-Lecturas!V25)<= 0,"",Lecturas!W25-Lecturas!V25) -> 0.344 | AS27: =IFERROR(AR27*$AS$3,"") -> 4.0650226 | AT27: =IF((Lecturas!X25-Lecturas!W25)<= 0,"",Lecturas!X25-Lecturas!W25) -> 3.214 | AU27: =IFERROR(AT27*$AU$3,"") -> 38.64897 | AV27: =IF((Lecturas!Y25-Lecturas!X25)<= 0,"",Lecturas!Y25-Lecturas!X25) -> 1.811 | AW27: =IFERROR(AV27*$AW$3,"") -> 22.200058 | AX27: =IF((Lecturas!Z25-Lecturas!Y25)<= 0,"0",Lecturas!Z25-Lecturas!Y25) -> 1.936 | AY27: =IFERROR(AX27*$AY$3,"0") -> 22.465468 | AZ27: =IF((Lecturas!AA25-Lecturas!Z25)<= 0,"0",Lecturas!AA25-Lecturas!Z25) -> 2.593 | BA27: =IFERROR(AZ27*$BA$3,"0") -> 35.793852 | BB27: =IF((Lecturas!AB25-Lecturas!AA25)<= 0,"0",Lecturas!AB25-Lecturas!AA25) -> 1.73 | BC27: =IFERROR(BB27*$BC$3,"0") -> 25.925202 | BD27: =IF((Lecturas!AC25-Lecturas!AB25)<= 0,"0",Lecturas!AC25-Lecturas!AB25) -> 1.539 | BE27: =IFERROR(BD27*$BE$3,"0") -> 33.265512 | BF27: =IF((Lecturas!AD25-Lecturas!AC25)<= 0,"0",Lecturas!AD25-Lecturas!AC25) -> 0 | BG27: =IFERROR(BF27*$BG$3,"0") -> 0 | BH27: =IF((Lecturas!AE25-Lecturas!AD25)<= 0,"0",Lecturas!AE25-Lecturas!AD25) -> 0 | BI27: =IFERROR(BH27*$BI$3,"0") -> 0 | BJ27: =IF((Lecturas!AF25-Lecturas!AE25)<= 0,"0",Lecturas!AF25-Lecturas!AE25) -> 0 | BK27: =IFERROR(BJ27*$BK$3,"0") -> 0 | BL27: =IF((Lecturas!AG25-Lecturas!AF25)<= 0,"0",Lecturas!AG25-Lecturas!AF25) -> 0 | BM27: =IFERROR(BL27*$BM$3,"0") -> 0 | BN27: =IF((Lecturas!AH25-Lecturas!AG25)<= 0,"0",Lecturas!AH25-Lecturas!AG25) -> 0 | BO27: =IFERROR(BN27*$BO$3,"0") -> 0
A28: =ROUND(AG28,1) -> 99.4 | B28: =AF28 -> 6.976 | C28: 505 | D28: MONICA LIGARDA CASTRO | E28: 2034047 | F28: =Lecturas!D26-Lecturas!C26 -> 6.565 | G28: =F28*$G$3 -> 146.63536 | H28: =IF((Lecturas!E26-Lecturas!D26) < 0, "", Lecturas!E26-Lecturas!D26) -> 5.227 | I28: =IFERROR(H28*$I$3,"") -> 93.383959 | J28: =IF(OR((Lecturas!F26-Lecturas!E26) <= 0), "", Lecturas!F26-Lecturas!E26) -> 4.997 | K28: =IFERROR(J28*$K$3,"") -> 60.767642 | L28: =IF(OR((Lecturas!G26-Lecturas!F26) <= 0), "", Lecturas!G26-Lecturas!F26) -> 5.296 | M28: =IFERROR(L28*$M$3,"") -> 82.673932 | N28: =IF(OR((Lecturas!H26-Lecturas!G26) <= 0), "", Lecturas!H26-Lecturas!G26) -> 5.578 | O28: =IFERROR(N28*$O$3,"") -> 84.767037 | P28: =IF(OR((Lecturas!I26-Lecturas!H26) <= 0), "", Lecturas!I26-Lecturas!H26) -> 5.167 | Q28: =IFERROR(P28*$Q$3,"") -> 76.683172 | R28: =IF(OR((Lecturas!J26-Lecturas!I26) <= 0), "", Lecturas!J26-Lecturas!I26) -> 6.072 | S28: =IFERROR(R28*$S$3,"") -> 100.62232 | T28: =IF(OR((Lecturas!K26-Lecturas!J26) <= 0), "", Lecturas!K26-Lecturas!J26) -> 4.209 | U28: =IFERROR(T28*$U$3,"") -> 73.918727 | V28: =IF(OR((Lecturas!L26-Lecturas!K26) < 0), "", Lecturas!L26-Lecturas!K26) -> 4.429 | W28: =IFERROR(V28*$W$3,"") -> 54.137768 | X28: =IF(OR((Lecturas!M26-Lecturas!L26) < 0), "", Lecturas!M26-Lecturas!L26) -> 4.68 | Y28: =IFERROR(X28*$Y$3,"") -> 56.788881 | Z28: =IF(OR((Lecturas!N26-Lecturas!M26) <= 0), "", Lecturas!N26-Lecturas!M26) -> 5.7 | AA28: =IFERROR(Z28*$AA$3,"") -> 80.292034 | AB28: =IF(OR((Lecturas!O26-Lecturas!N26) < 0), "", Lecturas!O26-Lecturas!N26) -> 6.024 | AC28: =IFERROR(AB28*$AC$3,"") -> 77.390564 | AD28: =IF(OR((Lecturas!P26-Lecturas!O26) < 0), "", Lecturas!P26-Lecturas!O26) -> 5.187 | AE28: =IFERROR(AD28*$AE$3,"") -> 65.243053 | AF28: =IF((Lecturas!Q26-Lecturas!P26)<= 0,"",Lecturas!Q26-Lecturas!P26) -> 6.976 | AG28: =IFERROR(AF28*$AG$3,"") -> 99.393356 | AH28: =IF((Lecturas!R26-Lecturas!Q26)<= 0,"",Lecturas!R26-Lecturas!Q26) -> 6.073 | AI28: =IFERROR(AH28*$AI$3,"") -> 84.499459 | AJ28: =IF((Lecturas!S26-Lecturas!R26)<= 0,"",Lecturas!S26-Lecturas!R26) -> 6.016 | AK28: =IFERROR(AJ28*$AK$3,"") -> 86.676958 | AL28: =IF((Lecturas!T26-Lecturas!S26)<= 0,"",Lecturas!T26-Lecturas!S26) -> 6.804 | AM28: =IFERROR(AL28*$AM$3,"") -> 67.555715 | AN28: =IF((Lecturas!U26-Lecturas!T26)<= 0,"",Lecturas!U26-Lecturas!T26) -> 4.646 | AO28: =IFERROR(AN28*$AO$3,"") -> 75.557616 | AP28: =IF((Lecturas!V26-Lecturas!U26)<= 0,"",Lecturas!V26-Lecturas!U26) -> 5.181 | AQ28: =IFERROR(AP28*$AQ$3,"") -> 69.027654 | AR28: =IF((Lecturas!W26-Lecturas!V26)<= 0,"",Lecturas!W26-Lecturas!V26) -> 5.761 | AS28: =IFERROR(AR28*$AS$3,"") -> 68.077312 | AT28: =IF((Lecturas!X26-Lecturas!W26)<= 0,"",Lecturas!X26-Lecturas!W26) -> 5.173 | AU28: =IFERROR(AT28*$AU$3,"") -> 62.206322 | AV28: =IF((Lecturas!Y26-Lecturas!X26)<= 0,"",Lecturas!Y26-Lecturas!X26) -> 4.672 | AW28: =IFERROR(AV28*$AW$3,"") -> 57.271491 | AX28: =IF((Lecturas!Z26-Lecturas!Y26)<= 0,"0",Lecturas!Z26-Lecturas!Y26) -> 5.01 | AY28: =IFERROR(AX28*$AY$3,"0") -> 58.136361 | AZ28: =IF((Lecturas!AA26-Lecturas!Z26)<= 0,"0",Lecturas!AA26-Lecturas!Z26) -> 5.094 | BA28: =IFERROR(AZ28*$BA$3,"0") -> 70.317733 | BB28: =IF((Lecturas!AB26-Lecturas!AA26)<= 0,"0",Lecturas!AB26-Lecturas!AA26) -> 4.666 | BC28: =IFERROR(BB28*$BC$3,"0") -> 69.923117 | BD28: =IF((Lecturas!AC26-Lecturas!AB26)<= 0,"0",Lecturas!AC26-Lecturas!AB26) -> 4.608 | BE28: =IFERROR(BD28*$BE$3,"0") -> 99.602002 | BF28: =IF((Lecturas!AD26-Lecturas!AC26)<= 0,"0",Lecturas!AD26-Lecturas!AC26) -> 0 | BG28: =IFERROR(BF28*$BG$3,"0") -> 0 | BH28: =IF((Lecturas!AE26-Lecturas!AD26)<= 0,"0",Lecturas!AE26-Lecturas!AD26) -> 0 | BI28: =IFERROR(BH28*$BI$3,"0") -> 0 | BJ28: =IF((Lecturas!AF26-Lecturas!AE26)<= 0,"0",Lecturas!AF26-Lecturas!AE26) -> 0 | BK28: =IFERROR(BJ28*$BK$3,"0") -> 0 | BL28: =IF((Lecturas!AG26-Lecturas!AF26)<= 0,"0",Lecturas!AG26-Lecturas!AF26) -> 0 | BM28: =IFERROR(BL28*$BM$3,"0") -> 0 | BN28: =IF((Lecturas!AH26-Lecturas!AG26)<= 0,"0",Lecturas!AH26-Lecturas!AG26) -> 0 | BO28: =IFERROR(BN28*$BO$3,"0") -> 0
A29: =ROUND(AG29,1) -> 14.7 | B29: =AF29 -> 1.035 | C29: 506 | D29: TELMO SALAZAR GONZALES | E29: 2034045 | F29: =Lecturas!D27-Lecturas!C27 -> 0.542 | G29: =F29*$G$3 -> 12.106073 | H29: =IF((Lecturas!E27-Lecturas!D27) < 0, "", Lecturas!E27-Lecturas!D27) -> 0.417 | I29: =IFERROR(H29*$I$3,"") -> 7.4499925 | J29: =IF(OR((Lecturas!F27-Lecturas!E27) <= 0), "", Lecturas!F27-Lecturas!E27) -> 0.458 | K29: =IFERROR(J29*$K$3,"") -> 5.5696578 | L29: =IF(OR((Lecturas!G27-Lecturas!F27) <= 0), "", Lecturas!G27-Lecturas!F27) -> 0.475 | M29: =IFERROR(L29*$M$3,"") -> 7.4150524 | N29: =IF(OR((Lecturas!H27-Lecturas!G27) <= 0), "", Lecturas!H27-Lecturas!G27) -> 0.868 | O29: =IFERROR(N29*$O$3,"") -> 13.190711 | P29: =IF(OR((Lecturas!I27-Lecturas!H27) <= 0), "", Lecturas!I27-Lecturas!H27) -> 0.557 | Q29: =IFERROR(P29*$Q$3,"") -> 8.2664074 | R29: =IF(OR((Lecturas!J27-Lecturas!I27) <= 0), "", Lecturas!J27-Lecturas!I27) -> 1.266 | S29: =IFERROR(R29*$S$3,"") -> 20.979554 | T29: =IF(OR((Lecturas!K27-Lecturas!J27) <= 0), "", Lecturas!K27-Lecturas!J27) -> 0.621 | U29: =IFERROR(T29*$U$3,"") -> 10.906042 | V29: =IF(OR((Lecturas!L27-Lecturas!K27) < 0), "", Lecturas!L27-Lecturas!K27) -> 0.481 | W29: =IFERROR(V29*$W$3,"") -> 5.8794912 | X29: =IF(OR((Lecturas!M27-Lecturas!L27) < 0), "", Lecturas!M27-Lecturas!L27) -> 0.427 | Y29: =IFERROR(X29*$Y$3,"") -> 5.1813787 | Z29: =IF(OR((Lecturas!N27-Lecturas!M27) <= 0), "", Lecturas!N27-Lecturas!M27) -> 0.635 | AA29: =IFERROR(Z29*$AA$3,"") -> 8.9448143 | AB29: =IF(OR((Lecturas!O27-Lecturas!N27) < 0), "", Lecturas!O27-Lecturas!N27) -> 0.457 | AC29: =IFERROR(AB29*$AC$3,"") -> 5.8710969 | AD29: =IF(OR((Lecturas!P27-Lecturas!O27) < 0), "", Lecturas!P27-Lecturas!O27) -> 0.943 | AE29: =IFERROR(AD29*$AE$3,"") -> 11.86123 | AF29: =IF((Lecturas!Q27-Lecturas!P27)<= 0,"",Lecturas!Q27-Lecturas!P27) -> 1.035 | AG29: =IFERROR(AF29*$AG$3,"") -> 14.746577 | AH29: =IF((Lecturas!R27-Lecturas!Q27)<= 0,"",Lecturas!R27-Lecturas!Q27) -> 1.352 | AI29: =IFERROR(AH29*$AI$3,"") -> 18.811669 | AJ29: =IF((Lecturas!S27-Lecturas!R27)<= 0,"",Lecturas!S27-Lecturas!R27) -> 1.02 | AK29: =IFERROR(AJ29*$AK$3,"") -> 14.695894 | AL29: =IF((Lecturas!T27-Lecturas!S27)<= 0,"",Lecturas!T27-Lecturas!S27) -> 0.682 | AM29: =IFERROR(AL29*$AM$3,"") -> 6.7714576 | AN29: =IF((Lecturas!U27-Lecturas!T27)<= 0,"",Lecturas!U27-Lecturas!T27) -> 0.605 | AO29: =IFERROR(AN29*$AO$3,"") -> 9.8390782 | AP29: =IF((Lecturas!V27-Lecturas!U27)<= 0,"",Lecturas!V27-Lecturas!U27) -> 0.982 | AQ29: =IFERROR(AP29*$AQ$3,"") -> 13.083412 | AR29: =IF((Lecturas!W27-Lecturas!V27)<= 0,"",Lecturas!W27-Lecturas!V27) -> 0.654 | AS29: =IFERROR(AR29*$AS$3,"") -> 7.7282698 | AT29: =IF((Lecturas!X27-Lecturas!W27)<= 0,"",Lecturas!X27-Lecturas!W27) -> 0.76 | AU29: =IFERROR(AT29*$AU$3,"") -> 9.1391465 | AV29: =IF((Lecturas!Y27-Lecturas!X27)<= 0,"",Lecturas!Y27-Lecturas!X27) -> 3.769 | AW29: =IFERROR(AV29*$AW$3,"") -> 46.202108 | AX29: =IF((Lecturas!Z27-Lecturas!Y27)<= 0,"0",Lecturas!Z27-Lecturas!Y27) -> 4.4 | AY29: =IFERROR(AX29*$AY$3,"0") -> 51.057882 | AZ29: =IF((Lecturas!AA27-Lecturas!Z27)<= 0,"0",Lecturas!AA27-Lecturas!Z27) -> 5.955 | BA29: =IFERROR(AZ29*$BA$3,"0") -> 82.203003 | BB29: =IF((Lecturas!AB27-Lecturas!AA27)<= 0,"0",Lecturas!AB27-Lecturas!AA27) -> 5.592 | BC29: =IFERROR(BB29*$BC$3,"0") -> 83.799844 | BD29: =IF((Lecturas!AC27-Lecturas!AB27)<= 0,"0",Lecturas!AC27-Lecturas!AB27) -> 4.192 | BE29: =IFERROR(BD29*$BE$3,"0") -> 90.610154 | BF29: =IF((Lecturas!AD27-Lecturas!AC27)<= 0,"0",Lecturas!AD27-Lecturas!AC27) -> 0 | BG29: =IFERROR(BF29*$BG$3,"0") -> 0 | BH29: =IF((Lecturas!AE27-Lecturas!AD27)<= 0,"0",Lecturas!AE27-Lecturas!AD27) -> 0 | BI29: =IFERROR(BH29*$BI$3,"0") -> 0 | BJ29: =IF((Lecturas!AF27-Lecturas!AE27)<= 0,"0",Lecturas!AF27-Lecturas!AE27) -> 0 | BK29: =IFERROR(BJ29*$BK$3,"0") -> 0 | BL29: =IF((Lecturas!AG27-Lecturas!AF27)<= 0,"0",Lecturas!AG27-Lecturas!AF27) -> 0 | BM29: =IFERROR(BL29*$BM$3,"0") -> 0 | BN29: =IF((Lecturas!AH27-Lecturas!AG27)<= 0,"0",Lecturas!AH27-Lecturas!AG27) -> 0 | BO29: =IFERROR(BN29*$BO$3,"0") -> 0
A30: =ROUND(AG30,1) -> 19.1 | B30: =AF30 -> 1.343 | C30: 601 | D30: LUIGI FERNANDO RONCAGLIOLO | E30: 2034053 | F30: =Lecturas!D28-Lecturas!C28 -> 3.214 | G30: =F30*$G$3 -> 71.78767 | H30: =IF((Lecturas!E28-Lecturas!D28) < 0, "", Lecturas!E28-Lecturas!D28) -> 0.178 | I30: =IFERROR(H30*$I$3,"") -> 3.1800927 | J30: =IF(OR((Lecturas!F28-Lecturas!E28) <= 0), "", Lecturas!F28-Lecturas!E28) -> 1.577 | K30: =IFERROR(J30*$K$3,"") -> 19.177621 | L30: =IF(OR((Lecturas!G28-Lecturas!F28) <= 0), "", Lecturas!G28-Lecturas!F28) -> 0.743 | M30: =IFERROR(L30*$M$3,"") -> 11.598703 | N30: =IF(OR((Lecturas!H28-Lecturas!G28) <= 0), "", Lecturas!H28-Lecturas!G28) -> 0.122 | O30: =IFERROR(N30*$O$3,"") -> 1.853994 | P30: =IF(OR((Lecturas!I28-Lecturas!H28) < 0), "", Lecturas!I28-Lecturas!H28) -> 0 | Q30: =IFERROR(P30*$Q$3,"") -> 0 | R30: =IF(OR((Lecturas!J28-Lecturas!I28) <= 0), "", Lecturas!J28-Lecturas!I28) -> 2.001 | S30: =IFERROR(R30*$S$3,"") -> 33.159627 | T30: =IF(OR((Lecturas!K28-Lecturas!J28) <= 0), "", Lecturas!K28-Lecturas!J28) -> 2.504 | U30: =IFERROR(T30*$U$3,"") -> 43.975408 | V30: =IF(OR((Lecturas!L28-Lecturas!K28) < 0), "", Lecturas!L28-Lecturas!K28) -> 0.766 | W30: =IFERROR(V30*$W$3,"") -> 9.3631814 | X30: =IF(OR((Lecturas!M28-Lecturas!L28) < 0), "", Lecturas!M28-Lecturas!L28) -> 0.089 | Y30: =IFERROR(X30*$Y$3,"") -> 1.0799595 | Z30: =IF(OR((Lecturas!N28-Lecturas!M28) <= 0), "", Lecturas!N28-Lecturas!M28) -> 2.096 | AA30: =IFERROR(Z30*$AA$3,"") -> 29.52493 | AB30: =IF(OR((Lecturas!O28-Lecturas!N28) < 0), "", Lecturas!O28-Lecturas!N28) -> 0 | AC30: =IFERROR(AB30*$AC$3,"") -> 0 | AD30: =IF(OR((Lecturas!P28-Lecturas!O28) < 0), "", Lecturas!P28-Lecturas!O28) -> 0 | AE30: =IFERROR(AD30*$AE$3,"") -> 0 | AF30: =IF((Lecturas!Q28-Lecturas!P28)<= 0,"",Lecturas!Q28-Lecturas!P28) -> 1.343 | AG30: =IFERROR(AF30*$AG$3,"") -> 19.134931 | AH30: =IF((Lecturas!R28-Lecturas!Q28)<= 0,"",Lecturas!R28-Lecturas!Q28) -> 0.783 | AI30: =IFERROR(AH30*$AI$3,"") -> 10.894628 | AJ30: =IF((Lecturas!S28-Lecturas!R28)<= 0,"",Lecturas!S28-Lecturas!R28) -> 0.783 | AK30: =IFERROR(AJ30*$AK$3,"") -> 11.28126 | AL30: =IF((Lecturas!T28-Lecturas!S28)<= 0,"",Lecturas!T28-Lecturas!S28) -> 0.671 | AM30: =IFERROR(AL30*$AM$3,"") -> 6.6622406 | AN30: =IF((Lecturas!U28-Lecturas!T28)<= 0,"",Lecturas!U28-Lecturas!T28) -> 0.002 | AO30: =IFERROR(AN30*$AO$3,"") -> 0.032525878 | AP30: =IF((Lecturas!V28-Lecturas!U28)<= 0,"",Lecturas!V28-Lecturas!U28) -> 1.165 | AQ30: =IFERROR(AP30*$AQ$3,"") -> 15.521563 | AR30: =IF((Lecturas!W28-Lecturas!V28)<= 0,"",Lecturas!W28-Lecturas!V28) -> 0.696 | AS30: =IFERROR(AR30*$AS$3,"") -> 8.2245807 | AT30: =IF((Lecturas!X28-Lecturas!W28)<= 0,"",Lecturas!X28-Lecturas!W28) -> 0.037 | AU30: =IFERROR(AT30*$AU$3,"") -> 0.44493213 | AV30: =IF((Lecturas!Y28-Lecturas!X28)<= 0,"",Lecturas!Y28-Lecturas!X28) -> 3.201 | AW30: =IFERROR(AV30*$AW$3,"") -> 39.239307 | AX30: =IF((Lecturas!Z28-Lecturas!Y28)<= 0,"0",Lecturas!Z28-Lecturas!Y28) -> 0.002 | AY30: =IFERROR(AX30*$AY$3,"0") -> 0.023208128 | AZ30: =IF((Lecturas!AA28-Lecturas!Z28)<= 0,"0",Lecturas!AA28-Lecturas!Z28) -> 0 | BA30: =IFERROR(AZ30*$BA$3,"0") -> 0 | BB30: =IF((Lecturas!AB28-Lecturas!AA28)<= 0,"0",Lecturas!AB28-Lecturas!AA28) -> 3.327 | BC30: =IFERROR(BB30*$BC$3,"0") -> 49.85731 | BD30: =IF((Lecturas!AC28-Lecturas!AB28)<= 0,"0",Lecturas!AC28-Lecturas!AB28) -> 0.186 | BE30: =IFERROR(BD30*$BE$3,"0") -> 4.0203933 | BF30: =IF((Lecturas!AD28-Lecturas!AC28)<= 0,"0",Lecturas!AD28-Lecturas!AC28) -> 0 | BG30: =IFERROR(BF30*$BG$3,"0") -> 0 | BH30: =IF((Lecturas!AE28-Lecturas!AD28)<= 0,"0",Lecturas!AE28-Lecturas!AD28) -> 0 | BI30: =IFERROR(BH30*$BI$3,"0") -> 0 | BJ30: =IF((Lecturas!AF28-Lecturas!AE28)<= 0,"0",Lecturas!AF28-Lecturas!AE28) -> 0 | BK30: =IFERROR(BJ30*$BK$3,"0") -> 0 | BL30: =IF((Lecturas!AG28-Lecturas!AF28)<= 0,"0",Lecturas!AG28-Lecturas!AF28) -> 0 | BM30: =IFERROR(BL30*$BM$3,"0") -> 0 | BN30: =IF((Lecturas!AH28-Lecturas!AG28)<= 0,"0",Lecturas!AH28-Lecturas!AG28) -> 0 | BO30: =IFERROR(BN30*$BO$3,"0") -> 0
A31: =ROUND(AG31,1) -> 114.8 | B31: =AF31 -> 8.059 | C31: 602 | D31: POTERICO ROJAS JULIO ANTONIO | E31: GA202101900062 | F31: =Lecturas!D29-Lecturas!C29 -> 4.844 | G31: =F31*$G$3 -> 108.19523 | H31: =IF((Lecturas!E29-Lecturas!D29) < 0, "", Lecturas!E29-Lecturas!D29) -> 5.45 | I31: =IFERROR(H31*$I$3,"") -> 97.368008 | J31: =IF(OR((Lecturas!F29-Lecturas!E29) <= 0), "", Lecturas!F29-Lecturas!E29) -> 5.963 | K31: =IFERROR(J31*$K$3,"") -> 72.514999 | L31: =IF(OR((Lecturas!G29-Lecturas!F29) <= 0), "", Lecturas!G29-Lecturas!F29) -> 4.706 | M31: =IFERROR(L31*$M$3,"") -> 73.463656 | N31: =IF(OR((Lecturas!H29-Lecturas!G29) <= 0), "", Lecturas!H29-Lecturas!G29) -> 5.168 | O31: =IFERROR(N31*$O$3,"") -> 78.536402 | P31: =IF(OR((Lecturas!I29-Lecturas!H29) <= 0), "", Lecturas!I29-Lecturas!H29) -> 7.428 | Q31: =IFERROR(P31*$Q$3,"") -> 110.23855 | R31: =IF(OR((Lecturas!J29-Lecturas!I29) <= 0), "", Lecturas!J29-Lecturas!I29) -> 7.481 | S31: =IFERROR(R31*$S$3,"") -> 123.9716 | T31: =IF(OR((Lecturas!K29-Lecturas!J29) <= 0), "", Lecturas!K29-Lecturas!J29) -> 6.233 | U31: =IFERROR(T31*$U$3,"") -> 109.46434 | V31: =IF(OR((Lecturas!L29-Lecturas!K29) < 0), "", Lecturas!L29-Lecturas!K29) -> 7.823 | W31: =IFERROR(V31*$W$3,"") -> 95.62424 | X31: =IF(OR((Lecturas!M29-Lecturas!L29) < 0), "", Lecturas!M29-Lecturas!L29) -> 7.831 | Y31: =IFERROR(X31*$Y$3,"") -> 95.024301 | Z31: =IF(OR((Lecturas!N29-Lecturas!M29) <= 0), "", Lecturas!N29-Lecturas!M29) -> 7.608 | AA31: =IFERROR(Z31*$AA$3,"") -> 107.16874 | AB31: =IF(OR((Lecturas!O29-Lecturas!N29) < 0), "", Lecturas!O29-Lecturas!N29) -> 7.463 | AC31: =IFERROR(AB31*$AC$3,"") -> 95.877453 | AD31: =IF(OR((Lecturas!P29-Lecturas!O29) < 0), "", Lecturas!P29-Lecturas!O29) -> 7.219 | AE31: =IFERROR(AD31*$AE$3,"") -> 90.801928 | AF31: =IF((Lecturas!Q29-Lecturas!P29)<= 0,"",Lecturas!Q29-Lecturas!P29) -> 8.059 | AG31: =IFERROR(AF31*$AG$3,"") -> 114.82383 | AH31: =IF((Lecturas!R29-Lecturas!Q29)<= 0,"",Lecturas!R29-Lecturas!Q29) -> 8.232 | AI31: =IFERROR(AH31*$AI$3,"") -> 114.53969 | AJ31: =IF((Lecturas!S29-Lecturas!R29)<= 0,"",Lecturas!S29-Lecturas!R29) -> 8.018 | AK31: =IFERROR(AJ31*$AK$3,"") -> 115.52125 | AL31: =IF((Lecturas!T29-Lecturas!S29)<= 0,"",Lecturas!T29-Lecturas!S29) -> 9.605 | AM31: =IFERROR(AL31*$AM$3,"") -> 95.36635 | AN31: =IF((Lecturas!U29-Lecturas!T29)<= 0,"",Lecturas!U29-Lecturas!T29) -> 6.139 | AO31: =IFERROR(AN31*$AO$3,"") -> 99.838184 | AP31: =IF((Lecturas!V29-Lecturas!U29)<= 0,"",Lecturas!V29-Lecturas!U29) -> 7.095 | AQ31: =IFERROR(AP31*$AQ$3,"") -> 94.528316 | AR31: =IF((Lecturas!W29-Lecturas!V29)<= 0,"",Lecturas!W29-Lecturas!V29) -> 5.601 | AS31: =IFERROR(AR31*$AS$3,"") -> 66.186604 | AT31: =IF((Lecturas!X29-Lecturas!W29)<= 0,"",Lecturas!X29-Lecturas!W29) -> 6.434 | AU31: =IFERROR(AT31*$AU$3,"") -> 77.37009 | AV31: =IF((Lecturas!Y29-Lecturas!X29)<= 0,"",Lecturas!Y29-Lecturas!X29) -> 6.847 | AW31: =IFERROR(AV31*$AW$3,"") -> 83.933626 | AX31: =IF((Lecturas!Z29-Lecturas!Y29)<= 0,"0",Lecturas!Z29-Lecturas!Y29) -> 7.078 | AY31: =IFERROR(AX31*$AY$3,"0") -> 82.133565 | AZ31: =IF((Lecturas!AA29-Lecturas!Z29)<= 0,"0",Lecturas!AA29-Lecturas!Z29) -> 7.544 | BA31: =IFERROR(AZ31*$BA$3,"0") -> 104.13761 | BB31: =IF((Lecturas!AB29-Lecturas!AA29)<= 0,"0",Lecturas!AB29-Lecturas!AA29) -> 6.349 | BC31: =IFERROR(BB31*$BC$3,"0") -> 95.143993 | BD31: =IF((Lecturas!AC29-Lecturas!AB29)<= 0,"0",Lecturas!AC29-Lecturas!AB29) -> 7.019 | BE31: =IFERROR(BD31*$BE$3,"0") -> 151.71581 | BF31: =IF((Lecturas!AD29-Lecturas!AC29)<= 0,"0",Lecturas!AD29-Lecturas!AC29) -> 0 | BG31: =IFERROR(BF31*$BG$3,"0") -> 0 | BH31: =IF((Lecturas!AE29-Lecturas!AD29)<= 0,"0",Lecturas!AE29-Lecturas!AD29) -> 0 | BI31: =IFERROR(BH31*$BI$3,"0") -> 0 | BJ31: =IF((Lecturas!AF29-Lecturas!AE29)<= 0,"0",Lecturas!AF29-Lecturas!AE29) -> 0 | BK31: =IFERROR(BJ31*$BK$3,"0") -> 0 | BL31: =IF((Lecturas!AG29-Lecturas!AF29)<= 0,"0",Lecturas!AG29-Lecturas!AF29) -> 0 | BM31: =IFERROR(BL31*$BM$3,"0") -> 0 | BN31: =IF((Lecturas!AH29-Lecturas!AG29)<= 0,"0",Lecturas!AH29-Lecturas!AG29) -> 0 | BO31: =IFERROR(BN31*$BO$3,"0") -> 0
A32: =ROUND(AG32,1) -> 141.8 | B32: =AF32 -> 9.955 | C32: 603 | D32: GRACIELA ORTIZ | E32: 2034072 | F32: =Lecturas!D30-Lecturas!C30 -> 11.216 | G32: =F32*$G$3 -> 250.51976 | H32: =IF((Lecturas!E30-Lecturas!D30) < 0, "", Lecturas!E30-Lecturas!D30) -> 11.519 | I32: =IFERROR(H32*$I$3,"") -> 205.79488 | J32: =IF(OR((Lecturas!F30-Lecturas!E30) <= 0), "", Lecturas!F30-Lecturas!E30) -> 9.558 | K32: =IFERROR(J32*$K$3,"") -> 116.23316 | L32: =IF(OR((Lecturas!G30-Lecturas!F30) <= 0), "", Lecturas!G30-Lecturas!F30) -> 7.873 | M32: =IFERROR(L32*$M$3,"") -> 122.90254 | N32: =IF(OR((Lecturas!H30-Lecturas!G30) <= 0), "", Lecturas!H30-Lecturas!G30) -> 7.237 | O32: =IFERROR(N32*$O$3,"") -> 109.97832 | P32: =IF(OR((Lecturas!I30-Lecturas!H30) <= 0), "", Lecturas!I30-Lecturas!H30) -> 11.3 | Q32: =IFERROR(P32*$Q$3,"") -> 167.7027 | R32: =IF(OR((Lecturas!J30-Lecturas!I30) <= 0), "", Lecturas!J30-Lecturas!I30) -> 10.737 | S32: =IFERROR(R32*$S$3,"") -> 177.92849 | T32: =IF(OR((Lecturas!K30-Lecturas!J30) <= 0), "", Lecturas!K30-Lecturas!J30) -> 6.958 | U32: =IFERROR(T32*$U$3,"") -> 122.19684 | V32: =IF(OR((Lecturas!L30-Lecturas!K30) < 0), "", Lecturas!L30-Lecturas!K30) -> 7.611 | W32: =IFERROR(V32*$W$3,"") -> 93.032864 | X32: =IF(OR((Lecturas!M30-Lecturas!L30) < 0), "", Lecturas!M30-Lecturas!L30) -> 8.413 | Y32: =IFERROR(X32*$Y$3,"") -> 102.08651 | Z32: =IF(OR((Lecturas!N30-Lecturas!M30) <= 0), "", Lecturas!N30-Lecturas!M30) -> 8.754 | AA32: =IFERROR(Z32*$AA$3,"") -> 123.31166 | AB32: =IF(OR((Lecturas!O30-Lecturas!N30) < 0), "", Lecturas!O30-Lecturas!N30) -> 9.297 | AC32: =IFERROR(AB32*$AC$3,"") -> 119.43892 | AD32: =IF(OR((Lecturas!P30-Lecturas!O30) < 0), "", Lecturas!P30-Lecturas!O30) -> 9.349 | AE32: =IFERROR(AD32*$AE$3,"") -> 117.59346 | AF32: =IF((Lecturas!Q30-Lecturas!P30)<= 0,"",Lecturas!Q30-Lecturas!P30) -> 9.955 | AG32: =IFERROR(AF32*$AG$3,"") -> 141.83785 | AH32: =IF((Lecturas!R30-Lecturas!Q30)<= 0,"",Lecturas!R30-Lecturas!Q30) -> 10.424 | AI32: =IFERROR(AH32*$AI$3,"") -> 145.03908 | AJ32: =IF((Lecturas!S30-Lecturas!R30)<= 0,"",Lecturas!S30-Lecturas!R30) -> 10.204 | AK32: =IFERROR(AJ32*$AK$3,"") -> 147.01657 | AL32: =IF((Lecturas!T30-Lecturas!S30)<= 0,"",Lecturas!T30-Lecturas!S30) -> 11.83 | AM32: =IFERROR(AL32*$AM$3,"") -> 117.45798 | AN32: =IF((Lecturas!U30-Lecturas!T30)<= 0,"",Lecturas!U30-Lecturas!T30) -> 9.243 | AO32: =IFERROR(AN32*$AO$3,"") -> 150.31835 | AP32: =IF((Lecturas!V30-Lecturas!U30)<= 0,"",Lecturas!V30-Lecturas!U30) -> 7.956 | AQ32: =IFERROR(AP32*$AQ$3,"") -> 105.99962 | AR32: =IF((Lecturas!W30-Lecturas!V30)<= 0,"",Lecturas!W30-Lecturas!V30) -> 12.21 | AS32: =IFERROR(AR32*$AS$3,"") -> 144.28467 | AT32: =IF((Lecturas!X30-Lecturas!W30)<= 0,"",Lecturas!X30-Lecturas!W30) -> 7.287 | AU32: =IFERROR(AT32*$AU$3,"") -> 87.62758 | AV32: =IF((Lecturas!Y30-Lecturas!X30)<= 0,"",Lecturas!Y30-Lecturas!X30) -> 7.766 | AW32: =IFERROR(AV32*$AW$3,"") -> 95.199144 | AX32: =IF((Lecturas!Z30-Lecturas!Y30)<= 0,"0",Lecturas!Z30-Lecturas!Y30) -> 7.704 | AY32: =IFERROR(AX32*$AY$3,"0") -> 89.39771 | AZ32: =IF((Lecturas!AA30-Lecturas!Z30)<= 0,"0",Lecturas!AA30-Lecturas!Z30) -> 9.14 | BA32: =IFERROR(AZ32*$BA$3,"0") -> 126.16884 | BB32: =IF((Lecturas!AB30-Lecturas!AA30)<= 0,"0",Lecturas!AB30-Lecturas!AA30) -> 9.292 | BC32: =IFERROR(BB32*$BC$3,"0") -> 139.24681 | BD32: =IF((Lecturas!AC30-Lecturas!AB30)<= 0,"0",Lecturas!AC30-Lecturas!AB30) -> 9.457 | BE32: =IFERROR(BD32*$BE$3,"0") -> 204.41322 | BF32: =IF((Lecturas!AD30-Lecturas!AC30)<= 0,"0",Lecturas!AD30-Lecturas!AC30) -> 0 | BG32: =IFERROR(BF32*$BG$3,"0") -> 0 | BH32: =IF((Lecturas!AE30-Lecturas!AD30)<= 0,"0",Lecturas!AE30-Lecturas!AD30) -> 0 | BI32: =IFERROR(BH32*$BI$3,"0") -> 0 | BJ32: =IF((Lecturas!AF30-Lecturas!AE30)<= 0,"0",Lecturas!AF30-Lecturas!AE30) -> 0 | BK32: =IFERROR(BJ32*$BK$3,"0") -> 0 | BL32: =IF((Lecturas!AG30-Lecturas!AF30)<= 0,"0",Lecturas!AG30-Lecturas!AF30) -> 0 | BM32: =IFERROR(BL32*$BM$3,"0") -> 0 | BN32: =IF((Lecturas!AH30-Lecturas!AG30)<= 0,"0",Lecturas!AH30-Lecturas!AG30) -> 0 | BO32: =IFERROR(BN32*$BO$3,"0") -> 0
A33: =ROUND(AG33,1) -> 35.7 | B33: =AF33 -> 2.504 | C33: 604 | D33: RAFAEL BRISSOLESE D ANGELO | E33: 2034041 | F33: =Lecturas!D31-Lecturas!C31 -> 1.681 | G33: =F33*$G$3 -> 37.546694 | H33: =IF((Lecturas!E31-Lecturas!D31) < 0, "", Lecturas!E31-Lecturas!D31) -> 1.752 | I33: =IFERROR(H33*$I$3,"") -> 31.300688 | J33: =IF(OR((Lecturas!F31-Lecturas!E31) <= 0), "", Lecturas!F31-Lecturas!E31) -> 1.616 | K33: =IFERROR(J33*$K$3,"") -> 19.651893 | L33: =IF(OR((Lecturas!G31-Lecturas!F31) <= 0), "", Lecturas!G31-Lecturas!F31) -> 1.706 | M33: =IFERROR(L33*$M$3,"") -> 26.631746 | N33: =IF(OR((Lecturas!H31-Lecturas!G31) <= 0), "", Lecturas!H31-Lecturas!G31) -> 1.407 | O33: =IFERROR(N33*$O$3,"") -> 21.381718 | P33: =IF(OR((Lecturas!I31-Lecturas!H31) <= 0), "", Lecturas!I31-Lecturas!H31) -> 1.461 | Q33: =IFERROR(P33*$Q$3,"") -> 21.682623 | R33: =IF(OR((Lecturas!J31-Lecturas!I31) <= 0), "", Lecturas!J31-Lecturas!I31) -> 1.525 | S33: =IFERROR(R33*$S$3,"") -> 25.27158 | T33: =IF(OR((Lecturas!K31-Lecturas!J31) <= 0), "", Lecturas!K31-Lecturas!J31) -> 1.086 | U33: =IFERROR(T33*$U$3,"") -> 19.072401 | V33: =IF(OR((Lecturas!L31-Lecturas!K31) < 0), "", Lecturas!L31-Lecturas!K31) -> 0.984 | W33: =IFERROR(V33*$W$3,"") -> 12.027899 | X33: =IF(OR((Lecturas!M31-Lecturas!L31) < 0), "", Lecturas!M31-Lecturas!L31) -> 1.108 | Y33: =IFERROR(X33*$Y$3,"") -> 13.444889 | Z33: =IF(OR((Lecturas!N31-Lecturas!M31) <= 0), "", Lecturas!N31-Lecturas!M31) -> 1.175 | AA33: =IFERROR(Z33*$AA$3,"") -> 16.551428 | AB33: =IF(OR((Lecturas!O31-Lecturas!N31) < 0), "", Lecturas!O31-Lecturas!N31) -> 2.273 | AC33: =IFERROR(AB33*$AC$3,"") -> 29.20132 | AD33: =IF(OR((Lecturas!P31-Lecturas!O31) < 0), "", Lecturas!P31-Lecturas!O31) -> 1.839 | AE33: =IFERROR(AD33*$AE$3,"") -> 23.131285 | AF33: =IF((Lecturas!Q31-Lecturas!P31)<= 0,"",Lecturas!Q31-Lecturas!P31) -> 2.504 | AG33: =IFERROR(AF33*$AG$3,"") -> 35.676744 | AH33: =IF((Lecturas!R31-Lecturas!Q31)<= 0,"",Lecturas!R31-Lecturas!Q31) -> 2.842 | AI33: =IFERROR(AH33*$AI$3,"") -> 39.543465 | AJ33: =IF((Lecturas!S31-Lecturas!R31)<= 0,"",Lecturas!S31-Lecturas!R31) -> 0.803 | AK33: =IFERROR(AJ33*$AK$3,"") -> 11.569414 | AL33: =IF((Lecturas!T31-Lecturas!S31)<= 0,"",Lecturas!T31-Lecturas!S31) -> 2.979 | AM33: =IFERROR(AL33*$AM$3,"") -> 29.577965 | AN33: =IF((Lecturas!U31-Lecturas!T31)<= 0,"",Lecturas!U31-Lecturas!T31) -> 2.145 | AO33: =IFERROR(AN33*$AO$3,"") -> 34.884005 | AP33: =IF((Lecturas!V31-Lecturas!U31)<= 0,"",Lecturas!V31-Lecturas!U31) -> 1.881 | AQ33: =IFERROR(AP33*$AQ$3,"") -> 25.060995 | AR33: =IF((Lecturas!W31-Lecturas!V31)<= 0,"",Lecturas!W31-Lecturas!V31) -> 1.059 | AS33: =IFERROR(AR33*$AS$3,"") -> 12.514125 | AT33: =IF((Lecturas!X31-Lecturas!W31)<= 0,"",Lecturas!X31-Lecturas!W31) -> 1.165 | AU33: =IFERROR(AT33*$AU$3,"") -> 14.00935 | AV33: =IF((Lecturas!Y31-Lecturas!X31)<= 0,"",Lecturas!Y31-Lecturas!X31) -> 1.817 | AW33: =IFERROR(AV33*$AW$3,"") -> 22.273609 | AX33: =IF((Lecturas!Z31-Lecturas!Y31)<= 0,"0",Lecturas!Z31-Lecturas!Y31) -> 1.548 | AY33: =IFERROR(AX33*$AY$3,"0") -> 17.963091 | AZ33: =IF((Lecturas!AA31-Lecturas!Z31)<= 0,"0",Lecturas!AA31-Lecturas!Z31) -> 1.597 | BA33: =IFERROR(AZ33*$BA$3,"0") -> 22.045037 | BB33: =IF((Lecturas!AB31-Lecturas!AA31)<= 0,"0",Lecturas!AB31-Lecturas!AA31) -> 1.567 | BC33: =IFERROR(BB33*$BC$3,"0") -> 23.482538 | BD33: =IF((Lecturas!AC31-Lecturas!AB31)<= 0,"0",Lecturas!AC31-Lecturas!AB31) -> 1.648 | BE33: =IFERROR(BD33*$BE$3,"0") -> 35.621549 | BF33: =IF((Lecturas!AD31-Lecturas!AC31)<= 0,"0",Lecturas!AD31-Lecturas!AC31) -> 0 | BG33: =IFERROR(BF33*$BG$3,"0") -> 0 | BH33: =IF((Lecturas!AE31-Lecturas!AD31)<= 0,"0",Lecturas!AE31-Lecturas!AD31) -> 0 | BI33: =IFERROR(BH33*$BI$3,"0") -> 0 | BJ33: =IF((Lecturas!AF31-Lecturas!AE31)<= 0,"0",Lecturas!AF31-Lecturas!AE31) -> 0 | BK33: =IFERROR(BJ33*$BK$3,"0") -> 0 | BL33: =IF((Lecturas!AG31-Lecturas!AF31)<= 0,"0",Lecturas!AG31-Lecturas!AF31) -> 0 | BM33: =IFERROR(BL33*$BM$3,"0") -> 0 | BN33: =IF((Lecturas!AH31-Lecturas!AG31)<= 0,"0",Lecturas!AH31-Lecturas!AG31) -> 0 | BO33: =IFERROR(BN33*$BO$3,"0") -> 0
A34: =ROUND(AG34,1) -> 0 | B34: =AF34 -> 0 | C34: 605 | D34: JOHN MARTIN LLERENA SALAS | E34: 2034051 | F34: =Lecturas!D32-Lecturas!C32 -> 1.816 | G34: =F34*$G$3 -> 40.562044 | H34: =IF((Lecturas!E32-Lecturas!D32) < 0, "", Lecturas!E32-Lecturas!D32) -> 0.918 | I34: =IFERROR(H34*$I$3,"") -> 16.400703 | J34: =IF(OR((Lecturas!F32-Lecturas!E32) < 0), "", Lecturas!F32-Lecturas!E32) -> 0 | K34: =IFERROR(J34*$K$3,"") -> 0 | L34: =IF(OR((Lecturas!G32-Lecturas!F32) < 0), "", Lecturas!G32-Lecturas!F32) -> 0 | M34: =IFERROR(L34*$M$3,"") -> 0 | N34: =IF(OR((Lecturas!H32-Lecturas!G32) < 0), "", Lecturas!H32-Lecturas!G32) -> 0 | O34: =IFERROR(N34*$O$3,"") -> 0 | P34: =IF(OR((Lecturas!I32-Lecturas!H32) < 0), "", Lecturas!I32-Lecturas!H32) -> 0 | Q34: =IFERROR(P34*$Q$3,"") -> 0 | R34: =IF(OR((Lecturas!J32-Lecturas!I32) < 0), "", Lecturas!J32-Lecturas!I32) -> 0 | S34: =IFERROR(R34*$S$3,"") -> 0 | T34: =IF(OR((Lecturas!K32-Lecturas!J32) < 0), "", Lecturas!K32-Lecturas!J32) -> 0 | U34: =IFERROR(T34*$U$3,"") -> 0 | V34: =IF(OR((Lecturas!L32-Lecturas!K32) < 0), "", Lecturas!L32-Lecturas!K32) -> 0 | W34: =IFERROR(V34*$W$3,"") -> 0 | X34: =IF(OR((Lecturas!M32-Lecturas!L32) < 0), "", Lecturas!M32-Lecturas!L32) -> 0 | Y34: =IFERROR(X34*$Y$3,"") -> 0 | Z34: =IF(OR((Lecturas!N32-Lecturas!M32) < 0), "", Lecturas!N32-Lecturas!M32) -> 0 | AA34: =IFERROR(Z34*$AA$3,"") -> 0 | AB34: =IF(OR((Lecturas!O32-Lecturas!N32) < 0), "", Lecturas!O32-Lecturas!N32) -> 0 | AC34: =IFERROR(AB34*$AC$3,"") -> 0 | AD34: =IF(OR((Lecturas!P32-Lecturas!O32) < 0), "", Lecturas!P32-Lecturas!O32) -> 0 | AE34: =IFERROR(AD34*$AE$3,"") -> 0 | AF34: =IF((Lecturas!Q32-Lecturas!P32)< 0,"",Lecturas!Q32-Lecturas!P32) -> 0 | AG34: =IFERROR(AF34*$AG$3,"") -> 0 | AH34: 0 | AI34: =IFERROR(AH34*$AI$3,"") -> 0 | AJ34: 0 | AK34: =IFERROR(AJ34*$AK$3,"") -> 0 | AL34: 0 | AM34: =IFERROR(AL34*$AM$3,"") -> 0 | AN34: =IF((Lecturas!U32-Lecturas!T32)<= 0,"",Lecturas!U32-Lecturas!T32) | AO34: =IFERROR(AN34*$AO$3,"") -> 0 | AP34: =IF((Lecturas!V32-Lecturas!U32)<= 0,"",Lecturas!V32-Lecturas!U32) | AQ34: =IFERROR(AP34*$AQ$3,"") -> 0 | AR34: =IF((Lecturas!W32-Lecturas!V32)<= 0,"",Lecturas!W32-Lecturas!V32) | AS34: =IFERROR(AR34*$AS$3,"") -> 0 | AT34: =IF((Lecturas!X32-Lecturas!W32)<= 0,"",Lecturas!X32-Lecturas!W32) | AU34: =IFERROR(AT34*$AU$3,"") -> 0 | AV34: =IF((Lecturas!Y32-Lecturas!X32)<= 0,"",Lecturas!Y32-Lecturas!X32) | AW34: =IFERROR(AV34*$AW$3,"") -> 0 | AX34: =IF((Lecturas!Z32-Lecturas!Y32)<= 0,"0",Lecturas!Z32-Lecturas!Y32) -> 0 | AY34: =IFERROR(AX34*$AY$3,"0") -> 0 | AZ34: =IF((Lecturas!AA32-Lecturas!Z32)<= 0,"0",Lecturas!AA32-Lecturas!Z32) -> 0 | BA34: =IFERROR(AZ34*$BA$3,"0") -> 0 | BB34: =IF((Lecturas!AB32-Lecturas!AA32)<= 0,"0",Lecturas!AB32-Lecturas!AA32) -> 0 | BC34: =IFERROR(BB34*$BC$3,"0") -> 0 | BD34: =IF((Lecturas!AC32-Lecturas!AB32)<= 0,"0",Lecturas!AC32-Lecturas!AB32) -> 0 | BE34: =IFERROR(BD34*$BE$3,"0") -> 0 | BF34: =IF((Lecturas!AD32-Lecturas!AC32)<= 0,"0",Lecturas!AD32-Lecturas!AC32) -> 0 | BG34: =IFERROR(BF34*$BG$3,"0") -> 0 | BH34: =IF((Lecturas!AE32-Lecturas!AD32)<= 0,"0",Lecturas!AE32-Lecturas!AD32) -> 0 | BI34: =IFERROR(BH34*$BI$3,"0") -> 0 | BJ34: =IF((Lecturas!AF32-Lecturas!AE32)<= 0,"0",Lecturas!AF32-Lecturas!AE32) -> 0 | BK34: =IFERROR(BJ34*$BK$3,"0") -> 0 | BL34: =IF((Lecturas!AG32-Lecturas!AF32)<= 0,"0",Lecturas!AG32-Lecturas!AF32) -> 0 | BM34: =IFERROR(BL34*$BM$3,"0") -> 0 | BN34: =IF((Lecturas!AH32-Lecturas!AG32)<= 0,"0",Lecturas!AH32-Lecturas!AG32) -> 0 | BO34: =IFERROR(BN34*$BO$3,"0") -> 0
A35: =ROUND(AG35,1) -> 21.1 | B35: =AF35 -> 1.482 | C35: 702 | D35: LUIGI SCARIN | E35: 2034075 | F35: =Lecturas!D33-Lecturas!C33 -> 1.613 | G35: =F35*$G$3 -> 36.027851 | H35: =IF((Lecturas!E33-Lecturas!D33) < 0, "", Lecturas!E33-Lecturas!D33) -> 1.081 | I35: =IFERROR(H35*$I$3,"") -> 19.31281 | J35: =IF(OR((Lecturas!F33-Lecturas!E33) <= 0), "", Lecturas!F33-Lecturas!E33) -> 1.201 | K35: =IFERROR(J35*$K$3,"") -> 14.605151 | L35: =IF(OR((Lecturas!G33-Lecturas!F33) <= 0), "", Lecturas!G33-Lecturas!F33) -> 0.891 | M35: =IFERROR(L35*$M$3,"") -> 13.909077 | N35: =IF(OR((Lecturas!H33-Lecturas!G33) <= 0), "", Lecturas!H33-Lecturas!G33) -> 1.29 | O35: =IFERROR(N35*$O$3,"") -> 19.603707 | P35: =IF(OR((Lecturas!I33-Lecturas!H33) <= 0), "", Lecturas!I33-Lecturas!H33) -> 1.305 | Q35: =IFERROR(P35*$Q$3,"") -> 19.367436 | R35: =IF(OR((Lecturas!J33-Lecturas!I33) <= 0), "", Lecturas!J33-Lecturas!I33) -> 1.299 | S35: =IFERROR(R35*$S$3,"") -> 21.526414 | T35: =IF(OR((Lecturas!K33-Lecturas!J33) <= 0), "", Lecturas!K33-Lecturas!J33) -> 0.842 | U35: =IFERROR(T35*$U$3,"") -> 14.787258 | V35: =IF(OR((Lecturas!L33-Lecturas!K33) < 0), "", Lecturas!L33-Lecturas!K33) -> 1.386 | W35: =IFERROR(V35*$W$3,"") -> 16.941736 | X35: =IF(OR((Lecturas!M33-Lecturas!L33) < 0), "", Lecturas!M33-Lecturas!L33) -> 1.248 | Y35: =IFERROR(X35*$Y$3,"") -> 15.143702 | Z35: =IF(OR((Lecturas!N33-Lecturas!M33) <= 0), "", Lecturas!N33-Lecturas!M33) -> 1.112 | AA35: =IFERROR(Z35*$AA$3,"") -> 15.66399 | AB35: =IF(OR((Lecturas!O33-Lecturas!N33) < 0), "", Lecturas!O33-Lecturas!N33) -> 1.413 | AC35: =IFERROR(AB35*$AC$3,"") -> 18.152866 | AD35: =IF(OR((Lecturas!P33-Lecturas!O33) < 0), "", Lecturas!P33-Lecturas!O33) -> 1.355 | AE35: =IFERROR(AD35*$AE$3,"") -> 17.043443 | AF35: =IF((Lecturas!Q33-Lecturas!P33)<= 0,"",Lecturas!Q33-Lecturas!P33) -> 1.482 | AG35: =IFERROR(AF35*$AG$3,"") -> 21.115389 | AH35: =IF((Lecturas!R33-Lecturas!Q33)<= 0,"",Lecturas!R33-Lecturas!Q33) -> 1.269 | AI35: =IFERROR(AH35*$AI$3,"") -> 17.656811 | AJ35: =IF((Lecturas!S33-Lecturas!R33)<= 0,"",Lecturas!S33-Lecturas!R33) -> 0.902 | AK35: =IFERROR(AJ35*$AK$3,"") -> 12.995781 | AL35: =IF((Lecturas!T33-Lecturas!S33)<= 0,"",Lecturas!T33-Lecturas!S33) -> 1.512 | AM35: =IFERROR(AL35*$AM$3,"") -> 15.012381 | AN35: =IF((Lecturas!U33-Lecturas!T33)<= 0,"",Lecturas!U33-Lecturas!T33) -> 0.964 | AO35: =IFERROR(AN35*$AO$3,"") -> 15.677473 | AP35: =IF((Lecturas!V33-Lecturas!U33)<= 0,"",Lecturas!V33-Lecturas!U33) -> 1.084 | AQ35: =IFERROR(AP35*$AQ$3,"") -> 14.442381 | AR35: =IF((Lecturas!W33-Lecturas!V33)<= 0,"",Lecturas!W33-Lecturas!V33) -> 0.917 | AS35: =IFERROR(AR35*$AS$3,"") -> 10.836121 | AT35: =IF((Lecturas!X33-Lecturas!W33)<= 0,"",Lecturas!X33-Lecturas!W33) -> 1.03 | AU35: =IFERROR(AT35*$AU$3,"") -> 12.385949 | AV35: =IF((Lecturas!Y33-Lecturas!X33)<= 0,"",Lecturas!Y33-Lecturas!X33) -> 1.138 | AW35: =IFERROR(AV35*$AW$3,"") -> 13.950119 | AX35: =IF((Lecturas!Z33-Lecturas!Y33)<= 0,"0",Lecturas!Z33-Lecturas!Y33) -> 0.858 | AY35: =IFERROR(AX35*$AY$3,"0") -> 9.956287 | AZ35: =IF((Lecturas!AA33-Lecturas!Z33)<= 0,"0",Lecturas!AA33-Lecturas!Z33) -> 1.097 | BA35: =IFERROR(AZ35*$BA$3,"0") -> 15.143022 | BB35: =IF((Lecturas!AB33-Lecturas!AA33)<= 0,"0",Lecturas!AB33-Lecturas!AA33) -> 1.055 | BC35: =IFERROR(BB35*$BC$3,"0") -> 15.809878 | BD35: =IF((Lecturas!AC33-Lecturas!AB33)<= 0,"0",Lecturas!AC33-Lecturas!AB33) -> 1.295 | BE35: =IFERROR(BD35*$BE$3,"0") -> 27.991448 | BF35: =IF((Lecturas!AD33-Lecturas!AC33)<= 0,"0",Lecturas!AD33-Lecturas!AC33) -> 0 | BG35: =IFERROR(BF35*$BG$3,"0") -> 0 | BH35: =IF((Lecturas!AE33-Lecturas!AD33)<= 0,"0",Lecturas!AE33-Lecturas!AD33) -> 0 | BI35: =IFERROR(BH35*$BI$3,"0") -> 0 | BJ35: =IF((Lecturas!AF33-Lecturas!AE33)<= 0,"0",Lecturas!AF33-Lecturas!AE33) -> 0 | BK35: =IFERROR(BJ35*$BK$3,"0") -> 0 | BL35: =IF((Lecturas!AG33-Lecturas!AF33)<= 0,"0",Lecturas!AG33-Lecturas!AF33) -> 0 | BM35: =IFERROR(BL35*$BM$3,"0") -> 0 | BN35: =IF((Lecturas!AH33-Lecturas!AG33)<= 0,"0",Lecturas!AH33-Lecturas!AG33) -> 0 | BO35: =IFERROR(BN35*$BO$3,"0") -> 0
A36: =ROUND(AG36,1) -> 3.9 | B36: =AF36 -> 0.272 | C36: 703 | D36: RAMON FRANCISCO LABRIN FARIAS | E36: 2034079 | F36: =Lecturas!D34-Lecturas!C34 -> 0.298 | G36: =F36*$G$3 -> 6.6561063 | H36: =IF((Lecturas!E34-Lecturas!D34) < 0, "", Lecturas!E34-Lecturas!D34) -> 0.351 | I36: =IFERROR(H36*$I$3,"") -> 6.270857 | J36: =IF(OR((Lecturas!F34-Lecturas!E34) <= 0), "", Lecturas!F34-Lecturas!E34) -> 0.563 | K36: =IFERROR(J36*$K$3,"") -> 6.8465445 | L36: =IF(OR((Lecturas!G34-Lecturas!F34) <= 0), "", Lecturas!G34-Lecturas!F34) -> 0.506 | M36: =IFERROR(L36*$M$3,"") -> 7.8989821 | N36: =IF(OR((Lecturas!H34-Lecturas!G34) <= 0), "", Lecturas!H34-Lecturas!G34) -> 0.705 | O36: =IFERROR(N36*$O$3,"") -> 10.713654 | P36: =IF(OR((Lecturas!I34-Lecturas!H34) <= 0), "", Lecturas!I34-Lecturas!H34) -> 0.875 | Q36: =IFERROR(P36*$Q$3,"") -> 12.985829 | R36: =IF(OR((Lecturas!J34-Lecturas!I34) <= 0), "", Lecturas!J34-Lecturas!I34) -> 1.289 | S36: =IFERROR(R36*$S$3,"") -> 21.360699 | T36: =IF(OR((Lecturas!K34-Lecturas!J34) <= 0), "", Lecturas!K34-Lecturas!J34) -> 1.003 | U36: =IFERROR(T36*$U$3,"") -> 17.61475 | V36: =IF(OR((Lecturas!L34-Lecturas!K34) < 0), "", Lecturas!L34-Lecturas!K34) -> 0.808 | W36: =IFERROR(V36*$W$3,"") -> 9.8765673 | X36: =IF(OR((Lecturas!M34-Lecturas!L34) < 0), "", Lecturas!M34-Lecturas!L34) -> 0.403 | Y36: =IFERROR(X36*$Y$3,"") -> 4.8901537 | Z36: =IF(OR((Lecturas!N34-Lecturas!M34) <= 0), "", Lecturas!N34-Lecturas!M34) -> 0.242 | AA36: =IFERROR(Z36*$AA$3,"") -> 3.4088898 | AB36: =IF(OR((Lecturas!O34-Lecturas!N34) < 0), "", Lecturas!O34-Lecturas!N34) -> 0.262 | AC36: =IFERROR(AB36*$AC$3,"") -> 3.3659242 | AD36: =IF(OR((Lecturas!P34-Lecturas!O34) < 0), "", Lecturas!P34-Lecturas!O34) -> 0.225 | AE36: =IFERROR(AD36*$AE$3,"") -> 2.8300919 | AF36: =IF((Lecturas!Q34-Lecturas!P34)<= 0,"",Lecturas!Q34-Lecturas!P34) -> 0.272 | AG36: =IFERROR(AF36*$AG$3,"") -> 3.875429 | AH36: =IF((Lecturas!R34-Lecturas!Q34)<= 0,"",Lecturas!R34-Lecturas!Q34) -> 0.102 | AI36: =IFERROR(AH36*$AI$3,"") -> 1.4192236 | AJ36: =IF((Lecturas!S34-Lecturas!R34)<= 0,"",Lecturas!S34-Lecturas!R34) -> 0.316 | AK36: =IFERROR(AJ36*$AK$3,"") -> 4.5528455 | AL36: =IF((Lecturas!T34-Lecturas!S34)<= 0,"",Lecturas!T34-Lecturas!S34) -> 0.469 | AM36: =IFERROR(AL36*$AM$3,"") -> 4.6566182 | AN36: =IF((Lecturas!U34-Lecturas!T34)<= 0,"",Lecturas!U34-Lecturas!T34) -> 0.468 | AO36: =IFERROR(AN36*$AO$3,"") -> 7.6110555 | AP36: =IF((Lecturas!V34-Lecturas!U34)<= 0,"",Lecturas!V34-Lecturas!U34) -> 0.421 | AQ36: =IFERROR(AP36*$AQ$3,"") -> 5.6090798 | AR36: =IF((Lecturas!W34-Lecturas!V34)<= 0,"",Lecturas!W34-Lecturas!V34) -> 0.309 | AS36: =IFERROR(AR36*$AS$3,"") -> 3.6514302 | AT36: =IF((Lecturas!X34-Lecturas!W34)<= 0,"",Lecturas!X34-Lecturas!W34) -> 0.491 | AU36: =IFERROR(AT36*$AU$3,"") -> 5.9043697 | AV36: =IF((Lecturas!Y34-Lecturas!X34)<= 0,"",Lecturas!Y34-Lecturas!X34) -> 0.322 | AW36: =IFERROR(AV36*$AW$3,"") -> 3.9472218 | AX36: =IF((Lecturas!Z34-Lecturas!Y34)<= 0,"0",Lecturas!Z34-Lecturas!Y34) -> 0.583 | AY36: =IFERROR(AX36*$AY$3,"0") -> 6.7651693 | AZ36: =IF((Lecturas!AA34-Lecturas!Z34)<= 0,"0",Lecturas!AA34-Lecturas!Z34) -> 0.358 | BA36: =IFERROR(AZ36*$BA$3,"0") -> 4.941843 | BB36: =IF((Lecturas!AB34-Lecturas!AA34)<= 0,"0",Lecturas!AB34-Lecturas!AA34) -> 0.35 | BC36: =IFERROR(BB36*$BC$3,"0") -> 5.2449831 | BD36: =IF((Lecturas!AC34-Lecturas!AB34)<= 0,"0",Lecturas!AC34-Lecturas!AB34) -> 0.395 | BE36: =IFERROR(BD36*$BE$3,"0") -> 8.537932 | BF36: =IF((Lecturas!AD34-Lecturas!AC34)<= 0,"0",Lecturas!AD34-Lecturas!AC34) -> 0 | BG36: =IFERROR(BF36*$BG$3,"0") -> 0 | BH36: =IF((Lecturas!AE34-Lecturas!AD34)<= 0,"0",Lecturas!AE34-Lecturas!AD34) -> 0 | BI36: =IFERROR(BH36*$BI$3,"0") -> 0 | BJ36: =IF((Lecturas!AF34-Lecturas!AE34)<= 0,"0",Lecturas!AF34-Lecturas!AE34) -> 0 | BK36: =IFERROR(BJ36*$BK$3,"0") -> 0 | BL36: =IF((Lecturas!AG34-Lecturas!AF34)<= 0,"0",Lecturas!AG34-Lecturas!AF34) -> 0 | BM36: =IFERROR(BL36*$BM$3,"0") -> 0 | BN36: =IF((Lecturas!AH34-Lecturas!AG34)<= 0,"0",Lecturas!AH34-Lecturas!AG34) -> 0 | BO36: =IFERROR(BN36*$BO$3,"0") -> 0
A37: =ROUND(AG37,1) -> 8.8 | B37: =AF37 -> 0.618 | C37: 704 | D37: NOE VELA CORRALES | E37: 2034036 | F37: =Lecturas!D35-Lecturas!C35 -> 0.389 | G37: =F37*$G$3 -> 8.6886757 | H37: =IF((Lecturas!E35-Lecturas!D35) < 0, "", Lecturas!E35-Lecturas!D35) -> 0.253 | I37: =IFERROR(H37*$I$3,"") -> 4.5200195 | J37: =IF(OR((Lecturas!F35-Lecturas!E35) <= 0), "", Lecturas!F35-Lecturas!E35) -> 0.311 | K37: =IFERROR(J37*$K$3,"") -> 3.7820166 | L37: =IF(OR((Lecturas!G35-Lecturas!F35) <= 0), "", Lecturas!G35-Lecturas!F35) -> 0.434 | M37: =IFERROR(L37*$M$3,"") -> 6.7750163 | N37: =IF(OR((Lecturas!H35-Lecturas!G35) <= 0), "", Lecturas!H35-Lecturas!G35) -> 0.272 | O37: =IFERROR(N37*$O$3,"") -> 4.1334948 | P37: =IF(OR((Lecturas!I35-Lecturas!H35) <= 0), "", Lecturas!I35-Lecturas!H35) -> 0.412 | Q37: =IFERROR(P37*$Q$3,"") -> 6.1144701 | R37: =IF(OR((Lecturas!J35-Lecturas!I35) <= 0), "", Lecturas!J35-Lecturas!I35) -> 0.094 | S37: =IFERROR(R37*$S$3,"") -> 1.5577236 | T37: =IF(OR((Lecturas!K35-Lecturas!J35) <= 0), "", Lecturas!K35-Lecturas!J35) -> 0.612 | U37: =IFERROR(T37*$U$3,"") -> 10.747983 | V37: =IF(OR((Lecturas!L35-Lecturas!K35) < 0), "", Lecturas!L35-Lecturas!K35) -> 0.564 | W37: =IFERROR(V37*$W$3,"") -> 6.8940396 | X37: =IF(OR((Lecturas!M35-Lecturas!L35) < 0), "", Lecturas!M35-Lecturas!L35) -> 0.479 | Y37: =IFERROR(X37*$Y$3,"") -> 5.8123663 | Z37: =IF(OR((Lecturas!N35-Lecturas!M35) <= 0), "", Lecturas!N35-Lecturas!M35) -> 0.481 | AA37: =IFERROR(Z37*$AA$3,"") -> 6.7755207 | AB37: =IF(OR((Lecturas!O35-Lecturas!N35) < 0), "", Lecturas!O35-Lecturas!N35) -> 0.407 | AC37: =IFERROR(AB37*$AC$3,"") -> 5.2287449 | AD37: =IF(OR((Lecturas!P35-Lecturas!O35) < 0), "", Lecturas!P35-Lecturas!O35) -> 0.4 | AE37: =IFERROR(AD37*$AE$3,"") -> 5.0312746 | AF37: =IF((Lecturas!Q35-Lecturas!P35)<= 0,"",Lecturas!Q35-Lecturas!P35) -> 0.618 | AG37: =IFERROR(AF37*$AG$3,"") -> 8.8052027 | AH37: =IF((Lecturas!R35-Lecturas!Q35)<= 0,"",Lecturas!R35-Lecturas!Q35) -> 0.958 | AI37: =IFERROR(AH37*$AI$3,"") -> 13.32957 | AJ37: =IF((Lecturas!S35-Lecturas!R35)<= 0,"",Lecturas!S35-Lecturas!R35) -> 0.742 | AK37: =IFERROR(AJ37*$AK$3,"") -> 10.690542 | AL37: =IF((Lecturas!T35-Lecturas!S35)<= 0,"",Lecturas!T35-Lecturas!S35) -> 1.249 | AM37: =IFERROR(AL37*$AM$3,"") -> 12.401101 | AN37: =IF((Lecturas!U35-Lecturas!T35)<= 0,"",Lecturas!U35-Lecturas!T35) -> 0.643 | AO37: =IFERROR(AN37*$AO$3,"") -> 10.45707 | AP37: =IF((Lecturas!V35-Lecturas!U35)<= 0,"",Lecturas!V35-Lecturas!U35) -> 0.714 | AQ37: =IFERROR(AP37*$AQ$3,"") -> 9.5127861 | AR37: =IF((Lecturas!W35-Lecturas!V35)<= 0,"",Lecturas!W35-Lecturas!V35) -> 0.363 | AS37: =IFERROR(AR37*$AS$3,"") -> 4.2895442 | AT37: =IF((Lecturas!X35-Lecturas!W35)<= 0,"",Lecturas!X35-Lecturas!W35) -> 0.553 | AU37: =IFERROR(AT37*$AU$3,"") -> 6.6499316 | AV37: =IF((Lecturas!Y35-Lecturas!X35)<= 0,"",Lecturas!Y35-Lecturas!X35) -> 0.626 | AW37: =IFERROR(AV37*$AW$3,"") -> 7.6737914 | AX37: =IF((Lecturas!Z35-Lecturas!Y35)<= 0,"0",Lecturas!Z35-Lecturas!Y35) -> 0.53 | AY37: =IFERROR(AX37*$AY$3,"0") -> 6.150154 | AZ37: =IF((Lecturas!AA35-Lecturas!Z35)<= 0,"0",Lecturas!AA35-Lecturas!Z35) -> 0.819 | BA37: =IFERROR(AZ37*$BA$3,"0") -> 11.305501 | BB37: =IF((Lecturas!AB35-Lecturas!AA35)<= 0,"0",Lecturas!AB35-Lecturas!AA35) -> 0.642 | BC37: =IFERROR(BB37*$BC$3,"0") -> 9.6207975 | BD37: =IF((Lecturas!AC35-Lecturas!AB35)<= 0,"0",Lecturas!AC35-Lecturas!AB35) -> 0.447 | BE37: =IFERROR(BD37*$BE$3,"0") -> 9.6619129 | BF37: =IF((Lecturas!AD35-Lecturas!AC35)<= 0,"0",Lecturas!AD35-Lecturas!AC35) -> 0 | BG37: =IFERROR(BF37*$BG$3,"0") -> 0 | BH37: =IF((Lecturas!AE35-Lecturas!AD35)<= 0,"0",Lecturas!AE35-Lecturas!AD35) -> 0 | BI37: =IFERROR(BH37*$BI$3,"0") -> 0 | BJ37: =IF((Lecturas!AF35-Lecturas!AE35)<= 0,"0",Lecturas!AF35-Lecturas!AE35) -> 0 | BK37: =IFERROR(BJ37*$BK$3,"0") -> 0 | BL37: =IF((Lecturas!AG35-Lecturas!AF35)<= 0,"0",Lecturas!AG35-Lecturas!AF35) -> 0 | BM37: =IFERROR(BL37*$BM$3,"0") -> 0 | BN37: =IF((Lecturas!AH35-Lecturas!AG35)<= 0,"0",Lecturas!AH35-Lecturas!AG35) -> 0 | BO37: =IFERROR(BN37*$BO$3,"0") -> 0
A38: =ROUND(AG38,1) -> 114.1 | B38: =AF38 -> 8.009 | C38: 801 | D38: MERINO PEÑAFIEL KARINA MIA | E38: 2034023 | F38: =Lecturas!D36-Lecturas!C36 -> 7.142 | G38: =F38*$G$3 -> 159.52319 | H38: =IF((Lecturas!E36-Lecturas!D36) < 0, "", Lecturas!E36-Lecturas!D36) -> 6.725 | I38: =IFERROR(H38*$I$3,"") -> 120.14676 | J38: =IF(OR((Lecturas!F36-Lecturas!E36) <= 0), "", Lecturas!F36-Lecturas!E36) -> 7.333 | K38: =IFERROR(J38*$K$3,"") -> 89.175329 | L38: =IF(OR((Lecturas!G36-Lecturas!F36) <= 0), "", Lecturas!G36-Lecturas!F36) -> 5.893 | M38: =IFERROR(L38*$M$3,"") -> 91.993482 | N38: =IF(OR((Lecturas!H36-Lecturas!G36) <= 0), "", Lecturas!H36-Lecturas!G36) -> 5.942 | O38: =IFERROR(N38*$O$3,"") -> 90.298626 | P38: =IF(OR((Lecturas!I36-Lecturas!H36) <= 0), "", Lecturas!I36-Lecturas!H36) -> 8.777 | Q38: =IFERROR(P38*$Q$3,"") -> 130.25899 | R38: =IF(OR((Lecturas!J36-Lecturas!I36) <= 0), "", Lecturas!J36-Lecturas!I36) -> 6.571 | S38: =IFERROR(R38*$S$3,"") -> 108.89151 | T38: =IF(OR((Lecturas!K36-Lecturas!J36) <= 0), "", Lecturas!K36-Lecturas!J36) -> 5.177 | U38: =IFERROR(T38*$U$3,"") -> 90.918805 | V38: =IF(OR((Lecturas!L36-Lecturas!K36) < 0), "", Lecturas!L36-Lecturas!K36) -> 7.027 | W38: =IFERROR(V38*$W$3,"") -> 85.894355 | X38: =IF(OR((Lecturas!M36-Lecturas!L36) < 0), "", Lecturas!M36-Lecturas!L36) -> 6.253 | Y38: =IFERROR(X38*$Y$3,"") -> 75.876255 | Z38: =IF(OR((Lecturas!N36-Lecturas!M36) <= 0), "", Lecturas!N36-Lecturas!M36) -> 6.514 | AA38: =IFERROR(Z38*$AA$3,"") -> 91.758299 | AB38: =IF(OR((Lecturas!O36-Lecturas!N36) < 0), "", Lecturas!O36-Lecturas!N36) -> 6.718 | AC38: =IFERROR(AB38*$AC$3,"") -> 86.306409 | AD38: =IF(OR((Lecturas!P36-Lecturas!O36) < 0), "", Lecturas!P36-Lecturas!O36) -> 5.697 | AE38: =IFERROR(AD38*$AE$3,"") -> 71.657928 | AF38: =IF((Lecturas!Q36-Lecturas!P36)<= 0,"",Lecturas!Q36-Lecturas!P36) -> 8.009 | AG38: =IFERROR(AF38*$AG$3,"") -> 114.11144 | AH38: =IF((Lecturas!R36-Lecturas!Q36)<= 0,"",Lecturas!R36-Lecturas!Q36) -> 7.168 | AI38: =IFERROR(AH38*$AI$3,"") -> 99.735241 | AJ38: =IF((Lecturas!S36-Lecturas!R36)<= 0,"",Lecturas!S36-Lecturas!R36) -> 7.007 | AK38: =IFERROR(AJ38*$AK$3,"") -> 100.95503 | AL38: =IF((Lecturas!T36-Lecturas!S36)<= 0,"",Lecturas!T36-Lecturas!S36) -> 8.009 | AM38: =IFERROR(AL38*$AM$3,"") -> 79.519947 | AN38: =IF((Lecturas!U36-Lecturas!T36)<= 0,"",Lecturas!U36-Lecturas!T36) -> 5.601 | AO38: =IFERROR(AN38*$AO$3,"") -> 91.088722 | AP38: =IF((Lecturas!V36-Lecturas!U36)<= 0,"",Lecturas!V36-Lecturas!U36) -> 7.235 | AQ38: =IFERROR(AP38*$AQ$3,"") -> 96.393568 | AR38: =IF((Lecturas!W36-Lecturas!V36)<= 0,"",Lecturas!W36-Lecturas!V36) -> 4.195 | AS38: =IFERROR(AR38*$AS$3,"") -> 49.572006 | AT38: =IF((Lecturas!X36-Lecturas!W36)<= 0,"",Lecturas!X36-Lecturas!W36) -> 6.523 | AU38: =IFERROR(AT38*$AU$3,"") -> 78.440332 | AV38: =IF((Lecturas!Y36-Lecturas!X36)<= 0,"",Lecturas!Y36-Lecturas!X36) -> 5.656 | AW38: =IFERROR(AV38*$AW$3,"") -> 69.333809 | AX38: =IF((Lecturas!Z36-Lecturas!Y36)<= 0,"0",Lecturas!Z36-Lecturas!Y36) -> 5.141 | AY38: =IFERROR(AX38*$AY$3,"0") -> 59.656493 | AZ38: =IF((Lecturas!AA36-Lecturas!Z36)<= 0,"0",Lecturas!AA36-Lecturas!Z36) -> 5.315 | BA38: =IFERROR(AZ38*$BA$3,"0") -> 73.368424 | BB38: =IF((Lecturas!AB36-Lecturas!AA36)<= 0,"0",Lecturas!AB36-Lecturas!AA36) -> 5.509 | BC38: =IFERROR(BB38*$BC$3,"0") -> 82.556033 | BD38: =IF((Lecturas!AC36-Lecturas!AB36)<= 0,"0",Lecturas!AC36-Lecturas!AB36) -> 3.899 | BE38: =IFERROR(BD38*$BE$3,"0") -> 84.276954 | BF38: =IF((Lecturas!AD36-Lecturas!AC36)<= 0,"0",Lecturas!AD36-Lecturas!AC36) -> 0 | BG38: =IFERROR(BF38*$BG$3,"0") -> 0 | BH38: =IF((Lecturas!AE36-Lecturas!AD36)<= 0,"0",Lecturas!AE36-Lecturas!AD36) -> 0 | BI38: =IFERROR(BH38*$BI$3,"0") -> 0 | BJ38: =IF((Lecturas!AF36-Lecturas!AE36)<= 0,"0",Lecturas!AF36-Lecturas!AE36) -> 0 | BK38: =IFERROR(BJ38*$BK$3,"0") -> 0 | BL38: =IF((Lecturas!AG36-Lecturas!AF36)<= 0,"0",Lecturas!AG36-Lecturas!AF36) -> 0 | BM38: =IFERROR(BL38*$BM$3,"0") -> 0 | BN38: =IF((Lecturas!AH36-Lecturas!AG36)<= 0,"0",Lecturas!AH36-Lecturas!AG36) -> 0 | BO38: =IFERROR(BN38*$BO$3,"0") -> 0
A39: =ROUND(AG39,1) -> 17.1 | B39: =AF39 -> 1.201 | C39: 802 | D39: CONDOR ARATA MARIA TERESA | E39: 2034084 | F39: =Lecturas!D37-Lecturas!C37 -> 0.788 | G39: =F39*$G$3 -> 17.600711 | H39: =IF((Lecturas!E37-Lecturas!D37) < 0, "", Lecturas!E37-Lecturas!D37) -> 0.401 | I39: =IFERROR(H39*$I$3,"") -> 7.1641415 | J39: =IF(OR((Lecturas!F37-Lecturas!E37) <= 0), "", Lecturas!F37-Lecturas!E37) -> 0.552 | K39: =IFERROR(J39*$K$3,"") -> 6.7127754 | L39: =IF(OR((Lecturas!G37-Lecturas!F37) <= 0), "", Lecturas!G37-Lecturas!F37) -> 1.62 | M39: =IFERROR(L39*$M$3,"") -> 25.289231 | N39: =IF(OR((Lecturas!H37-Lecturas!G37) <= 0), "", Lecturas!H37-Lecturas!G37) -> 0.723 | O39: =IFERROR(N39*$O$3,"") -> 10.987194 | P39: =IF(OR((Lecturas!I37-Lecturas!H37) <= 0), "", Lecturas!I37-Lecturas!H37) -> 1.194 | Q39: =IFERROR(P39*$Q$3,"") -> 17.720091 | R39: =IF(OR((Lecturas!J37-Lecturas!I37) <= 0), "", Lecturas!J37-Lecturas!I37) -> 1.663 | S39: =IFERROR(R39*$S$3,"") -> 27.55845 | T39: =IF(OR((Lecturas!K37-Lecturas!J37) <= 0), "", Lecturas!K37-Lecturas!J37) -> 1.134 | U39: =IFERROR(T39*$U$3,"") -> 19.91538 | V39: =IF(OR((Lecturas!L37-Lecturas!K37) < 0), "", Lecturas!L37-Lecturas!K37) -> 1.613 | W39: =IFERROR(V39*$W$3,"") -> 19.716464 | X39: =IF(OR((Lecturas!M37-Lecturas!L37) < 0), "", Lecturas!M37-Lecturas!L37) -> 1.188 | Y39: =IFERROR(X39*$Y$3,"") -> 14.415639 | Z39: =IF(OR((Lecturas!N37-Lecturas!M37) <= 0), "", Lecturas!N37-Lecturas!M37) -> 2.383 | AA39: =IFERROR(Z39*$AA$3,"") -> 33.567705 | AB39: =IF(OR((Lecturas!O37-Lecturas!N37) < 0), "", Lecturas!O37-Lecturas!N37) -> 1.347 | AC39: =IFERROR(AB39*$AC$3,"") -> 17.304962 | AD39: =IF(OR((Lecturas!P37-Lecturas!O37) < 0), "", Lecturas!P37-Lecturas!O37) -> 1.121 | AE39: =IFERROR(AD39*$AE$3,"") -> 14.100147 | AF39: =IF((Lecturas!Q37-Lecturas!P37)<= 0,"",Lecturas!Q37-Lecturas!P37) -> 1.201 | AG39: =IFERROR(AF39*$AG$3,"") -> 17.111729 | AH39: =IF((Lecturas!R37-Lecturas!Q37)<= 0,"",Lecturas!R37-Lecturas!Q37) -> 1.583 | AI39: =IFERROR(AH39*$AI$3,"") -> 22.025793 | AJ39: =IF((Lecturas!S37-Lecturas!R37)<= 0,"",Lecturas!S37-Lecturas!R37) -> 2.265 | AK39: =IFERROR(AJ39*$AK$3,"") -> 32.633529 | AL39: =IF((Lecturas!T37-Lecturas!S37)<= 0,"",Lecturas!T37-Lecturas!S37) -> 3.434 | AM39: =IFERROR(AL39*$AM$3,"") -> 34.09558 | AN39: =IF((Lecturas!U37-Lecturas!T37)<= 0,"",Lecturas!U37-Lecturas!T37) -> 1.64 | AO39: =IFERROR(AN39*$AO$3,"") -> 26.67122 | AP39: =IF((Lecturas!V37-Lecturas!U37)<= 0,"",Lecturas!V37-Lecturas!U37) -> 1.374 | AQ39: =IFERROR(AP39*$AQ$3,"") -> 18.306118 | AR39: =IF((Lecturas!W37-Lecturas!V37)<= 0,"",Lecturas!W37-Lecturas!V37) -> 0.412 | AS39: =IFERROR(AR39*$AS$3,"") -> 4.8685736 | AT39: =IF((Lecturas!X37-Lecturas!W37)<= 0,"",Lecturas!X37-Lecturas!W37) -> 1.153 | AU39: =IFERROR(AT39*$AU$3,"") -> 13.865047 | AV39: =IF((Lecturas!Y37-Lecturas!X37)<= 0,"",Lecturas!Y37-Lecturas!X37) -> 1.398 | AW39: =IFERROR(AV39*$AW$3,"") -> 17.137317 | AX39: =IF((Lecturas!Z37-Lecturas!Y37)<= 0,"0",Lecturas!Z37-Lecturas!Y37) -> 1.466 | AY39: =IFERROR(AX39*$AY$3,"0") -> 17.011558 | AZ39: =IF((Lecturas!AA37-Lecturas!Z37)<= 0,"0",Lecturas!AA37-Lecturas!Z37) -> 1.645 | BA39: =IFERROR(AZ39*$BA$3,"0") -> 22.707631 | BB39: =IF((Lecturas!AB37-Lecturas!AA37)<= 0,"0",Lecturas!AB37-Lecturas!AA37) -> 1.465 | BC39: =IFERROR(BB39*$BC$3,"0") -> 21.954001 | BD39: =IF((Lecturas!AC37-Lecturas!AB37)<= 0,"0",Lecturas!AC37-Lecturas!AB37) -> 1.274 | BE39: =IFERROR(BD39*$BE$3,"0") -> 27.537533 | BF39: =IF((Lecturas!AD37-Lecturas!AC37)<= 0,"0",Lecturas!AD37-Lecturas!AC37) -> 0 | BG39: =IFERROR(BF39*$BG$3,"0") -> 0 | BH39: =IF((Lecturas!AE37-Lecturas!AD37)<= 0,"0",Lecturas!AE37-Lecturas!AD37) -> 0 | BI39: =IFERROR(BH39*$BI$3,"0") -> 0 | BJ39: =IF((Lecturas!AF37-Lecturas!AE37)<= 0,"0",Lecturas!AF37-Lecturas!AE37) -> 0 | BK39: =IFERROR(BJ39*$BK$3,"0") -> 0 | BL39: =IF((Lecturas!AG37-Lecturas!AF37)<= 0,"0",Lecturas!AG37-Lecturas!AF37) -> 0 | BM39: =IFERROR(BL39*$BM$3,"0") -> 0 | BN39: =IF((Lecturas!AH37-Lecturas!AG37)<= 0,"0",Lecturas!AH37-Lecturas!AG37) -> 0 | BO39: =IFERROR(BN39*$BO$3,"0") -> 0
A40: =ROUND(AG40,1) -> 0 | B40: =AF40 -> 0 | C40: 804 | D40: RICARDINA GUTIERREZ | E40: 170800161 | F40: =Lecturas!D38-Lecturas!C38 -> 0 | G40: =F40*$G$3 -> 0 | H40: =IF((Lecturas!E38-Lecturas!D38) < 0, "", Lecturas!E38-Lecturas!D38) -> 0 | I40: =IFERROR(H40*$I$3,"") -> 0 | J40: =IF(OR((Lecturas!F38-Lecturas!E38) < 0), "", Lecturas!F38-Lecturas!E38) -> 0 | K40: =IFERROR(J40*$K$3,"") -> 0 | L40: =IF(OR((Lecturas!G38-Lecturas!F38) < 0), "", Lecturas!G38-Lecturas!F38) -> 0 | M40: =IFERROR(L40*$M$3,"") -> 0 | N40: =IF(OR((Lecturas!H38-Lecturas!G38) < 0), "", Lecturas!H38-Lecturas!G38) -> 0 | O40: =IFERROR(N40*$O$3,"") -> 0 | P40: =IF(OR((Lecturas!I38-Lecturas!H38) < 0), "", Lecturas!I38-Lecturas!H38) -> 0 | Q40: =IFERROR(P40*$Q$3,"") -> 0 | R40: =IF(OR((Lecturas!J38-Lecturas!I38) < 0), "", Lecturas!J38-Lecturas!I38) -> 0 | S40: =IFERROR(R40*$S$3,"") -> 0 | T40: =IF(OR((Lecturas!K38-Lecturas!J38) < 0), "", Lecturas!K38-Lecturas!J38) -> 0 | U40: =IFERROR(T40*$U$3,"") -> 0 | V40: =IF(OR((Lecturas!L38-Lecturas!K38) < 0), "", Lecturas!L38-Lecturas!K38) -> 0 | W40: =IFERROR(V40*$W$3,"") -> 0 | X40: =IF(OR((Lecturas!M38-Lecturas!L38) < 0), "", Lecturas!M38-Lecturas!L38) -> 0 | Y40: =IFERROR(X40*$Y$3,"") -> 0 | Z40: =IF(OR((Lecturas!N38-Lecturas!M38) < 0), "", Lecturas!N38-Lecturas!M38) -> 0 | AA40: =IFERROR(Z40*$AA$3,"") -> 0 | AB40: =IF(OR((Lecturas!O38-Lecturas!N38) < 0), "", Lecturas!O38-Lecturas!N38) -> 0 | AC40: =IFERROR(AB40*$AC$3,"") -> 0 | AD40: =IF(OR((Lecturas!P38-Lecturas!O38) < 0), "", Lecturas!P38-Lecturas!O38) -> 0 | AE40: =IFERROR(AD40*$AE$3,"") -> 0 | AF40: =IF((Lecturas!Q38-Lecturas!P38)< 0,"",Lecturas!Q38-Lecturas!P38) -> 0 | AG40: =IFERROR(AF40*$AG$3,"") -> 0 | AH40: 0 | AI40: =IFERROR(AH40*$AI$3,"") -> 0 | AJ40: 0 | AK40: =IFERROR(AJ40*$AK$3,"") -> 0 | AL40: 0 | AM40: =IFERROR(AL40*$AM$3,"") -> 0 | AN40: =IF((Lecturas!U38-Lecturas!T38)<= 0,"",Lecturas!U38-Lecturas!T38) | AO40: =IFERROR(AN40*$AO$3,"") -> 0 | AP40: =IF((Lecturas!V38-Lecturas!U38)<= 0,"",Lecturas!V38-Lecturas!U38) | AQ40: =IFERROR(AP40*$AQ$3,"") -> 0 | AR40: =IF((Lecturas!W38-Lecturas!V38)<= 0,"",Lecturas!W38-Lecturas!V38) | AS40: =IFERROR(AR40*$AS$3,"") -> 0 | AT40: =IF((Lecturas!X38-Lecturas!W38)<= 0,"",Lecturas!X38-Lecturas!W38) | AU40: =IFERROR(AT40*$AU$3,"") -> 0 | AV40: =IF((Lecturas!Y38-Lecturas!X38)<= 0,"",Lecturas!Y38-Lecturas!X38) | AW40: =IFERROR(AV40*$AW$3,"") -> 0 | AX40: =IF((Lecturas!Z38-Lecturas!Y38)<= 0,"0",Lecturas!Z38-Lecturas!Y38) -> 0 | AY40: =IFERROR(AX40*$AY$3,"0") -> 0 | AZ40: =IF((Lecturas!AA38-Lecturas!Z38)<= 0,"0",Lecturas!AA38-Lecturas!Z38) -> 0 | BA40: =IFERROR(AZ40*$BA$3,"0") -> 0 | BB40: =IF((Lecturas!AB38-Lecturas!AA38)<= 0,"0",Lecturas!AB38-Lecturas!AA38) -> 0 | BC40: =IFERROR(BB40*$BC$3,"0") -> 0 | BD40: =IF((Lecturas!AC38-Lecturas!AB38)<= 0,"0",Lecturas!AC38-Lecturas!AB38) -> 0 | BE40: =IFERROR(BD40*$BE$3,"0") -> 0 | BF40: =IF((Lecturas!AD38-Lecturas!AC38)<= 0,"0",Lecturas!AD38-Lecturas!AC38) -> 0 | BG40: =IFERROR(BF40*$BG$3,"0") -> 0 | BH40: =IF((Lecturas!AE38-Lecturas!AD38)<= 0,"0",Lecturas!AE38-Lecturas!AD38) -> 0 | BI40: =IFERROR(BH40*$BI$3,"0") -> 0 | BJ40: =IF((Lecturas!AF38-Lecturas!AE38)<= 0,"0",Lecturas!AF38-Lecturas!AE38) -> 0 | BK40: =IFERROR(BJ40*$BK$3,"0") -> 0 | BL40: =IF((Lecturas!AG38-Lecturas!AF38)<= 0,"0",Lecturas!AG38-Lecturas!AF38) -> 0 | BM40: =IFERROR(BL40*$BM$3,"0") -> 0 | BN40: =IF((Lecturas!AH38-Lecturas!AG38)<= 0,"0",Lecturas!AH38-Lecturas!AG38) -> 0 | BO40: =IFERROR(BN40*$BO$3,"0") -> 0
A41: =ROUND(AG41,1) -> 153.7 | B41: =AF41 -> 10.788 | C41: 901 | D41: MARIO CORNEJO VASQUEZ | E41: 2033963 | F41: =Lecturas!D39-Lecturas!C39 -> 1.096 | G41: =F41*$G$3 -> 24.480176 | H41: =IF((Lecturas!E39-Lecturas!D39) < 0, "", Lecturas!E39-Lecturas!D39) -> 1.077 | I41: =IFERROR(H41*$I$3,"") -> 19.241348 | J41: =IF(OR((Lecturas!F39-Lecturas!E39) <= 0), "", Lecturas!F39-Lecturas!E39) -> 1.285 | K41: =IFERROR(J41*$K$3,"") -> 15.62666 | L41: =IF(OR((Lecturas!G39-Lecturas!F39) <= 0), "", Lecturas!G39-Lecturas!F39) -> 3.782 | M41: =IFERROR(L41*$M$3,"") -> 59.039428 | N41: =IF(OR((Lecturas!H39-Lecturas!G39) <= 0), "", Lecturas!H39-Lecturas!G39) -> 7.468 | O41: =IFERROR(N41*$O$3,"") -> 113.48875 | P41: =IF(OR((Lecturas!I39-Lecturas!H39) <= 0), "", Lecturas!I39-Lecturas!H39) -> 5.827 | Q41: =IFERROR(P41*$Q$3,"") -> 86.478197 | R41: =IF(OR((Lecturas!J39-Lecturas!I39) <= 0), "", Lecturas!J39-Lecturas!I39) -> 4.661 | S41: =IFERROR(R41*$S$3,"") -> 77.23989 | T41: =IF(OR((Lecturas!K39-Lecturas!J39) <= 0), "", Lecturas!K39-Lecturas!J39) -> 3.362 | U41: =IFERROR(T41*$U$3,"") -> 59.043659 | V41: =IF(OR((Lecturas!L39-Lecturas!K39) < 0), "", Lecturas!L39-Lecturas!K39) -> 3.67 | W41: =IFERROR(V41*$W$3,"") -> 44.860151 | X41: =IF(OR((Lecturas!M39-Lecturas!L39) < 0), "", Lecturas!M39-Lecturas!L39) -> 3.185 | Y41: =IFERROR(X41*$Y$3,"") -> 38.647989 | Z41: =IF(OR((Lecturas!N39-Lecturas!M39) <= 0), "", Lecturas!N39-Lecturas!M39) -> 4.707 | AA41: =IFERROR(Z41*$AA$3,"") -> 66.304316 | AB41: =IF(OR((Lecturas!O39-Lecturas!N39) < 0), "", Lecturas!O39-Lecturas!N39) -> 6.165 | AC41: =IFERROR(AB41*$AC$3,"") -> 79.201996 | AD41: =IF(OR((Lecturas!P39-Lecturas!O39) < 0), "", Lecturas!P39-Lecturas!O39) -> 7.801 | AE41: =IFERROR(AD41*$AE$3,"") -> 98.122432 | AF41: =IF((Lecturas!Q39-Lecturas!P39)<= 0,"",Lecturas!Q39-Lecturas!P39) -> 10.788 | AG41: =IFERROR(AF41*$AG$3,"") -> 153.70635 | AH41: =IF((Lecturas!R39-Lecturas!Q39)<= 0,"",Lecturas!R39-Lecturas!Q39) -> 9.588 | AI41: =IFERROR(AH41*$AI$3,"") -> 133.40702 | AJ41: =IF((Lecturas!S39-Lecturas!R39)<= 0,"",Lecturas!S39-Lecturas!R39) -> 8.768 | AK41: =IFERROR(AJ41*$AK$3,"") -> 126.32706 | AL41: =IF((Lecturas!T39-Lecturas!S39)<= 0,"",Lecturas!T39-Lecturas!S39) -> 10.093 | AM41: =IFERROR(AL41*$AM$3,"") -> 100.21162 | AN41: =IF((Lecturas!U39-Lecturas!T39)<= 0,"",Lecturas!U39-Lecturas!T39) -> 1.124 | AO41: =IFERROR(AN41*$AO$3,"") -> 18.279544 | AP41: =IF((Lecturas!V39-Lecturas!U39)<= 0,"",Lecturas!V39-Lecturas!U39) -> 1.383 | AQ41: =IFERROR(AP41*$AQ$3,"") -> 18.426027 | AR41: =IF((Lecturas!W39-Lecturas!V39)<= 0,"",Lecturas!W39-Lecturas!V39) -> 0.449 | AS41: =IFERROR(AR41*$AS$3,"") -> 5.3057999 | AT41: =IF((Lecturas!X39-Lecturas!W39)<= 0,"",Lecturas!X39-Lecturas!W39) -> 0.824 | AU41: =IFERROR(AT41*$AU$3,"") -> 9.9087588 | AV41: =IF((Lecturas!Y39-Lecturas!X39)<= 0,"",Lecturas!Y39-Lecturas!X39) -> 1.078 | AW41: =IFERROR(AV41*$AW$3,"") -> 13.214612 | AX41: =IF((Lecturas!Z39-Lecturas!Y39)<= 0,"0",Lecturas!Z39-Lecturas!Y39) -> 0.842 | AY41: =IFERROR(AX41*$AY$3,"0") -> 9.7706219 | AZ41: =IF((Lecturas!AA39-Lecturas!Z39)<= 0,"0",Lecturas!AA39-Lecturas!Z39) -> 0.957 | BA41: =IFERROR(AZ41*$BA$3,"0") -> 13.210457 | BB41: =IF((Lecturas!AB39-Lecturas!AA39)<= 0,"0",Lecturas!AB39-Lecturas!AA39) -> 0.839 | BC41: =IFERROR(BB41*$BC$3,"0") -> 12.572974 | BD41: =IF((Lecturas!AC39-Lecturas!AB39)<= 0,"0",Lecturas!AC39-Lecturas!AB39) -> 0.899 | BE41: =IFERROR(BD41*$BE$3,"0") -> 19.431901 | BF41: =IF((Lecturas!AD39-Lecturas!AC39)<= 0,"0",Lecturas!AD39-Lecturas!AC39) -> 0 | BG41: =IFERROR(BF41*$BG$3,"0") -> 0 | BH41: =IF((Lecturas!AE39-Lecturas!AD39)<= 0,"0",Lecturas!AE39-Lecturas!AD39) -> 0 | BI41: =IFERROR(BH41*$BI$3,"0") -> 0 | BJ41: =IF((Lecturas!AF39-Lecturas!AE39)<= 0,"0",Lecturas!AF39-Lecturas!AE39) -> 0 | BK41: =IFERROR(BJ41*$BK$3,"0") -> 0 | BL41: =IF((Lecturas!AG39-Lecturas!AF39)<= 0,"0",Lecturas!AG39-Lecturas!AF39) -> 0 | BM41: =IFERROR(BL41*$BM$3,"0") -> 0 | BN41: =IF((Lecturas!AH39-Lecturas!AG39)<= 0,"0",Lecturas!AH39-Lecturas!AG39) -> 0 | BO41: =IFERROR(BN41*$BO$3,"0") -> 0
A42: =ROUND(AG42,1) -> 0 | B42: =AF42 -> 0 | C42: 902 | D42: PENAGOS CUADROS NORA BEATRIZ | E42: GA2108000738 | F42: =Lecturas!D40-Lecturas!C40 -> 0 | G42: =F42*$G$3 -> 0 | H42: =IF((Lecturas!E40-Lecturas!D40) < 0, "", Lecturas!E40-Lecturas!D40) -> 0 | I42: =IFERROR(H42*$I$3,"") -> 0 | J42: =IF(OR((Lecturas!F40-Lecturas!E40) < 0), "", Lecturas!F40-Lecturas!E40) -> 0 | K42: =IFERROR(J42*$K$3,"") -> 0 | L42: =IF(OR((Lecturas!G40-Lecturas!F40) < 0), "", Lecturas!G40-Lecturas!F40) -> 0 | M42: =IFERROR(L42*$M$3,"") -> 0 | N42: =IF(OR((Lecturas!H40-Lecturas!G40) < 0), "", Lecturas!H40-Lecturas!G40) -> 0 | O42: =IFERROR(N42*$O$3,"") -> 0 | P42: =IF(OR((Lecturas!I40-Lecturas!H40) < 0), "", Lecturas!I40-Lecturas!H40) -> 0 | Q42: =IFERROR(P42*$Q$3,"") -> 0 | R42: =IF(OR((Lecturas!J40-Lecturas!I40) < 0), "", Lecturas!J40-Lecturas!I40) -> 0 | S42: =IFERROR(R42*$S$3,"") -> 0 | T42: =IF(OR((Lecturas!K40-Lecturas!J40) < 0), "", Lecturas!K40-Lecturas!J40) -> 0 | U42: =IFERROR(T42*$U$3,"") -> 0 | V42: =IF(OR((Lecturas!L40-Lecturas!K40) < 0), "", Lecturas!L40-Lecturas!K40) -> 0 | W42: =IFERROR(V42*$W$3,"") -> 0 | X42: =IF(OR((Lecturas!M40-Lecturas!L40) < 0), "", Lecturas!M40-Lecturas!L40) -> 0 | Y42: =IFERROR(X42*$Y$3,"") -> 0 | Z42: =IF(OR((Lecturas!N40-Lecturas!M40) < 0), "", Lecturas!N40-Lecturas!M40) -> 0 | AA42: =IFERROR(Z42*$AA$3,"") -> 0 | AB42: =IF(OR((Lecturas!O40-Lecturas!N40) < 0), "", Lecturas!O40-Lecturas!N40) -> 0 | AC42: =IFERROR(AB42*$AC$3,"") -> 0 | AD42: =IF(OR((Lecturas!P40-Lecturas!O40) < 0), "", Lecturas!P40-Lecturas!O40) -> 0 | AE42: =IFERROR(AD42*$AE$3,"") -> 0 | AF42: =IF((Lecturas!Q40-Lecturas!P40)< 0,"",Lecturas!Q40-Lecturas!P40) -> 0 | AG42: =IFERROR(AF42*$AG$3,"") -> 0 | AH42: =IF((Lecturas!R40-Lecturas!Q40)<= 0,"",Lecturas!R40-Lecturas!Q40) -> 0.013 | AI42: =IFERROR(AH42*$AI$3,"") -> 0.18088144 | AJ42: 0 | AK42: =IFERROR(AJ42*$AK$3,"") -> 0 | AL42: 0 | AM42: =IFERROR(AL42*$AM$3,"") -> 0 | AN42: =IF((Lecturas!U40-Lecturas!T40)<= 0,"",Lecturas!U40-Lecturas!T40) | AO42: =IFERROR(AN42*$AO$3,"") -> 0 | AP42: =IF((Lecturas!V40-Lecturas!U40)<= 0,"",Lecturas!V40-Lecturas!U40) | AQ42: =IFERROR(AP42*$AQ$3,"") -> 0 | AR42: =IF((Lecturas!W40-Lecturas!V40)<= 0,"",Lecturas!W40-Lecturas!V40) -> 0.001 | AS42: =IFERROR(AR42*$AS$3,"") -> 0.011816926 | AT42: =IF((Lecturas!X40-Lecturas!W40)<= 0,"",Lecturas!X40-Lecturas!W40) -> 0.072 | AU42: =IFERROR(AT42*$AU$3,"") -> 0.86581388 | AV42: =IF((Lecturas!Y40-Lecturas!X40)<= 0,"",Lecturas!Y40-Lecturas!X40) -> 0.199 | AW42: =IFERROR(AV42*$AW$3,"") -> 2.4394321 | AX42: =IF((Lecturas!Z40-Lecturas!Y40)<= 0,"0",Lecturas!Z40-Lecturas!Y40) -> 0.123 | AY42: =IFERROR(AX42*$AY$3,"0") -> 1.4272999 | AZ42: =IF((Lecturas!AA40-Lecturas!Z40)<= 0,"0",Lecturas!AA40-Lecturas!Z40) -> 0.197 | BA42: =IFERROR(AZ42*$BA$3,"0") -> 2.7193941 | BB42: =IF((Lecturas!AB40-Lecturas!AA40)<= 0,"0",Lecturas!AB40-Lecturas!AA40) -> 2.332 | BC42: =IFERROR(BB42*$BC$3,"0") -> 34.946573 | BD42: =IF((Lecturas!AC40-Lecturas!AB40)<= 0,"0",Lecturas!AC40-Lecturas!AB40) -> 3.536 | BE42: =IFERROR(BD42*$BE$3,"0") -> 76.430703 | BF42: =IF((Lecturas!AD40-Lecturas!AC40)<= 0,"0",Lecturas!AD40-Lecturas!AC40) -> 0 | BG42: =IFERROR(BF42*$BG$3,"0") -> 0 | BH42: =IF((Lecturas!AE40-Lecturas!AD40)<= 0,"0",Lecturas!AE40-Lecturas!AD40) -> 0 | BI42: =IFERROR(BH42*$BI$3,"0") -> 0 | BJ42: =IF((Lecturas!AF40-Lecturas!AE40)<= 0,"0",Lecturas!AF40-Lecturas!AE40) -> 0 | BK42: =IFERROR(BJ42*$BK$3,"0") -> 0 | BL42: =IF((Lecturas!AG40-Lecturas!AF40)<= 0,"0",Lecturas!AG40-Lecturas!AF40) -> 0 | BM42: =IFERROR(BL42*$BM$3,"0") -> 0 | BN42: =IF((Lecturas!AH40-Lecturas!AG40)<= 0,"0",Lecturas!AH40-Lecturas!AG40) -> 0 | BO42: =IFERROR(BN42*$BO$3,"0") -> 0
A43: =ROUND(AG43,1) -> 20.3 | B43: =AF43 -> 1.426 | C43: 903 | D43: VALENCIA BALAZAR BRENDA | E43: 2034024 | F43: =Lecturas!D41-Lecturas!C41 -> 1.269 | G43: =F43*$G$3 -> 28.344292 | H43: =IF((Lecturas!E41-Lecturas!D41) < 0, "", Lecturas!E41-Lecturas!D41) -> 1.521 | I43: =IFERROR(H43*$I$3,"") -> 27.173714 | J43: =IF(OR((Lecturas!F41-Lecturas!E41) <= 0), "", Lecturas!F41-Lecturas!E41) -> 2.094 | K43: =IFERROR(J43*$K$3,"") -> 25.464767 | L43: =IF(OR((Lecturas!G41-Lecturas!F41) <= 0), "", Lecturas!G41-Lecturas!F41) -> 1.49 | M43: =IFERROR(L43*$M$3,"") -> 23.259849 | N43: =IF(OR((Lecturas!H41-Lecturas!G41) <= 0), "", Lecturas!H41-Lecturas!G41) -> 1.266 | O43: =IFERROR(N43*$O$3,"") -> 19.238987 | P43: =IF(OR((Lecturas!I41-Lecturas!H41) <= 0), "", Lecturas!I41-Lecturas!H41) -> 1.394 | Q43: =IFERROR(P43*$Q$3,"") -> 20.68828 | R43: =IF(OR((Lecturas!J41-Lecturas!I41) <= 0), "", Lecturas!J41-Lecturas!I41) -> 1.876 | S43: =IFERROR(R43*$S$3,"") -> 31.088186 | T43: =IF(OR((Lecturas!K41-Lecturas!J41) <= 0), "", Lecturas!K41-Lecturas!J41) -> 1.334 | U43: =IFERROR(T43*$U$3,"") -> 23.427793 | V43: =IF(OR((Lecturas!L41-Lecturas!K41) < 0), "", Lecturas!L41-Lecturas!K41) -> 1.54 | W43: =IFERROR(V43*$W$3,"") -> 18.824151 | X43: =IF(OR((Lecturas!M41-Lecturas!L41) < 0), "", Lecturas!M41-Lecturas!L41) -> 2.339 | Y43: =IFERROR(X43*$Y$3,"") -> 28.382306 | Z43: =IF(OR((Lecturas!N41-Lecturas!M41) <= 0), "", Lecturas!N41-Lecturas!M41) -> 2.527 | AA43: =IFERROR(Z43*$AA$3,"") -> 35.596135 | AB43: =IF(OR((Lecturas!O41-Lecturas!N41) < 0), "", Lecturas!O41-Lecturas!N41) -> 1.888 | AC43: =IFERROR(AB43*$AC$3,"") -> 24.25521 | AD43: =IF(OR((Lecturas!P41-Lecturas!O41) < 0), "", Lecturas!P41-Lecturas!O41) -> 1.835 | AE43: =IFERROR(AD43*$AE$3,"") -> 23.080972 | AF43: =IF((Lecturas!Q41-Lecturas!P41)<= 0,"",Lecturas!Q41-Lecturas!P41) -> 1.426 | AG43: =IFERROR(AF43*$AG$3,"") -> 20.317507 | AH43: =IF((Lecturas!R41-Lecturas!Q41)<= 0,"",Lecturas!R41-Lecturas!Q41) -> 1.76 | AI43: =IFERROR(AH43*$AI$3,"") -> 24.488564 | AJ43: =IF((Lecturas!S41-Lecturas!R41)<= 0,"",Lecturas!S41-Lecturas!R41) -> 1.462 | AK43: =IFERROR(AJ43*$AK$3,"") -> 21.064114 | AL43: =IF((Lecturas!T41-Lecturas!S41)<= 0,"",Lecturas!T41-Lecturas!S41) -> 2.119 | AM43: =IFERROR(AL43*$AM$3,"") -> 21.039177 | AN43: =IF((Lecturas!U41-Lecturas!T41)<= 0,"",Lecturas!U41-Lecturas!T41) -> 1.101 | AO43: =IFERROR(AN43*$AO$3,"") -> 17.905496 | AP43: =IF((Lecturas!V41-Lecturas!U41)<= 0,"",Lecturas!V41-Lecturas!U41) -> 0.803 | AQ43: =IFERROR(AP43*$AQ$3,"") -> 10.698554 | AR43: =IF((Lecturas!W41-Lecturas!V41)<= 0,"",Lecturas!W41-Lecturas!V41) -> 1.254 | AS43: =IFERROR(AR43*$AS$3,"") -> 14.818426 | AT43: =IF((Lecturas!X41-Lecturas!W41)<= 0,"",Lecturas!X41-Lecturas!W41) -> 3.596 | AU43: =IFERROR(AT43*$AU$3,"") -> 43.242593 | AV43: =IF((Lecturas!Y41-Lecturas!X41)<= 0,"",Lecturas!Y41-Lecturas!X41) -> 1.91 | AW43: =IFERROR(AV43*$AW$3,"") -> 23.413645 | AX43: =IF((Lecturas!Z41-Lecturas!Y41)<= 0,"0",Lecturas!Z41-Lecturas!Y41) -> 1.173 | AY43: =IFERROR(AX43*$AY$3,"0") -> 13.611567 | AZ43: =IF((Lecturas!AA41-Lecturas!Z41)<= 0,"0",Lecturas!AA41-Lecturas!Z41) -> 1.654 | BA43: =IFERROR(AZ43*$BA$3,"0") -> 22.831867 | BB43: =IF((Lecturas!AB41-Lecturas!AA41)<= 0,"0",Lecturas!AB41-Lecturas!AA41) -> 1.673 | BC43: =IFERROR(BB43*$BC$3,"0") -> 25.071019 | BD43: =IF((Lecturas!AC41-Lecturas!AB41)<= 0,"0",Lecturas!AC41-Lecturas!AB41) -> 1.561 | BE43: =IFERROR(BD43*$BE$3,"0") -> 33.741043 | BF43: =IF((Lecturas!AD41-Lecturas!AC41)<= 0,"0",Lecturas!AD41-Lecturas!AC41) -> 0 | BG43: =IFERROR(BF43*$BG$3,"0") -> 0 | BH43: =IF((Lecturas!AE41-Lecturas!AD41)<= 0,"0",Lecturas!AE41-Lecturas!AD41) -> 0 | BI43: =IFERROR(BH43*$BI$3,"0") -> 0 | BJ43: =IF((Lecturas!AF41-Lecturas!AE41)<= 0,"0",Lecturas!AF41-Lecturas!AE41) -> 0 | BK43: =IFERROR(BJ43*$BK$3,"0") -> 0 | BL43: =IF((Lecturas!AG41-Lecturas!AF41)<= 0,"0",Lecturas!AG41-Lecturas!AF41) -> 0 | BM43: =IFERROR(BL43*$BM$3,"0") -> 0 | BN43: =IF((Lecturas!AH41-Lecturas!AG41)<= 0,"0",Lecturas!AH41-Lecturas!AG41) -> 0 | BO43: =IFERROR(BN43*$BO$3,"0") -> 0
A44: =ROUND(AG44,1) -> 48.7 | B44: =AF44 -> 3.417 | C44: 1002 | D44: SERGIO RIOS CUELLAR - FELIPE | E44: 2034091 | F44: =Lecturas!D42-Lecturas!C42 -> 2.809 | G44: =F44*$G$3 -> 62.74162 | H44: =IF((Lecturas!E42-Lecturas!D42) < 0, "", Lecturas!E42-Lecturas!D42) -> 5.825 | I44: =IFERROR(H44*$I$3,"") -> 104.06764 | J44: =IF(OR((Lecturas!F42-Lecturas!E42) <= 0), "", Lecturas!F42-Lecturas!E42) -> 4.547 | K44: =IFERROR(J44*$K$3,"") -> 55.295271 | L44: =IF(OR((Lecturas!G42-Lecturas!F42) <= 0), "", Lecturas!G42-Lecturas!F42) -> 3.962 | M44: =IFERROR(L44*$M$3,"") -> 61.849342 | N44: =IF(OR((Lecturas!H42-Lecturas!G42) <= 0), "", Lecturas!H42-Lecturas!G42) -> 4.756 | O44: =IFERROR(N44*$O$3,"") -> 72.275373 | P44: =IF(OR((Lecturas!I42-Lecturas!H42) <= 0), "", Lecturas!I42-Lecturas!H42) -> 2.542 | Q44: =IFERROR(P44*$Q$3,"") -> 37.725687 | R44: =IF(OR((Lecturas!J42-Lecturas!I42) <= 0), "", Lecturas!J42-Lecturas!I42) -> 2.802 | S44: =IFERROR(R44*$S$3,"") -> 46.43342 | T44: =IF(OR((Lecturas!K42-Lecturas!J42) <= 0), "", Lecturas!K42-Lecturas!J42) -> 2.357 | U44: =IFERROR(T44*$U$3,"") -> 41.393785 | V44: =IF(OR((Lecturas!L42-Lecturas!K42) < 0), "", Lecturas!L42-Lecturas!K42) -> 3.272 | W44: =IFERROR(V44*$W$3,"") -> 39.995208 | X44: =IF(OR((Lecturas!M42-Lecturas!L42) < 0), "", Lecturas!M42-Lecturas!L42) -> 3.734 | Y44: =IFERROR(X44*$Y$3,"") -> 45.309761 | Z44: =IF(OR((Lecturas!N42-Lecturas!M42) <= 0), "", Lecturas!N42-Lecturas!M42) -> 3.339 | AA44: =IFERROR(Z44*$AA$3,"") -> 47.034228 | AB44: =IF(OR((Lecturas!O42-Lecturas!N42) < 0), "", Lecturas!O42-Lecturas!N42) -> 2.553 | AC44: =IFERROR(AB44*$AC$3,"") -> 32.798491 | AD44: =IF(OR((Lecturas!P42-Lecturas!O42) < 0), "", Lecturas!P42-Lecturas!O42) -> 3.463 | AE44: =IFERROR(AD44*$AE$3,"") -> 43.55826 | AF44: =IF((Lecturas!Q42-Lecturas!P42)<= 0,"",Lecturas!Q42-Lecturas!P42) -> 3.417 | AG44: =IFERROR(AF44*$AG$3,"") -> 48.685077 | AH44: =IF((Lecturas!R42-Lecturas!Q42)<= 0,"",Lecturas!R42-Lecturas!Q42) -> 3.182 | AI44: =IFERROR(AH44*$AI$3,"") -> 44.27421 | AJ44: =IF((Lecturas!S42-Lecturas!R42)<= 0,"",Lecturas!S42-Lecturas!R42) -> 3.059 | AK44: =IFERROR(AJ44*$AK$3,"") -> 44.073274 | AL44: =IF((Lecturas!T42-Lecturas!S42)<= 0,"",Lecturas!T42-Lecturas!S42) -> 4.491 | AM44: =IFERROR(AL44*$AM$3,"") -> 44.590346 | AN44: =IF((Lecturas!U42-Lecturas!T42)<= 0,"",Lecturas!U42-Lecturas!T42) -> 2.716 | AO44: =IFERROR(AN44*$AO$3,"") -> 44.170143 | AP44: =IF((Lecturas!V42-Lecturas!U42)<= 0,"",Lecturas!V42-Lecturas!U42) -> 0.918 | AQ44: =IFERROR(AP44*$AQ$3,"") -> 12.230725 | AR44: =IF((Lecturas!W42-Lecturas!V42)<= 0,"",Lecturas!W42-Lecturas!V42) -> 1.442 | AS44: =IFERROR(AR44*$AS$3,"") -> 17.040008 | AT44: =IF((Lecturas!X42-Lecturas!W42)<= 0,"",Lecturas!X42-Lecturas!W42) -> 0.192 | AU44: =IFERROR(AT44*$AU$3,"") -> 2.308837 | AV44: =IF((Lecturas!Y42-Lecturas!X42)<= 0,"",Lecturas!Y42-Lecturas!X42) -> 12.381 | AW44: =IFERROR(AV44*$AW$3,"") -> 151.7719 | AX44: =IF((Lecturas!Z42-Lecturas!Y42)<= 0,"0",Lecturas!Z42-Lecturas!Y42) -> 4.411 | AY44: =IFERROR(AX44*$AY$3,"0") -> 51.185527 | AZ44: =IF((Lecturas!AA42-Lecturas!Z42)<= 0,"0",Lecturas!AA42-Lecturas!Z42) -> 4.485 | BA44: =IFERROR(AZ44*$BA$3,"0") -> 61.911078 | BB44: =IF((Lecturas!AB42-Lecturas!AA42)<= 0,"0",Lecturas!AB42-Lecturas!AA42) -> 1.656 | BC44: =IFERROR(BB44*$BC$3,"0") -> 24.816263 | BD44: =IF((Lecturas!AC42-Lecturas!AB42)<= 0,"0",Lecturas!AC42-Lecturas!AB42) -> 1.234 | BE44: =IFERROR(BD44*$BE$3,"0") -> 26.672932 | BF44: =IF((Lecturas!AD42-Lecturas!AC42)<= 0,"0",Lecturas!AD42-Lecturas!AC42) -> 0 | BG44: =IFERROR(BF44*$BG$3,"0") -> 0 | BH44: =IF((Lecturas!AE42-Lecturas!AD42)<= 0,"0",Lecturas!AE42-Lecturas!AD42) -> 0 | BI44: =IFERROR(BH44*$BI$3,"0") -> 0 | BJ44: =IF((Lecturas!AF42-Lecturas!AE42)<= 0,"0",Lecturas!AF42-Lecturas!AE42) -> 0 | BK44: =IFERROR(BJ44*$BK$3,"0") -> 0 | BL44: =IF((Lecturas!AG42-Lecturas!AF42)<= 0,"0",Lecturas!AG42-Lecturas!AF42) -> 0 | BM44: =IFERROR(BL44*$BM$3,"0") -> 0 | BN44: =IF((Lecturas!AH42-Lecturas!AG42)<= 0,"0",Lecturas!AH42-Lecturas!AG42) -> 0 | BO44: =IFERROR(BN44*$BO$3,"0") -> 0
A45: =ROUND(AG45,1) -> 185.3 | B45: =AF45 -> 13.002 | C45: 1001 | D45: SERGIO RIOS CUELLAR - MARIA FERNANDA | E45: 2034086 | F45: =Lecturas!D43-Lecturas!C43 -> 3.942 | G45: =F45*$G$3 -> 88.048225 | H45: =IF((Lecturas!E43-Lecturas!D43) < 0, "", Lecturas!E43-Lecturas!D43) -> 6.134 | I45: =IFERROR(H45*$I$3,"") -> 109.58814 | J45: =IF(OR((Lecturas!F43-Lecturas!E43) <= 0), "", Lecturas!F43-Lecturas!E43) -> 3.979 | K45: =IFERROR(J45*$K$3,"") -> 48.387923 | L45: =IF(OR((Lecturas!G43-Lecturas!F43) <= 0), "", Lecturas!G43-Lecturas!F43) -> 8.023 | M45: =IFERROR(L45*$M$3,"") -> 125.24414 | N45: =IF(OR((Lecturas!H43-Lecturas!G43) <= 0), "", Lecturas!H43-Lecturas!G43) -> 9.18 | O45: =IFERROR(N45*$O$3,"") -> 139.50545 | P45: =IF(OR((Lecturas!I43-Lecturas!H43) <= 0), "", Lecturas!I43-Lecturas!H43) -> 9.009 | Q45: =IFERROR(P45*$Q$3,"") -> 133.70209 | R45: =IF(OR((Lecturas!J43-Lecturas!I43) <= 0), "", Lecturas!J43-Lecturas!I43) -> 10.824 | S45: =IFERROR(R45*$S$3,"") -> 179.37022 | T45: =IF(OR((Lecturas!K43-Lecturas!J43) <= 0), "", Lecturas!K43-Lecturas!J43) -> 5.58 | U45: =IFERROR(T45*$U$3,"") -> 97.996316 | V45: =IF(OR((Lecturas!L43-Lecturas!K43) < 0), "", Lecturas!L43-Lecturas!K43) -> 9.051 | W45: =IFERROR(V45*$W$3,"") -> 110.63467 | X45: =IF(OR((Lecturas!M43-Lecturas!L43) < 0), "", Lecturas!M43-Lecturas!L43) -> 11.233 | Y45: =IFERROR(X45*$Y$3,"") -> 136.30545 | Z45: =IF(OR((Lecturas!N43-Lecturas!M43) <= 0), "", Lecturas!N43-Lecturas!M43) -> 10.231 | AA45: =IFERROR(Z45*$AA$3,"") -> 144.11716 | AB45: =IF(OR((Lecturas!O43-Lecturas!N43) < 0), "", Lecturas!O43-Lecturas!N43) -> 11.277 | AC45: =IFERROR(AB45*$AC$3,"") -> 144.87606 | AD45: =IF(OR((Lecturas!P43-Lecturas!O43) < 0), "", Lecturas!P43-Lecturas!O43) -> 10.19 | AE45: =IFERROR(AD45*$AE$3,"") -> 128.17172 | AF45: =IF((Lecturas!Q43-Lecturas!P43)<= 0,"",Lecturas!Q43-Lecturas!P43) -> 13.002 | AG45: =IFERROR(AF45*$AG$3,"") -> 185.25121 | AH45: =IF((Lecturas!R43-Lecturas!Q43)<= 0,"",Lecturas!R43-Lecturas!Q43) -> 11.04 | AI45: =IFERROR(AH45*$AI$3,"") -> 153.61008 | AJ45: =IF((Lecturas!S43-Lecturas!R43)<= 0,"",Lecturas!S43-Lecturas!R43) -> 10.104 | AK45: =IFERROR(AJ45*$AK$3,"") -> 145.57579 | AL45: =IF((Lecturas!T43-Lecturas!S43)<= 0,"",Lecturas!T43-Lecturas!S43) -> 9.762 | AM45: =IFERROR(AL45*$AM$3,"") -> 96.925175 | AN45: =IF((Lecturas!U43-Lecturas!T43)<= 0,"",Lecturas!U43-Lecturas!T43) -> 9.882 | AO45: =IFERROR(AN45*$AO$3,"") -> 160.71037 | AP45: =IF((Lecturas!V43-Lecturas!U43)<= 0,"",Lecturas!V43-Lecturas!U43) -> 10.17 | AQ45: =IFERROR(AP45*$AQ$3,"") -> 135.49725 | AR45: =IF((Lecturas!W43-Lecturas!V43)<= 0,"",Lecturas!W43-Lecturas!V43) -> 6.997 | AS45: =IFERROR(AR45*$AS$3,"") -> 82.683033 | AT45: =IF((Lecturas!X43-Lecturas!W43)<= 0,"",Lecturas!X43-Lecturas!W43) -> 12.742 | AU45: =IFERROR(AT45*$AU$3,"") -> 153.22501 | AV45: =IF((Lecturas!Y43-Lecturas!X43)<= 0,"",Lecturas!Y43-Lecturas!X43) -> 12.606 | AW45: =IFERROR(AV45*$AW$3,"") -> 154.53006 | AX45: =IF((Lecturas!Z43-Lecturas!Y43)<= 0,"0",Lecturas!Z43-Lecturas!Y43) -> 11.177 | AY45: =IFERROR(AX45*$AY$3,"0") -> 129.69862 | AZ45: =IF((Lecturas!AA43-Lecturas!Z43)<= 0,"0",Lecturas!AA43-Lecturas!Z43) -> 12.765 | BA45: =IFERROR(AZ45*$BA$3,"0") -> 176.20845 | BB45: =IF((Lecturas!AB43-Lecturas!AA43)<= 0,"0",Lecturas!AB43-Lecturas!AA43) -> 11.601 | BC45: =IFERROR(BB45*$BC$3,"0") -> 173.84871 | BD45: =IF((Lecturas!AC43-Lecturas!AB43)<= 0,"0",Lecturas!AC43-Lecturas!AB43) -> 7.461 | BE45: =IFERROR(BD45*$BE$3,"0") -> 161.26965 | BF45: =IF((Lecturas!AD43-Lecturas!AC43)<= 0,"0",Lecturas!AD43-Lecturas!AC43) -> 0 | BG45: =IFERROR(BF45*$BG$3,"0") -> 0 | BH45: =IF((Lecturas!AE43-Lecturas!AD43)<= 0,"0",Lecturas!AE43-Lecturas!AD43) -> 0 | BI45: =IFERROR(BH45*$BI$3,"0") -> 0 | BJ45: =IF((Lecturas!AF43-Lecturas!AE43)<= 0,"0",Lecturas!AF43-Lecturas!AE43) -> 0 | BK45: =IFERROR(BJ45*$BK$3,"0") -> 0 | BL45: =IF((Lecturas!AG43-Lecturas!AF43)<= 0,"0",Lecturas!AG43-Lecturas!AF43) -> 0 | BM45: =IFERROR(BL45*$BM$3,"0") -> 0 | BN45: =IF((Lecturas!AH43-Lecturas!AG43)<= 0,"0",Lecturas!AH43-Lecturas!AG43) -> 0 | BO45: =IFERROR(BN45*$BO$3,"0") -> 0
A46: =ROUND(AG46,1) -> 0 | B46: =AF46 -> 0 | C46: 1003 | D46: JAVIER ENRIQUE ESPINOZA PAZ | E46: 2034021 | F46: =Lecturas!D44-Lecturas!C44 -> 0 | G46: =F46*$G$3 -> 0 | H46: =IF((Lecturas!E44-Lecturas!D44) < 0, "", Lecturas!E44-Lecturas!D44) -> 0 | I46: =IFERROR(H46*$I$3,"") -> 0 | J46: =IF(OR((Lecturas!F44-Lecturas!E44) < 0), "", Lecturas!F44-Lecturas!E44) -> 0 | K46: =IFERROR(J46*$K$3,"") -> 0 | L46: =IF(OR((Lecturas!G44-Lecturas!F44) < 0), "", Lecturas!G44-Lecturas!F44) -> 0 | M46: =IFERROR(L46*$M$3,"") -> 0 | N46: =IF(OR((Lecturas!H44-Lecturas!G44) < 0), "", Lecturas!H44-Lecturas!G44) -> 0 | O46: =IFERROR(N46*$O$3,"") -> 0 | P46: =IF(OR((Lecturas!I44-Lecturas!H44) < 0), "", Lecturas!I44-Lecturas!H44) -> 0 | Q46: =IFERROR(P46*$Q$3,"") -> 0 | R46: =IF(OR((Lecturas!J44-Lecturas!I44) < 0), "", Lecturas!J44-Lecturas!I44) -> 0 | S46: =IFERROR(R46*$S$3,"") -> 0 | T46: =IF(OR((Lecturas!K44-Lecturas!J44) < 0), "", Lecturas!K44-Lecturas!J44) -> 0 | U46: =IFERROR(T46*$U$3,"") -> 0 | V46: =IF(OR((Lecturas!L44-Lecturas!K44) < 0), "", Lecturas!L44-Lecturas!K44) -> 0 | W46: =IFERROR(V46*$W$3,"") -> 0 | X46: =IF(OR((Lecturas!M44-Lecturas!L44) < 0), "", Lecturas!M44-Lecturas!L44) -> 0 | Y46: =IFERROR(X46*$Y$3,"") -> 0 | Z46: =IF(OR((Lecturas!N44-Lecturas!M44) < 0), "", Lecturas!N44-Lecturas!M44) -> 0 | AA46: =IFERROR(Z46*$AA$3,"") -> 0 | AB46: =IF(OR((Lecturas!O44-Lecturas!N44) < 0), "", Lecturas!O44-Lecturas!N44) -> 0 | AC46: =IFERROR(AB46*$AC$3,"") -> 0 | AD46: =IF(OR((Lecturas!P44-Lecturas!O44) < 0), "", Lecturas!P44-Lecturas!O44) -> 0 | AE46: =IFERROR(AD46*$AE$3,"") -> 0 | AF46: =IF((Lecturas!Q44-Lecturas!P44)< 0,"",Lecturas!Q44-Lecturas!P44) -> 0 | AG46: =IFERROR(AF46*$AG$3,"") -> 0 | AH46: 0 | AI46: =IFERROR(AH46*$AI$3,"") -> 0 | AJ46: 0 | AK46: =IFERROR(AJ46*$AK$3,"") -> 0 | AL46: 0 | AM46: =IFERROR(AL46*$AM$3,"") -> 0 | AN46: =IF((Lecturas!U44-Lecturas!T44)<= 0,"",Lecturas!U44-Lecturas!T44) | AO46: =IFERROR(AN46*$AO$3,"") -> 0 | AP46: =IF((Lecturas!V44-Lecturas!U44)<= 0,"",Lecturas!V44-Lecturas!U44) | AQ46: =IFERROR(AP46*$AQ$3,"") -> 0 | AR46: =IF((Lecturas!W44-Lecturas!V44)<= 0,"",Lecturas!W44-Lecturas!V44) | AS46: =IFERROR(AR46*$AS$3,"") -> 0 | AT46: =IF((Lecturas!X44-Lecturas!W44)<= 0,"",Lecturas!X44-Lecturas!W44) | AU46: =IFERROR(AT46*$AU$3,"") -> 0 | AV46: =IF((Lecturas!Y44-Lecturas!X44)<= 0,"",Lecturas!Y44-Lecturas!X44) | AW46: =IFERROR(AV46*$AW$3,"") -> 0 | AX46: =IF((Lecturas!Z44-Lecturas!Y44)<= 0,"0",Lecturas!Z44-Lecturas!Y44) -> 0 | AY46: =IFERROR(AX46*$AY$3,"0") -> 0 | AZ46: =IF((Lecturas!AA44-Lecturas!Z44)<= 0,"0",Lecturas!AA44-Lecturas!Z44) -> 0 | BA46: =IFERROR(AZ46*$BA$3,"0") -> 0 | BB46: =IF((Lecturas!AB44-Lecturas!AA44)<= 0,"0",Lecturas!AB44-Lecturas!AA44) -> 0 | BC46: =IFERROR(BB46*$BC$3,"0") -> 0 | BD46: =IF((Lecturas!AC44-Lecturas!AB44)<= 0,"0",Lecturas!AC44-Lecturas!AB44) -> 0 | BE46: =IFERROR(BD46*$BE$3,"0") -> 0 | BF46: =IF((Lecturas!AD44-Lecturas!AC44)<= 0,"0",Lecturas!AD44-Lecturas!AC44) -> 0 | BG46: =IFERROR(BF46*$BG$3,"0") -> 0 | BH46: =IF((Lecturas!AE44-Lecturas!AD44)<= 0,"0",Lecturas!AE44-Lecturas!AD44) -> 0 | BI46: =IFERROR(BH46*$BI$3,"0") -> 0 | BJ46: =IF((Lecturas!AF44-Lecturas!AE44)<= 0,"0",Lecturas!AF44-Lecturas!AE44) -> 0 | BK46: =IFERROR(BJ46*$BK$3,"0") -> 0 | BL46: =IF((Lecturas!AG44-Lecturas!AF44)<= 0,"0",Lecturas!AG44-Lecturas!AF44) -> 0 | BM46: =IFERROR(BL46*$BM$3,"0") -> 0 | BN46: =IF((Lecturas!AH44-Lecturas!AG44)<= 0,"0",Lecturas!AH44-Lecturas!AG44) -> 0 | BO46: =IFERROR(BN46*$BO$3,"0") -> 0
A47: =ROUND(AG47,1) -> 30.6 | B47: =AF47 -> 2.151 | C47: 1101 | D47: AMPARO AMALIA MEJIA BREÑA | E47: 2034054 | F47: =Lecturas!D45-Lecturas!C45 -> 2.691 | G47: =F47*$G$3 -> 60.10598 | H47: =IF((Lecturas!E45-Lecturas!D45) < 0, "", Lecturas!E45-Lecturas!D45) -> 2.584 | I47: =IFERROR(H47*$I$3,"") -> 46.164942 | J47: =IF(OR((Lecturas!F45-Lecturas!E45) <= 0), "", Lecturas!F45-Lecturas!E45) -> 1.279 | K47: =IFERROR(J47*$K$3,"") -> 15.553695 | L47: =IF(OR((Lecturas!G45-Lecturas!F45) <= 0), "", Lecturas!G45-Lecturas!F45) -> 2.624 | M47: =IFERROR(L47*$M$3,"") -> 40.962311 | N47: =IF(OR((Lecturas!H45-Lecturas!G45) <= 0), "", Lecturas!H45-Lecturas!G45) -> 3.159 | O47: =IFERROR(N47*$O$3,"") -> 48.006287 | P47: =IF(OR((Lecturas!I45-Lecturas!H45) <= 0), "", Lecturas!I45-Lecturas!H45) -> 3.055 | Q47: =IFERROR(P47*$Q$3,"") -> 45.339093 | R47: =IF(OR((Lecturas!J45-Lecturas!I45) <= 0), "", Lecturas!J45-Lecturas!I45) -> 2.073 | S47: =IFERROR(R47*$S$3,"") -> 34.352777 | T47: =IF(OR((Lecturas!K45-Lecturas!J45) <= 0), "", Lecturas!K45-Lecturas!J45) -> 2.402 | U47: =IFERROR(T47*$U$3,"") -> 42.184077 | V47: =IF(OR((Lecturas!L45-Lecturas!K45) < 0), "", Lecturas!L45-Lecturas!K45) -> 1.97 | W47: =IFERROR(V47*$W$3,"") -> 24.080245 | X47: =IF(OR((Lecturas!M45-Lecturas!L45) < 0), "", Lecturas!M45-Lecturas!L45) -> 1.959 | Y47: =IFERROR(X47*$Y$3,"") -> 23.771243 | Z47: =IF(OR((Lecturas!N45-Lecturas!M45) <= 0), "", Lecturas!N45-Lecturas!M45) -> 1.535 | AA47: =IFERROR(Z47*$AA$3,"") -> 21.622504 | AB47: =IF(OR((Lecturas!O45-Lecturas!N45) < 0), "", Lecturas!O45-Lecturas!N45) -> 2.565 | AC47: =IFERROR(AB47*$AC$3,"") -> 32.952655 | AD47: =IF(OR((Lecturas!P45-Lecturas!O45) < 0), "", Lecturas!P45-Lecturas!O45) -> 2.875 | AE47: =IFERROR(AD47*$AE$3,"") -> 36.162286 | AF47: =IF((Lecturas!Q45-Lecturas!P45)<= 0,"",Lecturas!Q45-Lecturas!P45) -> 2.151 | AG47: =IFERROR(AF47*$AG$3,"") -> 30.647235 | AH47: =IF((Lecturas!R45-Lecturas!Q45)<= 0,"",Lecturas!R45-Lecturas!Q45) -> 3.649 | AI47: =IFERROR(AH47*$AI$3,"") -> 50.772028 | AJ47: =IF((Lecturas!S45-Lecturas!R45)<= 0,"",Lecturas!S45-Lecturas!R45) -> 1.949 | AK47: =IFERROR(AJ47*$AK$3,"") -> 28.080683 | AL47: =IF((Lecturas!T45-Lecturas!S45)<= 0,"",Lecturas!T45-Lecturas!S45) -> 4.023 | AM47: =IFERROR(AL47*$AM$3,"") -> 39.943657 | AN47: =IF((Lecturas!U45-Lecturas!T45)<= 0,"",Lecturas!U45-Lecturas!T45) -> 3.352 | AO47: =IFERROR(AN47*$AO$3,"") -> 54.513372 | AP47: =IF((Lecturas!V45-Lecturas!U45)<= 0,"",Lecturas!V45-Lecturas!U45) -> 3.442 | AQ47: =IFERROR(AP47*$AQ$3,"") -> 45.858557 | AR47: =IF((Lecturas!W45-Lecturas!V45)<= 0,"",Lecturas!W45-Lecturas!V45) -> 1.653 | AS47: =IFERROR(AR47*$AS$3,"") -> 19.533379 | AT47: =IF((Lecturas!X45-Lecturas!W45)<= 0,"",Lecturas!X45-Lecturas!W45) -> 1.902 | AU47: =IFERROR(AT47*$AU$3,"") -> 22.871917 | AV47: =IF((Lecturas!Y45-Lecturas!X45)<= 0,"",Lecturas!Y45-Lecturas!X45) -> 1.886 | AW47: =IFERROR(AV47*$AW$3,"") -> 23.119442 | AX47: =IF((Lecturas!Z45-Lecturas!Y45)<= 0,"0",Lecturas!Z45-Lecturas!Y45) -> 2.583 | AY47: =IFERROR(AX47*$AY$3,"0") -> 29.973297 | AZ47: =IF((Lecturas!AA45-Lecturas!Z45)<= 0,"0",Lecturas!AA45-Lecturas!Z45) -> 2.681 | BA47: =IFERROR(AZ47*$BA$3,"0") -> 37.008607 | BB47: =IF((Lecturas!AB45-Lecturas!AA45)<= 0,"0",Lecturas!AB45-Lecturas!AA45) -> 2.534 | BC47: =IFERROR(BB47*$BC$3,"0") -> 37.973677 | BD47: =IF((Lecturas!AC45-Lecturas!AB45)<= 0,"0",Lecturas!AC45-Lecturas!AB45) -> 2.26 | BE47: =IFERROR(BD47*$BE$3,"0") -> 48.84994 | BF47: =IF((Lecturas!AD45-Lecturas!AC45)<= 0,"0",Lecturas!AD45-Lecturas!AC45) -> 0 | BG47: =IFERROR(BF47*$BG$3,"0") -> 0 | BH47: =IF((Lecturas!AE45-Lecturas!AD45)<= 0,"0",Lecturas!AE45-Lecturas!AD45) -> 0 | BI47: =IFERROR(BH47*$BI$3,"0") -> 0 | BJ47: =IF((Lecturas!AF45-Lecturas!AE45)<= 0,"0",Lecturas!AF45-Lecturas!AE45) -> 0 | BK47: =IFERROR(BJ47*$BK$3,"0") -> 0 | BL47: =IF((Lecturas!AG45-Lecturas!AF45)<= 0,"0",Lecturas!AG45-Lecturas!AF45) -> 0 | BM47: =IFERROR(BL47*$BM$3,"0") -> 0 | BN47: =IF((Lecturas!AH45-Lecturas!AG45)<= 0,"0",Lecturas!AH45-Lecturas!AG45) -> 0 | BO47: =IFERROR(BN47*$BO$3,"0") -> 0
A48: =ROUND(AG48,1) -> 60.5 | B48: =AF48 -> 4.246 | C48: 1102 | D48: JULIO POTERICO | E48: 2034060 | F48: =Lecturas!D46-Lecturas!C46 -> 4.309 | G48: =F48*$G$3 -> 96.24551 | H48: =IF((Lecturas!E46-Lecturas!D46) < 0, "", Lecturas!E46-Lecturas!D46) -> 4.406 | I48: =IFERROR(H48*$I$3,"") -> 78.716228 | J48: =IF(OR((Lecturas!F46-Lecturas!E46) <= 0), "", Lecturas!F46-Lecturas!E46) -> 4.319 | K48: =IFERROR(J48*$K$3,"") -> 52.522603 | L48: =IF(OR((Lecturas!G46-Lecturas!F46) <= 0), "", Lecturas!G46-Lecturas!F46) -> 3.975 | M48: =IFERROR(L48*$M$3,"") -> 62.052281 | N48: =IF(OR((Lecturas!H46-Lecturas!G46) < 0), "", Lecturas!H46-Lecturas!G46) -> 4.299 | O48: =IFERROR(N48*$O$3,"") -> 65.330494 | P48: =IF(OR((Lecturas!I46-Lecturas!H46) <= 0), "", Lecturas!I46-Lecturas!H46) -> 3.892 | Q48: =IFERROR(P48*$Q$3,"") -> 57.760965 | R48: =IF(OR((Lecturas!J46-Lecturas!I46) <= 0), "", Lecturas!J46-Lecturas!I46) -> 3.259 | S48: =IFERROR(R48*$S$3,"") -> 54.006609 | T48: =IF(OR((Lecturas!K46-Lecturas!J46) < 0), "", Lecturas!K46-Lecturas!J46) -> 0 | U48: =IFERROR(T48*$U$3,"") -> 0 | V48: =IF(OR((Lecturas!L46-Lecturas!K46) < 0), "", Lecturas!L46-Lecturas!K46) -> 0 | W48: =IFERROR(V48*$W$3,"") -> 0 | X48: =IF(OR((Lecturas!M46-Lecturas!L46) < 0), "", Lecturas!M46-Lecturas!L46) -> 0 | Y48: =IFERROR(X48*$Y$3,"") -> 0 | Z48: =IF(OR((Lecturas!N46-Lecturas!M46) < 0), "", Lecturas!N46-Lecturas!M46) -> 0 | AA48: =IFERROR(Z48*$AA$3,"") -> 0 | AB48: =IF(OR((Lecturas!O46-Lecturas!N46) < 0), "", Lecturas!O46-Lecturas!N46) -> 4.228 | AC48: =IFERROR(AB48*$AC$3,"") -> 54.317281 | AD48: =IF(OR((Lecturas!P46-Lecturas!O46) < 0), "", Lecturas!P46-Lecturas!O46) -> 3.532 | AE48: =IFERROR(AD48*$AE$3,"") -> 44.426154 | AF48: =IF((Lecturas!Q46-Lecturas!P46)<= 0,"",Lecturas!Q46-Lecturas!P46) -> 4.246 | AG48: =IFERROR(AF48*$AG$3,"") -> 60.496587 | AH48: =IF((Lecturas!R46-Lecturas!Q46)<= 0,"",Lecturas!R46-Lecturas!Q46) -> 3.693 | AI48: =IFERROR(AH48*$AI$3,"") -> 51.384242 | AJ48: =IF((Lecturas!S46-Lecturas!R46)<= 0,"",Lecturas!S46-Lecturas!R46) -> 4.065 | AK48: =IFERROR(AJ48*$AK$3,"") -> 58.567459 | AL48: =IF((Lecturas!T46-Lecturas!S46)<= 0,"",Lecturas!T46-Lecturas!S46) -> 5.067 | AM48: =IFERROR(AL48*$AM$3,"") -> 50.309349 | AN48: =IF((Lecturas!U46-Lecturas!T46)<= 0,"",Lecturas!U46-Lecturas!T46) -> 3.341 | AO48: =IFERROR(AN48*$AO$3,"") -> 54.33448 | AP48: =IF((Lecturas!V46-Lecturas!U46)<= 0,"",Lecturas!V46-Lecturas!U46) -> 1.167 | AQ48: =IFERROR(AP48*$AQ$3,"") -> 15.548209 | AR48: =IF((Lecturas!W46-Lecturas!V46)<= 0,"",Lecturas!W46-Lecturas!V46) -> 1.558 | AS48: =IFERROR(AR48*$AS$3,"") -> 18.410771 | AT48: =IF((Lecturas!X46-Lecturas!W46)<= 0,"",Lecturas!X46-Lecturas!W46) -> 0.001 | AU48: =IFERROR(AT48*$AU$3,"") -> 0.012025193 | AV48: =IF((Lecturas!Y46-Lecturas!X46)<= 0,"",Lecturas!Y46-Lecturas!X46) | AW48: =IFERROR(AV48*$AW$3,"") -> 0 | AX48: =IF((Lecturas!Z46-Lecturas!Y46)<= 0,"0",Lecturas!Z46-Lecturas!Y46) -> 3.006 | AY48: =IFERROR(AX48*$AY$3,"0") -> 34.881817 | AZ48: =IF((Lecturas!AA46-Lecturas!Z46)<= 0,"0",Lecturas!AA46-Lecturas!Z46) -> 3.726 | BA48: =IFERROR(AZ48*$BA$3,"0") -> 51.433819 | BB48: =IF((Lecturas!AB46-Lecturas!AA46)<= 0,"0",Lecturas!AB46-Lecturas!AA46) -> 3.759 | BC48: =IFERROR(BB48*$BC$3,"0") -> 56.331118 | BD48: =IF((Lecturas!AC46-Lecturas!AB46)<= 0,"0",Lecturas!AC46-Lecturas!AB46) -> 3.534 | BE48: =IFERROR(BD48*$BE$3,"0") -> 76.387473 | BF48: =IF((Lecturas!AD46-Lecturas!AC46)<= 0,"0",Lecturas!AD46-Lecturas!AC46) -> 0 | BG48: =IFERROR(BF48*$BG$3,"0") -> 0 | BH48: =IF((Lecturas!AE46-Lecturas!AD46)<= 0,"0",Lecturas!AE46-Lecturas!AD46) -> 0 | BI48: =IFERROR(BH48*$BI$3,"0") -> 0 | BJ48: =IF((Lecturas!AF46-Lecturas!AE46)<= 0,"0",Lecturas!AF46-Lecturas!AE46) -> 0 | BK48: =IFERROR(BJ48*$BK$3,"0") -> 0 | BL48: =IF((Lecturas!AG46-Lecturas!AF46)<= 0,"0",Lecturas!AG46-Lecturas!AF46) -> 0 | BM48: =IFERROR(BL48*$BM$3,"0") -> 0 | BN48: =IF((Lecturas!AH46-Lecturas!AG46)<= 0,"0",Lecturas!AH46-Lecturas!AG46) -> 0 | BO48: =IFERROR(BN48*$BO$3,"0") -> 0
A49: =ROUND(AG49,1) -> 0 | B49: =AF49 -> 0 | C49: 1103 | D49: JESUS MARGARITA ANTAYHUA | E49: GA202101900060 | F49: =Lecturas!D47-Lecturas!C47 -> 0 | G49: =F49*$G$3 -> 0 | H49: =IF((Lecturas!E47-Lecturas!D47) < 0, "", Lecturas!E47-Lecturas!D47) -> 0 | I49: =IFERROR(H49*$I$3,"") -> 0 | J49: =IF(OR((Lecturas!F47-Lecturas!E47) < 0), "", Lecturas!F47-Lecturas!E47) -> 0 | K49: =IFERROR(J49*$K$3,"") -> 0 | L49: =IF(OR((Lecturas!G47-Lecturas!F47) < 0), "", Lecturas!G47-Lecturas!F47) -> 0 | M49: =IFERROR(L49*$M$3,"") -> 0 | N49: =IF(OR((Lecturas!H47-Lecturas!G47) < 0), "", Lecturas!H47-Lecturas!G47) -> 0 | O49: =IFERROR(N49*$O$3,"") -> 0 | P49: =IF(OR((Lecturas!I47-Lecturas!H47) < 0), "", Lecturas!I47-Lecturas!H47) -> 0 | Q49: =IFERROR(P49*$Q$3,"") -> 0 | R49: =IF(OR((Lecturas!J47-Lecturas!I47) < 0), "", Lecturas!J47-Lecturas!I47) -> 0 | S49: =IFERROR(R49*$S$3,"") -> 0 | T49: =IF(OR((Lecturas!K47-Lecturas!J47) < 0), "", Lecturas!K47-Lecturas!J47) -> 0 | U49: =IFERROR(T49*$U$3,"") -> 0 | V49: =IF(OR((Lecturas!L47-Lecturas!K47) < 0), "", Lecturas!L47-Lecturas!K47) -> 0 | W49: =IFERROR(V49*$W$3,"") -> 0 | X49: =IF(OR((Lecturas!M47-Lecturas!L47) < 0), "", Lecturas!M47-Lecturas!L47) -> 0 | Y49: =IFERROR(X49*$Y$3,"") -> 0 | Z49: =IF(OR((Lecturas!N47-Lecturas!M47) < 0), "", Lecturas!N47-Lecturas!M47) -> 0 | AA49: =IFERROR(Z49*$AA$3,"") -> 0 | AB49: =IF(OR((Lecturas!O47-Lecturas!N47) < 0), "", Lecturas!O47-Lecturas!N47) -> 0 | AC49: =IFERROR(AB49*$AC$3,"") -> 0 | AD49: =IF(OR((Lecturas!P47-Lecturas!O47) < 0), "", Lecturas!P47-Lecturas!O47) -> 0 | AE49: =IFERROR(AD49*$AE$3,"") -> 0 | AF49: =IF((Lecturas!Q47-Lecturas!P47)< 0,"",Lecturas!Q47-Lecturas!P47) -> 0 | AG49: =IFERROR(AF49*$AG$3,"") -> 0 | AH49: 0 | AI49: =IFERROR(AH49*$AI$3,"") -> 0 | AJ49: =IF((Lecturas!S47-Lecturas!R47)<= 0,"",Lecturas!S47-Lecturas!R47) -> 0.005 | AK49: =IFERROR(AJ49*$AK$3,"") -> 0.072038695 | AL49: =IF((Lecturas!T47-Lecturas!S47)<= 0,"",Lecturas!T47-Lecturas!S47) | AM49: =IFERROR(AL49*$AM$3,"") -> 0 | AN49: =IF((Lecturas!U47-Lecturas!T47)<= 0,"",Lecturas!U47-Lecturas!T47) -> 1.63 | AO49: =IFERROR(AN49*$AO$3,"") -> 26.508591 | AP49: =IF((Lecturas!V47-Lecturas!U47)<= 0,"",Lecturas!V47-Lecturas!U47) -> 1.086 | AQ49: =IFERROR(AP49*$AQ$3,"") -> 14.469028 | AR49: =IF((Lecturas!W47-Lecturas!V47)<= 0,"",Lecturas!W47-Lecturas!V47) -> 1.741 | AS49: =IFERROR(AR49*$AS$3,"") -> 20.573269 | AT49: =IF((Lecturas!X47-Lecturas!W47)<= 0,"",Lecturas!X47-Lecturas!W47) -> 0.669 | AU49: =IFERROR(AT49*$AU$3,"") -> 8.044854 | AV49: =IF((Lecturas!Y47-Lecturas!X47)<= 0,"",Lecturas!Y47-Lecturas!X47) | AW49: =IFERROR(AV49*$AW$3,"") -> 0 | AX49: =IF((Lecturas!Z47-Lecturas!Y47)<= 0,"0",Lecturas!Z47-Lecturas!Y47) -> 2.028 | AY49: =IFERROR(AX49*$AY$3,"0") -> 23.533042 | AZ49: =IF((Lecturas!AA47-Lecturas!Z47)<= 0,"0",Lecturas!AA47-Lecturas!Z47) -> 3.655 | BA49: =IFERROR(AZ49*$BA$3,"0") -> 50.453732 | BB49: =IF((Lecturas!AB47-Lecturas!AA47)<= 0,"0",Lecturas!AB47-Lecturas!AA47) -> 2.591 | BC49: =IFERROR(BB49*$BC$3,"0") -> 38.82786 | BD49: =IF((Lecturas!AC47-Lecturas!AB47)<= 0,"0",Lecturas!AC47-Lecturas!AB47) -> 0.859 | BE49: =IFERROR(BD49*$BE$3,"0") -> 18.5673 | BF49: =IF((Lecturas!AD47-Lecturas!AC47)<= 0,"0",Lecturas!AD47-Lecturas!AC47) -> 0 | BG49: =IFERROR(BF49*$BG$3,"0") -> 0 | BH49: =IF((Lecturas!AE47-Lecturas!AD47)<= 0,"0",Lecturas!AE47-Lecturas!AD47) -> 0 | BI49: =IFERROR(BH49*$BI$3,"0") -> 0 | BJ49: =IF((Lecturas!AF47-Lecturas!AE47)<= 0,"0",Lecturas!AF47-Lecturas!AE47) -> 0 | BK49: =IFERROR(BJ49*$BK$3,"0") -> 0 | BL49: =IF((Lecturas!AG47-Lecturas!AF47)<= 0,"0",Lecturas!AG47-Lecturas!AF47) -> 0 | BM49: =IFERROR(BL49*$BM$3,"0") -> 0 | BN49: =IF((Lecturas!AH47-Lecturas!AG47)<= 0,"0",Lecturas!AH47-Lecturas!AG47) -> 0 | BO49: =IFERROR(BN49*$BO$3,"0") -> 0
A50: =ROUND(AG50,1) -> 160.2 | B50: =AF50 -> 11.241 | C50: 1201 | D50: CARMEN DE LA TORRE MAYORGA | E50: 2034058 | F50: =Lecturas!D48-Lecturas!C48 -> 7.425 | G50: =F50*$G$3 -> 165.84426 | H50: =IF((Lecturas!E48-Lecturas!D48) < 0, "", Lecturas!E48-Lecturas!D48) -> 6.8 | I50: =IFERROR(H50*$I$3,"") -> 121.48669 | J50: =IF(OR((Lecturas!F48-Lecturas!E48) <= 0), "", Lecturas!F48-Lecturas!E48) -> 10.201 | K50: =IFERROR(J50*$K$3,"") -> 124.05258 | L50: =IF(OR((Lecturas!G48-Lecturas!F48) <= 0), "", Lecturas!G48-Lecturas!F48) -> 5.296 | M50: =IFERROR(L50*$M$3,"") -> 82.673932 | N50: =IF(OR((Lecturas!H48-Lecturas!G48) < 0), "", Lecturas!H48-Lecturas!G48) -> 0 | O50: =IFERROR(N50*$O$3,"") -> 0 | P50: =IF(OR((Lecturas!I48-Lecturas!H48) <= 0), "", Lecturas!I48-Lecturas!H48) -> 6.904 | Q50: =IFERROR(P50*$Q$3,"") -> 102.4619 | R50: =IF(OR((Lecturas!J48-Lecturas!I48) <= 0), "", Lecturas!J48-Lecturas!I48) -> 15.315 | S50: =IFERROR(R50*$S$3,"") -> 253.79295 | T50: =IF(OR((Lecturas!K48-Lecturas!J48) <= 0), "", Lecturas!K48-Lecturas!J48) -> 11.93 | U50: =IFERROR(T50*$U$3,"") -> 209.51542 | V50: =IF(OR((Lecturas!L48-Lecturas!K48) < 0), "", Lecturas!L48-Lecturas!K48) -> 6.423 | W50: =IFERROR(V50*$W$3,"") -> 78.511376 | X50: =IF(OR((Lecturas!M48-Lecturas!L48) < 0), "", Lecturas!M48-Lecturas!L48) -> 8.006 | Y50: =IFERROR(X50*$Y$3,"") -> 97.147817 | Z50: =IF(OR((Lecturas!N48-Lecturas!M48) <= 0), "", Lecturas!N48-Lecturas!M48) -> 9.061 | AA50: =IFERROR(Z50*$AA$3,"") -> 127.63616 | AB50: =IF(OR((Lecturas!O48-Lecturas!N48) < 0), "", Lecturas!O48-Lecturas!N48) -> 9.728 | AC50: =IFERROR(AB50*$AC$3,"") -> 124.976 | AD50: =IF(OR((Lecturas!P48-Lecturas!O48) < 0), "", Lecturas!P48-Lecturas!O48) -> 10.617 | AE50: =IFERROR(AD50*$AE$3,"") -> 133.54261 | AF50: =IF((Lecturas!Q48-Lecturas!P48)<= 0,"",Lecturas!Q48-Lecturas!P48) -> 11.241 | AG50: =IFERROR(AF50*$AG$3,"") -> 160.16065 | AH50: =IF((Lecturas!R48-Lecturas!Q48)<= 0,"",Lecturas!R48-Lecturas!Q48) -> 9.783 | AI50: =IFERROR(AH50*$AI$3,"") -> 136.12024 | AJ50: =IF((Lecturas!S48-Lecturas!R48)<= 0,"",Lecturas!S48-Lecturas!R48) -> 11.615 | AK50: =IFERROR(AJ50*$AK$3,"") -> 167.34589 | AL50: =IF((Lecturas!T48-Lecturas!S48)<= 0,"",Lecturas!T48-Lecturas!S48) -> 11.257 | AM50: =IFERROR(AL50*$AM$3,"") -> 111.76877 | AN50: =IF((Lecturas!U48-Lecturas!T48)<= 0,"",Lecturas!U48-Lecturas!T48) -> 8.948 | AO50: =IFERROR(AN50*$AO$3,"") -> 145.52078 | AP50: =IF((Lecturas!V48-Lecturas!U48)<= 0,"",Lecturas!V48-Lecturas!U48) -> 8.303 | AQ50: =IFERROR(AP50*$AQ$3,"") -> 110.62278 | AR50: =IF((Lecturas!W48-Lecturas!V48)<= 0,"",Lecturas!W48-Lecturas!V48) -> 11.003 | AS50: =IFERROR(AR50*$AS$3,"") -> 130.02164 | AT50: =IF((Lecturas!X48-Lecturas!W48)<= 0,"",Lecturas!X48-Lecturas!W48) -> 8.502 | AU50: =IFERROR(AT50*$AU$3,"") -> 102.23819 | AV50: =IF((Lecturas!Y48-Lecturas!X48)<= 0,"",Lecturas!Y48-Lecturas!X48) -> 8.378 | AW50: =IFERROR(AV50*$AW$3,"") -> 102.70132 | AX50: =IF((Lecturas!Z48-Lecturas!Y48)<= 0,"0",Lecturas!Z48-Lecturas!Y48) -> 9.023 | AY50: =IFERROR(AX50*$AY$3,"0") -> 104.70347 | AZ50: =IF((Lecturas!AA48-Lecturas!Z48)<= 0,"0",Lecturas!AA48-Lecturas!Z48) -> 9.794 | BA50: =IFERROR(AZ50*$BA$3,"0") -> 135.19668 | BB50: =IF((Lecturas!AB48-Lecturas!AA48)<= 0,"0",Lecturas!AB48-Lecturas!AA48) -> 10.104 | BC50: =IFERROR(BB50*$BC$3,"0") -> 151.41517 | BD50: =IF((Lecturas!AC48-Lecturas!AB48)<= 0,"0",Lecturas!AC48-Lecturas!AB48) -> 0.729 | BE50: =IFERROR(BD50*$BE$3,"0") -> 15.757348 | BF50: =IF((Lecturas!AD48-Lecturas!AC48)<= 0,"0",Lecturas!AD48-Lecturas!AC48) -> 0 | BG50: =IFERROR(BF50*$BG$3,"0") -> 0 | BH50: =IF((Lecturas!AE48-Lecturas!AD48)<= 0,"0",Lecturas!AE48-Lecturas!AD48) -> 0 | BI50: =IFERROR(BH50*$BI$3,"0") -> 0 | BJ50: =IF((Lecturas!AF48-Lecturas!AE48)<= 0,"0",Lecturas!AF48-Lecturas!AE48) -> 0 | BK50: =IFERROR(BJ50*$BK$3,"0") -> 0 | BL50: =IF((Lecturas!AG48-Lecturas!AF48)<= 0,"0",Lecturas!AG48-Lecturas!AF48) -> 0 | BM50: =IFERROR(BL50*$BM$3,"0") -> 0 | BN50: =IF((Lecturas!AH48-Lecturas!AG48)<= 0,"0",Lecturas!AH48-Lecturas!AG48) -> 0 | BO50: =IFERROR(BN50*$BO$3,"0") -> 0
A51: =ROUND(AG51,1) -> 0 | B51: =AF51 -> 0 | C51: 1202 | D51: MARIA INDACOCHEA PALACIOS VDA DE | E51: 2034076 | F51: =Lecturas!D49-Lecturas!C49 -> 0 | G51: =F51*$G$3 -> 0 | H51: =IF((Lecturas!E49-Lecturas!D49) < 0, "", Lecturas!E49-Lecturas!D49) -> 0 | I51: =IFERROR(H51*$I$3,"") -> 0 | J51: =IF(OR((Lecturas!F49-Lecturas!E49) < 0), "", Lecturas!F49-Lecturas!E49) -> 0 | K51: =IFERROR(J51*$K$3,"") -> 0 | L51: =IF(OR((Lecturas!G49-Lecturas!F49) < 0), "", Lecturas!G49-Lecturas!F49) -> 0 | M51: =IFERROR(L51*$M$3,"") -> 0 | N51: =IF(OR((Lecturas!H49-Lecturas!G49) < 0), "", Lecturas!H49-Lecturas!G49) -> 0 | O51: =IFERROR(N51*$O$3,"") -> 0 | P51: =IF(OR((Lecturas!I49-Lecturas!H49) <= 0), "", Lecturas!I49-Lecturas!H49) -> 0.294 | Q51: =IFERROR(P51*$Q$3,"") -> 4.3632384 | R51: =IF(OR((Lecturas!J49-Lecturas!I49) <= 0), "", Lecturas!J49-Lecturas!I49) -> 2.324 | S51: =IFERROR(R51*$S$3,"") -> 38.51223 | T51: =IF(OR((Lecturas!K49-Lecturas!J49) <= 0), "", Lecturas!K49-Lecturas!J49) -> 1.329 | U51: =IFERROR(T51*$U$3,"") -> 23.339983 | V51: =IF(OR((Lecturas!L49-Lecturas!K49) < 0), "", Lecturas!L49-Lecturas!K49) -> 1.176 | W51: =IFERROR(V51*$W$3,"") -> 14.374806 | X51: =IF(OR((Lecturas!M49-Lecturas!L49) < 0), "", Lecturas!M49-Lecturas!L49) -> 0.43 | Y51: =IFERROR(X51*$Y$3,"") -> 5.2177818 | Z51: =IF(OR((Lecturas!N49-Lecturas!M49) < 0), "", Lecturas!N49-Lecturas!M49) -> 0 | AA51: =IFERROR(Z51*$AA$3,"") -> 0 | AB51: =IF(OR((Lecturas!O49-Lecturas!N49) < 0), "", Lecturas!O49-Lecturas!N49) -> 0 | AC51: =IFERROR(AB51*$AC$3,"") -> 0 | AD51: =IF(OR((Lecturas!P49-Lecturas!O49) < 0), "", Lecturas!P49-Lecturas!O49) -> 0 | AE51: =IFERROR(AD51*$AE$3,"") -> 0 | AF51: =IF((Lecturas!Q49-Lecturas!P49)< 0,"",Lecturas!Q49-Lecturas!P49) -> 0 | AG51: =IFERROR(AF51*$AG$3,"") -> 0 | AH51: 0 | AI51: =IFERROR(AH51*$AI$3,"") -> 0 | AJ51: =IF((Lecturas!S49-Lecturas!R49)<= 0,"",Lecturas!S49-Lecturas!R49) | AK51: =IFERROR(AJ51*$AK$3,"") -> 0 | AL51: =IF((Lecturas!T49-Lecturas!S49)<= 0,"",Lecturas!T49-Lecturas!S49) | AM51: =IFERROR(AL51*$AM$3,"") -> 0 | AN51: =IF((Lecturas!U49-Lecturas!T49)<= 0,"",Lecturas!U49-Lecturas!T49) -> 0.001 | AO51: =IFERROR(AN51*$AO$3,"") -> 0.016262939 | AP51: =IF((Lecturas!V49-Lecturas!U49)<= 0,"",Lecturas!V49-Lecturas!U49) -> 0.328 | AQ51: =IFERROR(AP51*$AQ$3,"") -> 4.3700194 | AR51: =IF((Lecturas!W49-Lecturas!V49)<= 0,"",Lecturas!W49-Lecturas!V49) -> 1.953 | AS51: =IFERROR(AR51*$AS$3,"") -> 23.078457 | AT51: =IF((Lecturas!X49-Lecturas!W49)<= 0,"",Lecturas!X49-Lecturas!W49) -> 1.09 | AU51: =IFERROR(AT51*$AU$3,"") -> 13.10746 | AV51: =IF((Lecturas!Y49-Lecturas!X49)<= 0,"",Lecturas!Y49-Lecturas!X49) -> 0.041 | AW51: =IFERROR(AV51*$AW$3,"") -> 0.50259656 | AX51: =IF((Lecturas!Z49-Lecturas!Y49)<= 0,"0",Lecturas!Z49-Lecturas!Y49) -> 0 | AY51: =IFERROR(AX51*$AY$3,"0") -> 0 | AZ51: =IF((Lecturas!AA49-Lecturas!Z49)<= 0,"0",Lecturas!AA49-Lecturas!Z49) -> 0 | BA51: =IFERROR(AZ51*$BA$3,"0") -> 0 | BB51: =IF((Lecturas!AB49-Lecturas!AA49)<= 0,"0",Lecturas!AB49-Lecturas!AA49) -> 0 | BC51: =IFERROR(BB51*$BC$3,"0") -> 0 | BD51: =IF((Lecturas!AC49-Lecturas!AB49)<= 0,"0",Lecturas!AC49-Lecturas!AB49) -> 0 | BE51: =IFERROR(BD51*$BE$3,"0") -> 0 | BF51: =IF((Lecturas!AD49-Lecturas!AC49)<= 0,"0",Lecturas!AD49-Lecturas!AC49) -> 0 | BG51: =IFERROR(BF51*$BG$3,"0") -> 0 | BH51: =IF((Lecturas!AE49-Lecturas!AD49)<= 0,"0",Lecturas!AE49-Lecturas!AD49) -> 0 | BI51: =IFERROR(BH51*$BI$3,"0") -> 0 | BJ51: =IF((Lecturas!AF49-Lecturas!AE49)<= 0,"0",Lecturas!AF49-Lecturas!AE49) -> 0 | BK51: =IFERROR(BJ51*$BK$3,"0") -> 0 | BL51: =IF((Lecturas!AG49-Lecturas!AF49)<= 0,"0",Lecturas!AG49-Lecturas!AF49) -> 0 | BM51: =IFERROR(BL51*$BM$3,"0") -> 0 | BN51: =IF((Lecturas!AH49-Lecturas!AG49)<= 0,"0",Lecturas!AH49-Lecturas!AG49) -> 0 | BO51: =IFERROR(BN51*$BO$3,"0") -> 0
A52: =ROUND(AG52,1) -> 58.4 | B52: =AF52 -> 4.102 | C52: 1203 | D52: MARIA VIRGINIA BARANDIARAN PAGADOR | E52: 2034077 | F52: =Lecturas!D50-Lecturas!C50 -> 2.724 | G52: =F52*$G$3 -> 60.843066 | H52: =IF((Lecturas!E50-Lecturas!D50) < 0, "", Lecturas!E50-Lecturas!D50) -> 1.815 | I52: =IFERROR(H52*$I$3,"") -> 32.426227 | J52: =IF(OR((Lecturas!F50-Lecturas!E50) <= 0), "", Lecturas!F50-Lecturas!E50) -> 3.812 | K52: =IFERROR(J52*$K$3,"") -> 46.357065 | L52: =IF(OR((Lecturas!G50-Lecturas!F50) <= 0), "", Lecturas!G50-Lecturas!F50) -> 3.635 | M52: =IFERROR(L52*$M$3,"") -> 56.744664 | N52: =IF(OR((Lecturas!H50-Lecturas!G50) <= 0), "", Lecturas!H50-Lecturas!G50) -> 3.962 | O52: =IFERROR(N52*$O$3,"") -> 60.209215 | P52: =IF(OR((Lecturas!I50-Lecturas!H50) <= 0), "", Lecturas!I50-Lecturas!H50) -> 3.434 | Q52: =IFERROR(P52*$Q$3,"") -> 50.963812 | R52: =IF(OR((Lecturas!J50-Lecturas!I50) <= 0), "", Lecturas!J50-Lecturas!I50) -> 3.859 | S52: =IFERROR(R52*$S$3,"") -> 63.949525 | T52: =IF(OR((Lecturas!K50-Lecturas!J50) <= 0), "", Lecturas!K50-Lecturas!J50) -> 3.095 | U52: =IFERROR(T52*$U$3,"") -> 54.354588 | V52: =IF(OR((Lecturas!L50-Lecturas!K50) < 0), "", Lecturas!L50-Lecturas!K50) -> 3.175 | W52: =IFERROR(V52*$W$3,"") -> 38.809531 | X52: =IF(OR((Lecturas!M50-Lecturas!L50) < 0), "", Lecturas!M50-Lecturas!L50) -> 3.171 | Y52: =IFERROR(X52*$Y$3,"") -> 38.478107 | Z52: =IF(OR((Lecturas!N50-Lecturas!M50) <= 0), "", Lecturas!N50-Lecturas!M50) -> 3.076 | AA52: =IFERROR(Z52*$AA$3,"") -> 43.329525 | AB52: =IF(OR((Lecturas!O50-Lecturas!N50) < 0), "", Lecturas!O50-Lecturas!N50) -> 2.892 | AC52: =IFERROR(AB52*$AC$3,"") -> 37.153637 | AD52: =IF(OR((Lecturas!P50-Lecturas!O50) < 0), "", Lecturas!P50-Lecturas!O50) -> 1.466 | AE52: =IFERROR(AD52*$AE$3,"") -> 18.439621 | AF52: =IF((Lecturas!Q50-Lecturas!P50)<= 0,"",Lecturas!Q50-Lecturas!P50) -> 4.102 | AG52: =IFERROR(AF52*$AG$3,"") -> 58.444889 | AH52: =IF((Lecturas!R50-Lecturas!Q50)<= 0,"",Lecturas!R50-Lecturas!Q50) -> 4.377 | AI52: =IFERROR(AH52*$AI$3,"") -> 60.901388 | AJ52: =IF((Lecturas!S50-Lecturas!R50)<= 0,"",Lecturas!S50-Lecturas!R50) -> 4.153 | AK52: =IFERROR(AJ52*$AK$3,"") -> 59.83534 | AL52: =IF((Lecturas!T50-Lecturas!S50)<= 0,"",Lecturas!T50-Lecturas!S50) -> 3.417 | AM52: =IFERROR(AL52*$AM$3,"") -> 33.92679 | AN52: =IF((Lecturas!U50-Lecturas!T50)<= 0,"",Lecturas!U50-Lecturas!T50) -> 2.838 | AO52: =IFERROR(AN52*$AO$3,"") -> 46.154221 | AP52: =IF((Lecturas!V50-Lecturas!U50)<= 0,"",Lecturas!V50-Lecturas!U50) -> 2.119 | AQ52: =IFERROR(AP52*$AQ$3,"") -> 28.231924 | AR52: =IF((Lecturas!W50-Lecturas!V50)<= 0,"",Lecturas!W50-Lecturas!V50) -> 1.959 | AS52: =IFERROR(AR52*$AS$3,"") -> 23.149359 | AT52: =IF((Lecturas!X50-Lecturas!W50)<= 0,"",Lecturas!X50-Lecturas!W50) -> 1.044 | AU52: =IFERROR(AT52*$AU$3,"") -> 12.554301 | AV52: =IF((Lecturas!Y50-Lecturas!X50)<= 0,"",Lecturas!Y50-Lecturas!X50) -> 1.077 | AW52: =IFERROR(AV52*$AW$3,"") -> 13.202354 | AX52: =IF((Lecturas!Z50-Lecturas!Y50)<= 0,"0",Lecturas!Z50-Lecturas!Y50) -> 2.029 | AY52: =IFERROR(AX52*$AY$3,"0") -> 23.544646 | AZ52: =IF((Lecturas!AA50-Lecturas!Z50)<= 0,"0",Lecturas!AA50-Lecturas!Z50) -> 2.924 | BA52: =IFERROR(AZ52*$BA$3,"0") -> 40.362986 | BB52: =IF((Lecturas!AB50-Lecturas!AA50)<= 0,"0",Lecturas!AB50-Lecturas!AA50) -> 3.166 | BC52: =IFERROR(BB52*$BC$3,"0") -> 47.444618 | BD52: =IF((Lecturas!AC50-Lecturas!AB50)<= 0,"0",Lecturas!AC50-Lecturas!AB50) -> 2.866 | BE52: =IFERROR(BD52*$BE$3,"0") -> 61.948641 | BF52: =IF((Lecturas!AD50-Lecturas!AC50)<= 0,"0",Lecturas!AD50-Lecturas!AC50) -> 0 | BG52: =IFERROR(BF52*$BG$3,"0") -> 0 | BH52: =IF((Lecturas!AE50-Lecturas!AD50)<= 0,"0",Lecturas!AE50-Lecturas!AD50) -> 0 | BI52: =IFERROR(BH52*$BI$3,"0") -> 0 | BJ52: =IF((Lecturas!AF50-Lecturas!AE50)<= 0,"0",Lecturas!AF50-Lecturas!AE50) -> 0 | BK52: =IFERROR(BJ52*$BK$3,"0") -> 0 | BL52: =IF((Lecturas!AG50-Lecturas!AF50)<= 0,"0",Lecturas!AG50-Lecturas!AF50) -> 0 | BM52: =IFERROR(BL52*$BM$3,"0") -> 0 | BN52: =IF((Lecturas!AH50-Lecturas!AG50)<= 0,"0",Lecturas!AH50-Lecturas!AG50) -> 0 | BO52: =IFERROR(BN52*$BO$3,"0") -> 0
A53: =ROUND(AG53,1) -> 0 | B53: =AF53 -> 0 | C53: 1301 | D53: Laura Cristina Herrera Vega | E53: 2034059 | F53: =Lecturas!D51-Lecturas!C51 -> 0 | G53: =F53*$G$3 -> 0 | H53: =IF((Lecturas!E51-Lecturas!D51) < 0, "", Lecturas!E51-Lecturas!D51) -> 0 | I53: =IFERROR(H53*$I$3,"") -> 0 | J53: =IF(OR((Lecturas!F51-Lecturas!E51) < 0), "", Lecturas!F51-Lecturas!E51) -> 0 | K53: =IFERROR(J53*$K$3,"") -> 0 | L53: =IF(OR((Lecturas!G51-Lecturas!F51) < 0), "", Lecturas!G51-Lecturas!F51) -> 0 | M53: =IFERROR(L53*$M$3,"") -> 0 | N53: =IF(OR((Lecturas!H51-Lecturas!G51) < 0), "", Lecturas!H51-Lecturas!G51) -> 0 | O53: =IFERROR(N53*$O$3,"") -> 0 | P53: =IF(OR((Lecturas!I51-Lecturas!H51) < 0), "", Lecturas!I51-Lecturas!H51) -> 0 | Q53: =IFERROR(P53*$Q$3,"") -> 0 | R53: =IF(OR((Lecturas!J51-Lecturas!I51) < 0), "", Lecturas!J51-Lecturas!I51) -> 0 | S53: =IFERROR(R53*$S$3,"") -> 0 | T53: =IF(OR((Lecturas!K51-Lecturas!J51) < 0), "", Lecturas!K51-Lecturas!J51) -> 0 | U53: =IFERROR(T53*$U$3,"") -> 0 | V53: =IF(OR((Lecturas!L51-Lecturas!K51) < 0), "", Lecturas!L51-Lecturas!K51) -> 0 | W53: =IFERROR(V53*$W$3,"") -> 0 | X53: =IF(OR((Lecturas!M51-Lecturas!L51) < 0), "", Lecturas!M51-Lecturas!L51) -> 0 | Y53: =IFERROR(X53*$Y$3,"") -> 0 | Z53: =IF(OR((Lecturas!N51-Lecturas!M51) < 0), "", Lecturas!N51-Lecturas!M51) -> 0 | AA53: =IFERROR(Z53*$AA$3,"") -> 0 | AB53: =IF(OR((Lecturas!O51-Lecturas!N51) < 0), "", Lecturas!O51-Lecturas!N51) -> 0 | AC53: =IFERROR(AB53*$AC$3,"") -> 0 | AD53: =IF(OR((Lecturas!P51-Lecturas!O51) < 0), "", Lecturas!P51-Lecturas!O51) -> 0 | AE53: =IFERROR(AD53*$AE$3,"") -> 0 | AF53: =IF((Lecturas!Q51-Lecturas!P51)< 0,"",Lecturas!Q51-Lecturas!P51) -> 0 | AG53: =IFERROR(AF53*$AG$3,"") -> 0 | AH53: 0 | AI53: =IFERROR(AH53*$AI$3,"") -> 0 | AJ53: =IF((Lecturas!S51-Lecturas!R51)<= 0,"",Lecturas!S51-Lecturas!R51) | AK53: =IFERROR(AJ53*$AK$3,"") -> 0 | AL53: =IF((Lecturas!T51-Lecturas!S51)<= 0,"",Lecturas!T51-Lecturas!S51) | AM53: =IFERROR(AL53*$AM$3,"") -> 0 | AN53: =IF((Lecturas!U51-Lecturas!T51)<= 0,"",Lecturas!U51-Lecturas!T51) | AO53: =IFERROR(AN53*$AO$3,"") -> 0 | AP53: =IF((Lecturas!V51-Lecturas!U51)<= 0,"",Lecturas!V51-Lecturas!U51) | AQ53: =IFERROR(AP53*$AQ$3,"") -> 0 | AR53: =IF((Lecturas!W51-Lecturas!V51)<= 0,"",Lecturas!W51-Lecturas!V51) | AS53: =IFERROR(AR53*$AS$3,"") -> 0 | AT53: =IF((Lecturas!X51-Lecturas!W51)<= 0,"",Lecturas!X51-Lecturas!W51) | AU53: =IFERROR(AT53*$AU$3,"") -> 0 | AV53: =IF((Lecturas!Y51-Lecturas!X51)<= 0,"",Lecturas!Y51-Lecturas!X51) | AW53: =IFERROR(AV53*$AW$3,"") -> 0 | AX53: =IF((Lecturas!Z51-Lecturas!Y51)<= 0,"0",Lecturas!Z51-Lecturas!Y51) -> 0 | AY53: =IFERROR(AX53*$AY$3,"0") -> 0 | AZ53: =IF((Lecturas!AA51-Lecturas!Z51)<= 0,"0",Lecturas!AA51-Lecturas!Z51) -> 0 | BA53: =IFERROR(AZ53*$BA$3,"0") -> 0 | BB53: =IF((Lecturas!AB51-Lecturas!AA51)<= 0,"0",Lecturas!AB51-Lecturas!AA51) -> 0 | BC53: =IFERROR(BB53*$BC$3,"0") -> 0 | BD53: =IF((Lecturas!AC51-Lecturas!AB51)<= 0,"0",Lecturas!AC51-Lecturas!AB51) -> 0 | BE53: =IFERROR(BD53*$BE$3,"0") -> 0 | BF53: =IF((Lecturas!AD51-Lecturas!AC51)<= 0,"0",Lecturas!AD51-Lecturas!AC51) -> 0 | BG53: =IFERROR(BF53*$BG$3,"0") -> 0 | BH53: =IF((Lecturas!AE51-Lecturas!AD51)<= 0,"0",Lecturas!AE51-Lecturas!AD51) -> 0 | BI53: =IFERROR(BH53*$BI$3,"0") -> 0 | BJ53: =IF((Lecturas!AF51-Lecturas!AE51)<= 0,"0",Lecturas!AF51-Lecturas!AE51) -> 0 | BK53: =IFERROR(BJ53*$BK$3,"0") -> 0 | BL53: =IF((Lecturas!AG51-Lecturas!AF51)<= 0,"0",Lecturas!AG51-Lecturas!AF51) -> 0 | BM53: =IFERROR(BL53*$BM$3,"0") -> 0 | BN53: =IF((Lecturas!AH51-Lecturas!AG51)<= 0,"0",Lecturas!AH51-Lecturas!AG51) -> 0 | BO53: =IFERROR(BN53*$BO$3,"0") -> 0
A54: =ROUND(AG54,1) -> 34.2 | B54: =AF54 -> 2.401 | C54: 1302 | D54: RANDY RUSSELL CIVELLO | E54: 2034066 | F54: =Lecturas!D52-Lecturas!C52 -> 5.106 | G54: =F54*$G$3 -> 114.04724 | H54: =IF((Lecturas!E52-Lecturas!D52) < 0, "", Lecturas!E52-Lecturas!D52) -> 8.375 | I54: =IFERROR(H54*$I$3,"") -> 149.62515 | J54: =IF(OR((Lecturas!F52-Lecturas!E52) <= 0), "", Lecturas!F52-Lecturas!E52) -> 8.383 | K54: =IFERROR(J54*$K$3,"") -> 101.9442 | L54: =IF(OR((Lecturas!G52-Lecturas!F52) <= 0), "", Lecturas!G52-Lecturas!F52) -> 8.288 | M54: =IFERROR(L54*$M$3,"") -> 129.38096 | N54: =IF(OR((Lecturas!H52-Lecturas!G52) <= 0), "", Lecturas!H52-Lecturas!G52) -> 8.085 | O54: =IFERROR(N54*$O$3,"") -> 122.86509 | P54: =IF(OR((Lecturas!I52-Lecturas!H52) <= 0), "", Lecturas!I52-Lecturas!H52) -> 5.414 | Q54: =IFERROR(P54*$Q$3,"") -> 80.348886 | R54: =IF(OR((Lecturas!J52-Lecturas!I52) <= 0), "", Lecturas!J52-Lecturas!I52) -> 6.317 | S54: =IFERROR(R54*$S$3,"") -> 104.68234 | T54: =IF(OR((Lecturas!K52-Lecturas!J52) <= 0), "", Lecturas!K52-Lecturas!J52) -> 3.957 | U54: =IFERROR(T54*$U$3,"") -> 69.493087 | V54: =IF(OR((Lecturas!L52-Lecturas!K52) < 0), "", Lecturas!L52-Lecturas!K52) -> 5.684 | W54: =IFERROR(V54*$W$3,"") -> 69.478229 | X54: =IF(OR((Lecturas!M52-Lecturas!L52) < 0), "", Lecturas!M52-Lecturas!L52) -> 5.045 | Y54: =IFERROR(X54*$Y$3,"") -> 61.217929 | Z54: =IF(OR((Lecturas!N52-Lecturas!M52) <= 0), "", Lecturas!N52-Lecturas!M52) -> 6.294 | AA54: =IFERROR(Z54*$AA$3,"") -> 88.659309 | AB54: =IF(OR((Lecturas!O52-Lecturas!N52) < 0), "", Lecturas!O52-Lecturas!N52) -> 5.27 | AC54: =IFERROR(AB54*$AC$3,"") -> 67.703896 | AD54: =IF(OR((Lecturas!P52-Lecturas!O52) < 0), "", Lecturas!P52-Lecturas!O52) -> 2.813 | AE54: =IFERROR(AD54*$AE$3,"") -> 35.382438 | AF54: =IF((Lecturas!Q52-Lecturas!P52)<= 0,"",Lecturas!Q52-Lecturas!P52) -> 2.401 | AG54: =IFERROR(AF54*$AG$3,"") -> 34.20921 | AH54: 0 | AI54: =IFERROR(AH54*$AI$3,"") -> 0 | AJ54: =IF((Lecturas!S52-Lecturas!R52)<= 0,"",Lecturas!S52-Lecturas!R52) -> 1.054 | AK54: =IFERROR(AJ54*$AK$3,"") -> 15.185757 | AL54: =IF((Lecturas!T52-Lecturas!S52)<= 0,"",Lecturas!T52-Lecturas!S52) -> 1.521 | AM54: =IFERROR(AL54*$AM$3,"") -> 15.101741 | AN54: =IF((Lecturas!U52-Lecturas!T52)<= 0,"",Lecturas!U52-Lecturas!T52) -> 3.314 | AO54: =IFERROR(AN54*$AO$3,"") -> 53.895381 | AP54: =IF((Lecturas!V52-Lecturas!U52)<= 0,"",Lecturas!V52-Lecturas!U52) -> 3.13 | AQ54: =IFERROR(AP54*$AQ$3,"") -> 41.70171 | AR54: =IF((Lecturas!W52-Lecturas!V52)<= 0,"",Lecturas!W52-Lecturas!V52) -> 5.91 | AS54: =IFERROR(AR54*$AS$3,"") -> 69.838034 | AT54: =IF((Lecturas!X52-Lecturas!W52)<= 0,"",Lecturas!X52-Lecturas!W52) -> 2.684 | AU54: =IFERROR(AT54*$AU$3,"") -> 32.275617 | AV54: =IF((Lecturas!Y52-Lecturas!X52)<= 0,"",Lecturas!Y52-Lecturas!X52) -> 3.123 | AW54: =IFERROR(AV54*$AW$3,"") -> 38.283148 | AX54: =IF((Lecturas!Z52-Lecturas!Y52)<= 0,"0",Lecturas!Z52-Lecturas!Y52) -> 4.003 | AY54: =IFERROR(AX54*$AY$3,"0") -> 46.451068 | AZ54: =IF((Lecturas!AA52-Lecturas!Z52)<= 0,"0",Lecturas!AA52-Lecturas!Z52) -> 4.183 | BA54: =IFERROR(AZ54*$BA$3,"0") -> 57.742261 | BB54: =IF((Lecturas!AB52-Lecturas!AA52)<= 0,"0",Lecturas!AB52-Lecturas!AA52) -> 2.457 | BC54: =IFERROR(BB54*$BC$3,"0") -> 36.819781 | BD54: =IF((Lecturas!AC52-Lecturas!AB52)<= 0,"0",Lecturas!AC52-Lecturas!AB52) -> 2.845 | BE54: =IFERROR(BD54*$BE$3,"0") -> 61.494725 | BF54: =IF((Lecturas!AD52-Lecturas!AC52)<= 0,"0",Lecturas!AD52-Lecturas!AC52) -> 0 | BG54: =IFERROR(BF54*$BG$3,"0") -> 0 | BH54: =IF((Lecturas!AE52-Lecturas!AD52)<= 0,"0",Lecturas!AE52-Lecturas!AD52) -> 0 | BI54: =IFERROR(BH54*$BI$3,"0") -> 0 | BJ54: =IF((Lecturas!AF52-Lecturas!AE52)<= 0,"0",Lecturas!AF52-Lecturas!AE52) -> 0 | BK54: =IFERROR(BJ54*$BK$3,"0") -> 0 | BL54: =IF((Lecturas!AG52-Lecturas!AF52)<= 0,"0",Lecturas!AG52-Lecturas!AF52) -> 0 | BM54: =IFERROR(BL54*$BM$3,"0") -> 0 | BN54: =IF((Lecturas!AH52-Lecturas!AG52)<= 0,"0",Lecturas!AH52-Lecturas!AG52) -> 0 | BO54: =IFERROR(BN54*$BO$3,"0") -> 0
A55: =ROUND(AG55,1) -> 49.5 | B55: =AF55 -> 3.477 | C55: 1303 | D55: JUAN CARLOS RENGIFO SANTA MARIA | E55: 2034067 | F55: =Lecturas!D53-Lecturas!C53 -> 13.318 | G55: =F55*$G$3 -> 297.46988 | H55: =IF((Lecturas!E53-Lecturas!D53) < 0, "", Lecturas!E53-Lecturas!D53) -> 0.955 | I55: =IFERROR(H55*$I$3,"") -> 17.061734 | J55: =IF(OR((Lecturas!F53-Lecturas!E53) < 0), "", Lecturas!F53-Lecturas!E53) -> 0 | K55: =IFERROR(J55*$K$3,"") -> 0 | L55: =IF(OR((Lecturas!G53-Lecturas!F53) < 0), "", Lecturas!G53-Lecturas!F53) -> 0 | M55: =IFERROR(L55*$M$3,"") -> 0 | N55: =IF(OR((Lecturas!H53-Lecturas!G53) <= 0), "", Lecturas!H53-Lecturas!G53) -> 0.127 | O55: =IFERROR(N55*$O$3,"") -> 1.9299774 | P55: =IF(OR((Lecturas!I53-Lecturas!H53) <= 0), "", Lecturas!I53-Lecturas!H53) -> 1.784 | Q55: =IFERROR(P55*$Q$3,"") -> 26.476249 | R55: =IF(OR((Lecturas!J53-Lecturas!I53) <= 0), "", Lecturas!J53-Lecturas!I53) -> 4.477 | S55: =IFERROR(R55*$S$3,"") -> 74.190729 | T55: =IF(OR((Lecturas!K53-Lecturas!J53) <= 0), "", Lecturas!K53-Lecturas!J53) -> 4.439 | U55: =IFERROR(T55*$U$3,"") -> 77.958001 | V55: =IF(OR((Lecturas!L53-Lecturas!K53) < 0), "", Lecturas!L53-Lecturas!K53) -> 3.579 | W55: =IFERROR(V55*$W$3,"") -> 43.747815 | X55: =IF(OR((Lecturas!M53-Lecturas!L53) < 0), "", Lecturas!M53-Lecturas!L53) -> 2.535 | Y55: =IFERROR(X55*$Y$3,"") -> 30.760644 | Z55: =IF(OR((Lecturas!N53-Lecturas!M53) <= 0), "", Lecturas!N53-Lecturas!M53) -> 4.379 | AA55: =IFERROR(Z55*$AA$3,"") -> 61.684003 | AB55: =IF(OR((Lecturas!O53-Lecturas!N53) < 0), "", Lecturas!O53-Lecturas!N53) -> 3.671 | AC55: =IFERROR(AB55*$AC$3,"") -> 47.161481 | AD55: =IF(OR((Lecturas!P53-Lecturas!O53) < 0), "", Lecturas!P53-Lecturas!O53) -> 5.527 | AE55: =IFERROR(AD55*$AE$3,"") -> 69.519636 | AF55: =IF((Lecturas!Q53-Lecturas!P53)<= 0,"",Lecturas!Q53-Lecturas!P53) -> 3.477 | AG55: =IFERROR(AF55*$AG$3,"") -> 49.539951 | AH55: =IF((Lecturas!R53-Lecturas!Q53)<= 0,"",Lecturas!R53-Lecturas!Q53) -> 4.853 | AI55: =IFERROR(AH55*$AI$3,"") -> 67.524431 | AJ55: =IF((Lecturas!S53-Lecturas!R53)<= 0,"",Lecturas!S53-Lecturas!R53) -> 5.063 | AK55: =IFERROR(AJ55*$AK$3,"") -> 72.946383 | AL55: =IF((Lecturas!T53-Lecturas!S53)<= 0,"",Lecturas!T53-Lecturas!S53) -> 4.057 | AM55: =IFERROR(AL55*$AM$3,"") -> 40.281237 | AN55: =IF((Lecturas!U53-Lecturas!T53)<= 0,"",Lecturas!U53-Lecturas!T53) -> 3.277 | AO55: =IFERROR(AN55*$AO$3,"") -> 53.293652 | AP55: =IF((Lecturas!V53-Lecturas!U53)<= 0,"",Lecturas!V53-Lecturas!U53) -> 3.085 | AQ55: =IFERROR(AP55*$AQ$3,"") -> 41.102164 | AR55: =IF((Lecturas!W53-Lecturas!V53)<= 0,"",Lecturas!W53-Lecturas!V53) -> 2.153 | AS55: =IFERROR(AR55*$AS$3,"") -> 25.441842 | AT55: =IF((Lecturas!X53-Lecturas!W53)<= 0,"",Lecturas!X53-Lecturas!W53) -> 4.564 | AU55: =IFERROR(AT55*$AU$3,"") -> 54.88298 | AV55: =IF((Lecturas!Y53-Lecturas!X53)<= 0,"",Lecturas!Y53-Lecturas!X53) -> 1.949 | AW55: =IFERROR(AV55*$AW$3,"") -> 23.891724 | AX55: =IF((Lecturas!Z53-Lecturas!Y53)<= 0,"0",Lecturas!Z53-Lecturas!Y53) -> 2.838 | AY55: =IFERROR(AX55*$AY$3,"0") -> 32.932334 | AZ55: =IF((Lecturas!AA53-Lecturas!Z53)<= 0,"0",Lecturas!AA53-Lecturas!Z53) -> 3.203 | BA55: =IFERROR(AZ55*$BA$3,"0") -> 44.214311 | BB55: =IF((Lecturas!AB53-Lecturas!AA53)<= 0,"0",Lecturas!AB53-Lecturas!AA53) -> 2.577 | BC55: =IFERROR(BB55*$BC$3,"0") -> 38.618061 | BD55: =IF((Lecturas!AC53-Lecturas!AB53)<= 0,"0",Lecturas!AC53-Lecturas!AB53) -> 4.359 | BE55: =IFERROR(BD55*$BE$3,"0") -> 94.219862 | BF55: =IF((Lecturas!AD53-Lecturas!AC53)<= 0,"0",Lecturas!AD53-Lecturas!AC53) -> 0 | BG55: =IFERROR(BF55*$BG$3,"0") -> 0 | BH55: =IF((Lecturas!AE53-Lecturas!AD53)<= 0,"0",Lecturas!AE53-Lecturas!AD53) -> 0 | BI55: =IFERROR(BH55*$BI$3,"0") -> 0 | BJ55: =IF((Lecturas!AF53-Lecturas!AE53)<= 0,"0",Lecturas!AF53-Lecturas!AE53) -> 0 | BK55: =IFERROR(BJ55*$BK$3,"0") -> 0 | BL55: =IF((Lecturas!AG53-Lecturas!AF53)<= 0,"0",Lecturas!AG53-Lecturas!AF53) -> 0 | BM55: =IFERROR(BL55*$BM$3,"0") -> 0 | BN55: =IF((Lecturas!AH53-Lecturas!AG53)<= 0,"0",Lecturas!AH53-Lecturas!AG53) -> 0 | BO55: =IFERROR(BN55*$BO$3,"0") -> 0
